Workbook
Name Business_Day_End: '01_Parameters'!$C$14
Name Business_Day_Start: '01_Parameters'!$C$13
Name Duplicate_Amount_Tolerance: '01_Parameters'!$C$15
Name High_Value_AP_Threshold: '01_Parameters'!$C$8
Name High_Value_GL_Threshold: '01_Parameters'!$C$7
Name Invoice_Posting_Review_Limit: '01_Parameters'!$C$19
Name Near_Duplicate_Window: '01_Parameters'!$C$16
Name Reporting_End_Date: '01_Parameters'!$C$6
Name Reporting_Start_Date: '01_Parameters'!$C$5
Name Round_Number_Threshold: '01_Parameters'!$C$17
Name Year_End_Window_End: '01_Parameters'!$C$10
Name Year_End_Window_Start: '01_Parameters'!$C$9

Sheet 00_Read_Me
A1: Audit Data Analytics: General Ledger & Accounts Payable Exception Detection
A2: Namaa Retail Company — شركة نماء للتجزئة | Educational portfolio simulation | Reporting period: 01-Jan-2025 to 31-Dec-2025 | Currency: SAR
A4: Project information | B4: Value
A5: Fictional entity | B5: Namaa Retail Company — شركة نماء للتجزئة
A6: Project type | B6: Educational audit analytics simulation using synthetic financial transaction data
A7: Prepared by | B7: Accounting Student — Educational Portfolio Project.
A8: Preparation date | B8: 22-Oct-2026
A9: Tools used | B9: Microsoft Excel-compatible workbook, Python for deterministic synthetic data generation, PDF memorandum
A11: Project objective | B11: The purpose of this project is to demonstrate how audit data analytics can be used to examine accounting transaction populations, identify unusual patterns, and prioritize transactions for further audit investigation.
A13: Audit analytics workflow | B13: Data preparation → Data validation → Risk-based test design → Exception detection → Exception investigation → Evaluation → Reporting
A15: Worksheet guide | B15: 00_Read_Me: overview and instructions | 01_Parameters: editable thresholds | 02_GL_Data: GL population | 03_AP_Data: AP population | 04_Analytics_Tests: test catalog and results | 05_Exception_Register: traceable flagged items | 06_Dashboard: executive summary | 07_Audit_Memo: memo summary
A16: How to use | B16: 1. Review assumptions. 2. Review synthetic datasets. 3. Inspect test catalog. 4. Review flagged transactions. 5. Record simulated follow-up. 6. Review dashboard and memo.
A18: Important disclaimer | B18: Educational audit analytics simulation using synthetic transaction data. The transactions, counterparties, and exceptions are fictional and do not represent actual records of a real company. An identified anomaly does not, by itself, establish fraud or a financial statement misstatement.
A19: Data limitations | B19: All transactional data are synthetic; this is not an actual audit engagement; tests are illustrative and do not replace professional judgment; real-world completeness and accuracy would need separate assessment; a flag is not automatically an error or evidence of fraud.
... A21: Additional worksheet | B21: 99_Internal_QA is hidden and contains the planted-anomaly validation key and build checks; it is not presented as an audit working paper.

Sheet 01_Parameters
A1: Parameters & Assumptions
A2: Editable screening assumptions. Thresholds are screening rules and are not financial statement materiality.
A4: Parameter_ID | B4: Parameter_Name | C4: Parameter_Value | D4: Unit | E4: Rationale | F4: Source_Type | G4: Last_Updated
A5: P001 | B5: Reporting Start Date | C5: 45658 | D5: Date | E5: Beginning of reporting period | F5: Simulation assumption | G5: 46317
A6: P002 | B6: Reporting End Date | C6: 46022 | D6: Date | E6: End of reporting period | F6: Simulation assumption | G6: 46317
A7: P003 | B7: High-Value GL Threshold | C7: 100000 | D7: SAR | E7: Screen individually large journal lines | F7: Simulation assumption | G7: 46317
A8: P004 | B8: High-Value AP Threshold | C8: 75000 | D8: SAR | E8: Screen large supplier invoices | F8: Simulation assumption | G8: 46317
A9: P005 | B9: Year-End Window Start | C9: 46007 | D9: Date | E9: Illustrative year-end review window | F9: Simulation assumption | G9: 46317
A10: P006 | B10: Year-End Window End | C10: 46022 | D10: Date | E10: End of reporting period | F10: Simulation assumption | G10: 46317
A11: P007 | B11: Weekend Testing | C11: Enabled | D11: Setting | E11: Flag Friday or Saturday postings | F11: Saudi calendar convention | G11: 46317
A12: P008 | B12: After-Hours Testing | C12: Enabled | D12: Setting | E12: Flag timestamps outside business hours | F12: Simulation assumption | G12: 46317
A13: P009 | B13: Business Day Start | C13: 8 | D13: Hour | E13: Normal business hours start | F13: Simulation assumption | G13: 46317
A14: P010 | B14: Business Day End | C14: 18 | D14: Hour | E14: Normal business hours end | F14: Simulation assumption | G14: 46317
A15: P011 | B15: Duplicate Amount Tolerance | C15: 0.01 | D15: SAR | E15: Exact amount comparison tolerance | F15: Simulation assumption | G15: 46317
A16: P012 | B16: Near-Duplicate Window | C16: 90 | D16: Days | E16: Look-back for potentially repeated invoices | F16: Simulation assumption | G16: 46317
A17: P013 | B17: Round-Number Threshold | C17: 10000 | D17: SAR | E17: Minimum amount and multiple for round-number screen | F17: Simulation assumption | G17: 46317
A18: P014 | B18: Reporting Currency | C18: SAR | D18: Currency | E18: All monetary amounts | F18: Simulation assumption | G18: 46317
A19: P015 | B19: Invoice-to-Posting Review Limit | C19: 30 | D19: Days | E19: Flag unusually long invoice-to-posting lag | F19: Simulation assumption | G19: 46317

Sheet 02_GL_Data
A1: 02_GL_Data — Synthetic General Ledger Population
A2: Approximately 500 balanced journal entries and 1,000 lines. Formula-driven screening indicators are in columns V:Z.
A4: Journal_ID | B4: Journal_Line_ID | C4: Posting_Date | D4: Document_Date | E4: Fiscal_Year | F4: Fiscal_Period | G4: Account_Code | H4: Account_Name | I4: Account_Type | J4: Debit | K4: Credit | L4: Signed_Amount | M4: Description | N4: Document_Reference | O4: Source_Module | P4: Created_By | Q4: Approved_By | R4: Creation_Timestamp | S4: Approval_Status | T4: Vendor_ID | U4: Invoice_ID | V4: Is_Year_End | W4: Is_Weekend_Posting | X4: Is_After_Hours | Y4: Is_High_Value | Z4: Is_Round_Number
A5: JE-00001 | B5: JE-00001-01 | C5: 45822 | D5: 45820 | E5: 2025 | F5: 6 | G5: 6600 | H5: Other Operating Expenses | I5: Expense | J5: 169781.06 | K5: 0 | L5: =J5-K5 -> 169781.06 | M5: Manual period adjustment | N5: DOC-00001 | O5: MANUAL_JE | P5: USR_OM | Q5: USR_RE | R5: 45822.802 | S5: Approved | V5: =AND(C5>=Year_End_Window_Start,C5<=Year_End_Window_End) -> FALSE | W5: =AND(OR(WEEKDAY(C5,2)=5,WEEKDAY(C5,2)=6),'01_Parameters'!$C$11="Enabled") -> TRUE | X5: =AND(HOUR(R5)<Business_Day_Start,HOUR(R5)>=0)+AND(HOUR(R5)>=Business_Day_End,HOUR(R5)<=23)>0 -> TRUE | Y5: =ABS(L5)>High_Value_GL_Threshold -> TRUE | Z5: =AND(ABS(L5)>=Round_Number_Threshold,MOD(ABS(L5),Round_Number_Threshold)=0) -> FALSE
A6: JE-00001 | B6: JE-00001-02 | C6: 45822 | D6: 45820 | E6: 2025 | F6: 6 | G6: 2000 | H6: Trade Payables | I6: Liability | J6: 0 | K6: 169781.06 | L6: =J6-K6 -> -169781.06 | M6: Manual period adjustment | N6: DOC-00001 | O6: MANUAL_JE | P6: USR_OM | Q6: USR_RE | R6: 45822.802 | S6: Approved | V6: =AND(C6>=Year_End_Window_Start,C6<=Year_End_Window_End) -> FALSE | W6: =AND(OR(WEEKDAY(C6,2)=5,WEEKDAY(C6,2)=6),'01_Parameters'!$C$11="Enabled") -> TRUE | X6: =AND(HOUR(R6)<Business_Day_Start,HOUR(R6)>=0)+AND(HOUR(R6)>=Business_Day_End,HOUR(R6)<=23)>0 -> TRUE | Y6: =ABS(L6)>High_Value_GL_Threshold -> TRUE | Z6: =AND(ABS(L6)>=Round_Number_Threshold,MOD(ABS(L6),Round_Number_Threshold)=0) -> FALSE
A7: JE-00002 | B7: JE-00002-01 | C7: 45872 | D7: 45869 | E7: 2025 | F7: 8 | G7: 6300 | H7: Marketing Expense | I7: Expense | J7: 47662.32 | K7: 0 | L7: =J7-K7 -> 47662.32 | M7: Manual period adjustment | N7: DOC-00002 | O7: MANUAL_JE | P7: USR_AH | Q7: USR_OM | R7: 45872.417 | S7: Approved | V7: =AND(C7>=Year_End_Window_Start,C7<=Year_End_Window_End) -> FALSE | W7: =AND(OR(WEEKDAY(C7,2)=5,WEEKDAY(C7,2)=6),'01_Parameters'!$C$11="Enabled") -> FALSE | X7: =AND(HOUR(R7)<Business_Day_Start,HOUR(R7)>=0)+AND(HOUR(R7)>=Business_Day_End,HOUR(R7)<=23)>0 -> FALSE | Y7: =ABS(L7)>High_Value_GL_Threshold -> FALSE | Z7: =AND(ABS(L7)>=Round_Number_Threshold,MOD(ABS(L7),Round_Number_Threshold)=0) -> FALSE
A8: JE-00002 | B8: JE-00002-02 | C8: 45872 | D8: 45869 | E8: 2025 | F8: 8 | G8: 2000 | H8: Trade Payables | I8: Liability | J8: 0 | K8: 47662.32 | L8: =J8-K8 -> -47662.32 | M8: Manual period adjustment | N8: DOC-00002 | O8: MANUAL_JE | P8: USR_AH | Q8: USR_OM | R8: 45872.417 | S8: Approved | V8: =AND(C8>=Year_End_Window_Start,C8<=Year_End_Window_End) -> FALSE | W8: =AND(OR(WEEKDAY(C8,2)=5,WEEKDAY(C8,2)=6),'01_Parameters'!$C$11="Enabled") -> FALSE | X8: =AND(HOUR(R8)<Business_Day_Start,HOUR(R8)>=0)+AND(HOUR(R8)>=Business_Day_End,HOUR(R8)<=23)>0 -> FALSE | Y8: =ABS(L8)>High_Value_GL_Threshold -> FALSE | Z8: =AND(ABS(L8)>=Round_Number_Threshold,MOD(ABS(L8),Round_Number_Threshold)=0) -> FALSE
A9: JE-00003 | B9: JE-00003-01 | C9: 45709 | D9: 45704 | E9: 2025 | F9: 2 | G9: 1100 | H9: Trade Receivables | I9: Asset | J9: 46024.42 | K9: 0 | L9: =J9-K9 -> 46024.42 | M9: Daily retail sales | N9: DOC-00003 | O9: AUTO_SALES | P9: USR_SA | Q9: USR_FA | R9: 45709.417 | S9: Approved | V9: =AND(C9>=Year_End_Window_Start,C9<=Year_End_Window_End) -> FALSE | W9: =AND(OR(WEEKDAY(C9,2)=5,WEEKDAY(C9,2)=6),'01_Parameters'!$C$11="Enabled") -> TRUE | X9: =AND(HOUR(R9)<Business_Day_Start,HOUR(R9)>=0)+AND(HOUR(R9)>=Business_Day_End,HOUR(R9)<=23)>0 -> FALSE | Y9: =ABS(L9)>High_Value_GL_Threshold -> FALSE | Z9: =AND(ABS(L9)>=Round_Number_Threshold,MOD(ABS(L9),Round_Number_Threshold)=0) -> FALSE
A10: JE-00003 | B10: JE-00003-02 | C10: 45709 | D10: 45704 | E10: 2025 | F10: 2 | G10: 4000 | H10: Sales Revenue | I10: Revenue | J10: 0 | K10: 46024.42 | L10: =J10-K10 -> -46024.42 | M10: Daily retail sales | N10: DOC-00003 | O10: AUTO_SALES | P10: USR_SA | Q10: USR_FA | R10: 45709.417 | S10: Approved | V10: =AND(C10>=Year_End_Window_Start,C10<=Year_End_Window_End) -> FALSE | W10: =AND(OR(WEEKDAY(C10,2)=5,WEEKDAY(C10,2)=6),'01_Parameters'!$C$11="Enabled") -> TRUE | X10: =AND(HOUR(R10)<Business_Day_Start,HOUR(R10)>=0)+AND(HOUR(R10)>=Business_Day_End,HOUR(R10)<=23)>0 -> FALSE | Y10: =ABS(L10)>High_Value_GL_Threshold -> FALSE | Z10: =AND(ABS(L10)>=Round_Number_Threshold,MOD(ABS(L10),Round_Number_Threshold)=0) -> FALSE
A11: JE-00004 | B11: JE-00004-01 | C11: 45910 | D11: 45905 | E11: 2025 | F11: 9 | G11: 6500 | H11: Depreciation Expense | I11: Expense | J11: 21567.1 | K11: 0 | L11: =J11-K11 -> 21567.1 | M11: Monthly depreciation | N11: DOC-00004 | O11: AUTO_DEPR | P11: USR_FA | Q11: USR_AH | R11: 45910.625 | S11: Approved | V11: =AND(C11>=Year_End_Window_Start,C11<=Year_End_Window_End) -> FALSE | W11: =AND(OR(WEEKDAY(C11,2)=5,WEEKDAY(C11,2)=6),'01_Parameters'!$C$11="Enabled") -> FALSE | X11: =AND(HOUR(R11)<Business_Day_Start,HOUR(R11)>=0)+AND(HOUR(R11)>=Business_Day_End,HOUR(R11)<=23)>0 -> FALSE | Y11: =ABS(L11)>High_Value_GL_Threshold -> FALSE | Z11: =AND(ABS(L11)>=Round_Number_Threshold,MOD(ABS(L11),Round_Number_Threshold)=0) -> FALSE
A12: JE-00004 | B12: JE-00004-02 | C12: 45910 | D12: 45905 | E12: 2025 | F12: 9 | G12: 1500 | H12: Property and Equipment | I12: Asset | J12: 0 | K12: 21567.1 | L12: =J12-K12 -> -21567.1 | M12: Monthly depreciation | N12: DOC-00004 | O12: AUTO_DEPR | P12: USR_FA | Q12: USR_AH | R12: 45910.625 | S12: Approved | V12: =AND(C12>=Year_End_Window_Start,C12<=Year_End_Window_End) -> FALSE | W12: =AND(OR(WEEKDAY(C12,2)=5,WEEKDAY(C12,2)=6),'01_Parameters'!$C$11="Enabled") -> FALSE | X12: =AND(HOUR(R12)<Business_Day_Start,HOUR(R12)>=0)+AND(HOUR(R12)>=Business_Day_End,HOUR(R12)<=23)>0 -> FALSE | Y12: =ABS(L12)>High_Value_GL_Threshold -> FALSE | Z12: =AND(ABS(L12)>=Round_Number_Threshold,MOD(ABS(L12),Round_Number_Threshold)=0) -> FALSE
A13: JE-00005 | B13: JE-00005-01 | C13: 45874 | D13: 45873 | E13: 2025 | F13: 8 | G13: 6500 | H13: Depreciation Expense | I13: Expense | J13: 35129.35 | K13: 0 | L13: =J13-K13 -> 35129.35 | M13: Monthly depreciation | N13: DOC-00005 | O13: AUTO_DEPR | P13: USR_FA | Q13: USR_RE | R13: 45874.719 | S13: Approved | V13: =AND(C13>=Year_End_Window_Start,C13<=Year_End_Window_End) -> FALSE | W13: =AND(OR(WEEKDAY(C13,2)=5,WEEKDAY(C13,2)=6),'01_Parameters'!$C$11="Enabled") -> FALSE | X13: =AND(HOUR(R13)<Business_Day_Start,HOUR(R13)>=0)+AND(HOUR(R13)>=Business_Day_End,HOUR(R13)<=23)>0 -> FALSE | Y13: =ABS(L13)>High_Value_GL_Threshold -> FALSE | Z13: =AND(ABS(L13)>=Round_Number_Threshold,MOD(ABS(L13),Round_Number_Threshold)=0) -> FALSE
A14: JE-00005 | B14: JE-00005-02 | C14: 45874 | D14: 45873 | E14: 2025 | F14: 8 | G14: 1500 | H14: Property and Equipment | I14: Asset | J14: 0 | K14: 35129.35 | L14: =J14-K14 -> -35129.35 | M14: Monthly depreciation | N14: DOC-00005 | O14: AUTO_DEPR | P14: USR_FA | Q14: USR_RE | R14: 45874.719 | S14: Approved | V14: =AND(C14>=Year_End_Window_Start,C14<=Year_End_Window_End) -> FALSE | W14: =AND(OR(WEEKDAY(C14,2)=5,WEEKDAY(C14,2)=6),'01_Parameters'!$C$11="Enabled") -> FALSE | X14: =AND(HOUR(R14)<Business_Day_Start,HOUR(R14)>=0)+AND(HOUR(R14)>=Business_Day_End,HOUR(R14)<=23)>0 -> FALSE | Y14: =ABS(L14)>High_Value_GL_Threshold -> FALSE | Z14: =AND(ABS(L14)>=Round_Number_Threshold,MOD(ABS(L14),Round_Number_Threshold)=0) -> FALSE
A15: JE-00006 | B15: JE-00006-01 | C15: 45750 | D15: 45746 | E15: 2025 | F15: 4 | G15: 6400 | H15: Professional Fees | I15: Expense | J15: 10879.2 | K15: 0 | L15: =J15-K15 -> 10879.2 | M15: Manual period adjustment | N15: DOC-00006 | O15: MANUAL_JE | P15: USR_OM | Q15: USR_NA | R15: 45750.375 | S15: Approved | V15: =AND(C15>=Year_End_Window_Start,C15<=Year_End_Window_End) -> FALSE | W15: =AND(OR(WEEKDAY(C15,2)=5,WEEKDAY(C15,2)=6),'01_Parameters'!$C$11="Enabled") -> FALSE | X15: =AND(HOUR(R15)<Business_Day_Start,HOUR(R15)>=0)+AND(HOUR(R15)>=Business_Day_End,HOUR(R15)<=23)>0 -> FALSE | Y15: =ABS(L15)>High_Value_GL_Threshold -> FALSE | Z15: =AND(ABS(L15)>=Round_Number_Threshold,MOD(ABS(L15),Round_Number_Threshold)=0) -> FALSE
A16: JE-00006 | B16: JE-00006-02 | C16: 45750 | D16: 45746 | E16: 2025 | F16: 4 | G16: 2000 | H16: Trade Payables | I16: Liability | J16: 0 | K16: 10879.2 | L16: =J16-K16 -> -10879.2 | M16: Manual period adjustment | N16: DOC-00006 | O16: MANUAL_JE | P16: USR_OM | Q16: USR_NA | R16: 45750.375 | S16: Approved | V16: =AND(C16>=Year_End_Window_Start,C16<=Year_End_Window_End) -> FALSE | W16: =AND(OR(WEEKDAY(C16,2)=5,WEEKDAY(C16,2)=6),'01_Parameters'!$C$11="Enabled") -> FALSE | X16: =AND(HOUR(R16)<Business_Day_Start,HOUR(R16)>=0)+AND(HOUR(R16)>=Business_Day_End,HOUR(R16)<=23)>0 -> FALSE | Y16: =ABS(L16)>High_Value_GL_Threshold -> FALSE | Z16: =AND(ABS(L16)>=Round_Number_Threshold,MOD(ABS(L16),Round_Number_Threshold)=0) -> FALSE
... A24: JE-00010 | B24: JE-00010-02 | C24: 45919 | D24: 45916 | E24: 2025 | F24: 9 | G24: 1500 | H24: Property and Equipment | I24: Asset | J24: 0 | K24: 30865.18 | L24: =J24-K24 -> -30865.18 | M24: Monthly depreciation | N24: DOC-00010 | O24: AUTO_DEPR | P24: USR_RE | Q24: USR_SA | R24: 45919.792 | S24: Approved | V24: =AND(C24>=Year_End_Window_Start,C24<=Year_End_Window_End) -> FALSE | W24: =AND(OR(WEEKDAY(C24,2)=5,WEEKDAY(C24,2)=6),'01_Parameters'!$C$11="Enabled") -> TRUE | X24: =AND(HOUR(R24)<Business_Day_Start,HOUR(R24)>=0)+AND(HOUR(R24)>=Business_Day_End,HOUR(R24)<=23)>0 -> TRUE | Y24: =ABS(L24)>High_Value_GL_Threshold -> FALSE | Z24: =AND(ABS(L24)>=Round_Number_Threshold,MOD(ABS(L24),Round_Number_Threshold)=0) -> FALSE
A25: JE-00011 | B25: JE-00011-01 | C25: 45661 | D25: 45656 | E25: 2025 | F25: 1 | G25: 6200 | H25: Utilities Expense | I25: Expense | J25: 1910.58 | K25: 0 | L25: =J25-K25 -> 1910.58 | M25: Supplier invoice posting | N25: INV-00011 | O25: AUTO_AP | P25: USR_SA | Q25: USR_AH | R25: 45661.604 | S25: Approved | T25: V010 | U25: INV-00011 | V25: =AND(C25>=Year_End_Window_Start,C25<=Year_End_Window_End) -> FALSE | W25: =AND(OR(WEEKDAY(C25,2)=5,WEEKDAY(C25,2)=6),'01_Parameters'!$C$11="Enabled") -> TRUE | X25: =AND(HOUR(R25)<Business_Day_Start,HOUR(R25)>=0)+AND(HOUR(R25)>=Business_Day_End,HOUR(R25)<=23)>0 -> FALSE | Y25: =ABS(L25)>High_Value_GL_Threshold -> FALSE | Z25: =AND(ABS(L25)>=Round_Number_Threshold,MOD(ABS(L25),Round_Number_Threshold)=0) -> FALSE
A26: JE-00011 | B26: JE-00011-02 | C26: 45661 | D26: 45656 | E26: 2025 | F26: 1 | G26: 2000 | H26: Trade Payables | I26: Liability | J26: 0 | K26: 1910.58 | L26: =J26-K26 -> -1910.58 | M26: Supplier invoice posting | N26: INV-00011 | O26: AUTO_AP | P26: USR_SA | Q26: USR_AH | R26: 45661.604 | S26: Approved | T26: V010 | U26: INV-00011 | V26: =AND(C26>=Year_End_Window_Start,C26<=Year_End_Window_End) -> FALSE | W26: =AND(OR(WEEKDAY(C26,2)=5,WEEKDAY(C26,2)=6),'01_Parameters'!$C$11="Enabled") -> TRUE | X26: =AND(HOUR(R26)<Business_Day_Start,HOUR(R26)>=0)+AND(HOUR(R26)>=Business_Day_End,HOUR(R26)<=23)>0 -> FALSE | Y26: =ABS(L26)>High_Value_GL_Threshold -> FALSE | Z26: =AND(ABS(L26)>=Round_Number_Threshold,MOD(ABS(L26),Round_Number_Threshold)=0) -> FALSE
A27: JE-00012 | B27: JE-00012-01 | C27: 45737 | D27: 45937 | E27: 2025 | F27: 3 | G27: 6000 | H27: Salaries Expense | I27: Expense | J27: 74307.73 | K27: 0 | L27: =J27-K27 -> 74307.73 | M27: Monthly payroll accrual | N27: DOC-00012 | O27: AUTO_PAYROLL | P27: USR_OM | Q27: USR_AH | R27: 45942.812 | S27: Approved | V27: =AND(C27>=Year_End_Window_Start,C27<=Year_End_Window_End) -> FALSE | W27: =AND(OR(WEEKDAY(C27,2)=5,WEEKDAY(C27,2)=6),'01_Parameters'!$C$11="Enabled") -> TRUE | X27: =AND(HOUR(R27)<Business_Day_Start,HOUR(R27)>=0)+AND(HOUR(R27)>=Business_Day_End,HOUR(R27)<=23)>0 -> TRUE | Y27: =ABS(L27)>High_Value_GL_Threshold -> FALSE | Z27: =AND(ABS(L27)>=Round_Number_Threshold,MOD(ABS(L27),Round_Number_Threshold)=0) -> FALSE
A28: JE-00012 | B28: JE-00012-02 | C28: 45737 | D28: 45937 | E28: 2025 | F28: 3 | G28: 2100 | H28: Accrued Expenses | I28: Liability | J28: 0 | K28: 74307.73 | L28: =J28-K28 -> -74307.73 | M28: Monthly payroll accrual | N28: DOC-00012 | O28: AUTO_PAYROLL | P28: USR_OM | Q28: USR_AH | R28: 45942.812 | S28: Approved | V28: =AND(C28>=Year_End_Window_Start,C28<=Year_End_Window_End) -> FALSE | W28: =AND(OR(WEEKDAY(C28,2)=5,WEEKDAY(C28,2)=6),'01_Parameters'!$C$11="Enabled") -> TRUE | X28: =AND(HOUR(R28)<Business_Day_Start,HOUR(R28)>=0)+AND(HOUR(R28)>=Business_Day_End,HOUR(R28)<=23)>0 -> TRUE | Y28: =ABS(L28)>High_Value_GL_Threshold -> FALSE | Z28: =AND(ABS(L28)>=Round_Number_Threshold,MOD(ABS(L28),Round_Number_Threshold)=0) -> FALSE
A29: JE-00013 | B29: JE-00013-01 | C29: 46006 | D29: 46001 | E29: 2025 | F29: 12 | G29: 1100 | H29: Trade Receivables | I29: Asset | J29: 33640.64 | K29: 0 | L29: =J29-K29 -> 33640.64 | M29: Daily retail sales | N29: DOC-00013 | O29: AUTO_SALES | P29: USR_RE | Q29: USR_AH | R29: 45754.979 | S29: Approved | V29: =AND(C29>=Year_End_Window_Start,C29<=Year_End_Window_End) -> FALSE | W29: =AND(OR(WEEKDAY(C29,2)=5,WEEKDAY(C29,2)=6),'01_Parameters'!$C$11="Enabled") -> FALSE | X29: =AND(HOUR(R29)<Business_Day_Start,HOUR(R29)>=0)+AND(HOUR(R29)>=Business_Day_End,HOUR(R29)<=23)>0 -> TRUE | Y29: =ABS(L29)>High_Value_GL_Threshold -> FALSE | Z29: =AND(ABS(L29)>=Round_Number_Threshold,MOD(ABS(L29),Round_Number_Threshold)=0) -> FALSE
A30: JE-00013 | B30: JE-00013-02 | C30: 46006 | D30: 46001 | E30: 2025 | F30: 12 | G30: 4000 | H30: Sales Revenue | I30: Revenue | J30: 0 | K30: 33640.64 | L30: =J30-K30 -> -33640.64 | M30: Daily retail sales | N30: DOC-00013 | O30: AUTO_SALES | P30: USR_RE | Q30: USR_AH | R30: 45754.979 | S30: Approved | V30: =AND(C30>=Year_End_Window_Start,C30<=Year_End_Window_End) -> FALSE | W30: =AND(OR(WEEKDAY(C30,2)=5,WEEKDAY(C30,2)=6),'01_Parameters'!$C$11="Enabled") -> FALSE | X30: =AND(HOUR(R30)<Business_Day_Start,HOUR(R30)>=0)+AND(HOUR(R30)>=Business_Day_End,HOUR(R30)<=23)>0 -> TRUE | Y30: =ABS(L30)>High_Value_GL_Threshold -> FALSE | Z30: =AND(ABS(L30)>=Round_Number_Threshold,MOD(ABS(L30),Round_Number_Threshold)=0) -> FALSE
A31: JE-00014 | B31: JE-00014-01 | C31: 45877 | D31: 45874 | E31: 2025 | F31: 8 | G31: 6000 | H31: Salaries Expense | I31: Expense | J31: 50000 | K31: 0 | L31: =J31-K31 -> 50000 | M31: Monthly payroll accrual | N31: DOC-00014 | O31: AUTO_PAYROLL | P31: USR_RE | Q31: USR_AH | R31: 45877.865 | S31: Approved | V31: =AND(C31>=Year_End_Window_Start,C31<=Year_End_Window_End) -> FALSE | W31: =AND(OR(WEEKDAY(C31,2)=5,WEEKDAY(C31,2)=6),'01_Parameters'!$C$11="Enabled") -> TRUE | X31: =AND(HOUR(R31)<Business_Day_Start,HOUR(R31)>=0)+AND(HOUR(R31)>=Business_Day_End,HOUR(R31)<=23)>0 -> TRUE | Y31: =ABS(L31)>High_Value_GL_Threshold -> FALSE | Z31: =AND(ABS(L31)>=Round_Number_Threshold,MOD(ABS(L31),Round_Number_Threshold)=0) -> TRUE
A32: JE-00014 | B32: JE-00014-02 | C32: 45877 | D32: 45874 | E32: 2025 | F32: 8 | G32: 2100 | H32: Accrued Expenses | I32: Liability | J32: 0 | K32: 50000 | L32: =J32-K32 -> -50000 | M32: Monthly payroll accrual | N32: DOC-00014 | O32: AUTO_PAYROLL | P32: USR_RE | Q32: USR_AH | R32: 45877.865 | S32: Approved | V32: =AND(C32>=Year_End_Window_Start,C32<=Year_End_Window_End) -> FALSE | W32: =AND(OR(WEEKDAY(C32,2)=5,WEEKDAY(C32,2)=6),'01_Parameters'!$C$11="Enabled") -> TRUE | X32: =AND(HOUR(R32)<Business_Day_Start,HOUR(R32)>=0)+AND(HOUR(R32)>=Business_Day_End,HOUR(R32)<=23)>0 -> TRUE | Y32: =ABS(L32)>High_Value_GL_Threshold -> FALSE | Z32: =AND(ABS(L32)>=Round_Number_Threshold,MOD(ABS(L32),Round_Number_Threshold)=0) -> TRUE
A33: JE-00015 | B33: JE-00015-01 | C33: 45935 | D33: 45934 | E33: 2025 | F33: 10 | G33: 6600 | H33: Other Operating Expenses | I33: Expense | J33: 51634.78 | K33: 0 | L33: =J33-K33 -> 51634.78 | M33: Supplier invoice posting | N33: INV-00015 | O33: AUTO_AP | P33: USR_AH | Q33: USR_AH | R33: 45935.26 | S33: Approved | T33: V005 | U33: INV-00015 | V33: =AND(C33>=Year_End_Window_Start,C33<=Year_End_Window_End) -> FALSE | W33: =AND(OR(WEEKDAY(C33,2)=5,WEEKDAY(C33,2)=6),'01_Parameters'!$C$11="Enabled") -> FALSE | X33: =AND(HOUR(R33)<Business_Day_Start,HOUR(R33)>=0)+AND(HOUR(R33)>=Business_Day_End,HOUR(R33)<=23)>0 -> TRUE | Y33: =ABS(L33)>High_Value_GL_Threshold -> FALSE | Z33: =AND(ABS(L33)>=Round_Number_Threshold,MOD(ABS(L33),Round_Number_Threshold)=0) -> FALSE
A34: JE-00015 | B34: JE-00015-02 | C34: 45935 | D34: 45934 | E34: 2025 | F34: 10 | G34: 2000 | H34: Trade Payables | I34: Liability | J34: 0 | K34: 51634.78 | L34: =J34-K34 -> -51634.78 | M34: Supplier invoice posting | N34: INV-00015 | O34: AUTO_AP | P34: USR_AH | Q34: USR_AH | R34: 45935.26 | S34: Approved | T34: V005 | U34: INV-00015 | V34: =AND(C34>=Year_End_Window_Start,C34<=Year_End_Window_End) -> FALSE | W34: =AND(OR(WEEKDAY(C34,2)=5,WEEKDAY(C34,2)=6),'01_Parameters'!$C$11="Enabled") -> FALSE | X34: =AND(HOUR(R34)<Business_Day_Start,HOUR(R34)>=0)+AND(HOUR(R34)>=Business_Day_End,HOUR(R34)<=23)>0 -> TRUE | Y34: =ABS(L34)>High_Value_GL_Threshold -> FALSE | Z34: =AND(ABS(L34)>=Round_Number_Threshold,MOD(ABS(L34),Round_Number_Threshold)=0) -> FALSE
A35: JE-00016 | B35: JE-00016-01 | C35: 45753 | D35: 45753 | E35: 2025 | F35: 4 | G35: 4000 | H35: Sales Revenue | I35: Revenue | J35: 81715.31 | K35: 0 | L35: =J35-K35 -> 81715.31 | M35: Manual revenue to equipment transfer | N35: DOC-00016 | O35: MANUAL_JE | P35: USR_OM | Q35: USR_FA | R35: 45753.417 | S35: Approved | V35: =AND(C35>=Year_End_Window_Start,C35<=Year_End_Window_End) -> FALSE | W35: =AND(OR(WEEKDAY(C35,2)=5,WEEKDAY(C35,2)=6),'01_Parameters'!$C$11="Enabled") -> FALSE | X35: =AND(HOUR(R35)<Business_Day_Start,HOUR(R35)>=0)+AND(HOUR(R35)>=Business_Day_End,HOUR(R35)<=23)>0 -> FALSE | Y35: =ABS(L35)>High_Value_GL_Threshold -> FALSE | Z35: =AND(ABS(L35)>=Round_Number_Threshold,MOD(ABS(L35),Round_Number_Threshold)=0) -> FALSE
A36: JE-00016 | B36: JE-00016-02 | C36: 45753 | D36: 45753 | E36: 2025 | F36: 4 | G36: 1500 | H36: Property and Equipment | I36: Asset | J36: 0 | K36: 81715.31 | L36: =J36-K36 -> -81715.31 | M36: Manual revenue to equipment transfer | N36: DOC-00016 | O36: MANUAL_JE | P36: USR_OM | Q36: USR_FA | R36: 45753.417 | S36: Approved | V36: =AND(C36>=Year_End_Window_Start,C36<=Year_End_Window_End) -> FALSE | W36: =AND(OR(WEEKDAY(C36,2)=5,WEEKDAY(C36,2)=6),'01_Parameters'!$C$11="Enabled") -> FALSE | X36: =AND(HOUR(R36)<Business_Day_Start,HOUR(R36)>=0)+AND(HOUR(R36)>=Business_Day_End,HOUR(R36)<=23)>0 -> FALSE | Y36: =ABS(L36)>High_Value_GL_Threshold -> FALSE | Z36: =AND(ABS(L36)>=Round_Number_Threshold,MOD(ABS(L36),Round_Number_Threshold)=0) -> FALSE
A37: JE-00017 | B37: JE-00017-01 | C37: 45759 | D37: 45758 | E37: 2025 | F37: 4 | G37: 5000 | H37: Cost of Goods Sold | I37: Expense | J37: 84369.11 | K37: 0 | L37: =J37-K37 -> 84369.11 | M37: Inventory movement | N37: DOC-00017 | O37: AUTO_INVENTORY | P37: USR_FA | Q37: USR_OM | R37: 45759.281 | S37: Approved | V37: =AND(C37>=Year_End_Window_Start,C37<=Year_End_Window_End) -> FALSE | W37: =AND(OR(WEEKDAY(C37,2)=5,WEEKDAY(C37,2)=6),'01_Parameters'!$C$11="Enabled") -> TRUE | X37: =AND(HOUR(R37)<Business_Day_Start,HOUR(R37)>=0)+AND(HOUR(R37)>=Business_Day_End,HOUR(R37)<=23)>0 -> TRUE | Y37: =ABS(L37)>High_Value_GL_Threshold -> FALSE | Z37: =AND(ABS(L37)>=Round_Number_Threshold,MOD(ABS(L37),Round_Number_Threshold)=0) -> FALSE
A38: JE-00017 | B38: JE-00017-02 | C38: 45759 | D38: 45758 | E38: 2025 | F38: 4 | G38: 1200 | H38: Inventory | I38: Asset | J38: 0 | K38: 84369.11 | L38: =J38-K38 -> -84369.11 | M38: Inventory movement | N38: DOC-00017 | O38: AUTO_INVENTORY | P38: USR_FA | Q38: USR_OM | R38: 45759.281 | S38: Approved | V38: =AND(C38>=Year_End_Window_Start,C38<=Year_End_Window_End) -> FALSE | W38: =AND(OR(WEEKDAY(C38,2)=5,WEEKDAY(C38,2)=6),'01_Parameters'!$C$11="Enabled") -> TRUE | X38: =AND(HOUR(R38)<Business_Day_Start,HOUR(R38)>=0)+AND(HOUR(R38)>=Business_Day_End,HOUR(R38)<=23)>0 -> TRUE | Y38: =ABS(L38)>High_Value_GL_Threshold -> FALSE | Z38: =AND(ABS(L38)>=Round_Number_Threshold,MOD(ABS(L38),Round_Number_Threshold)=0) -> FALSE
A39: JE-00018 | B39: JE-00018-01 | C39: 45802 | D39: 45802 | E39: 2025 | F39: 5 | G39: 6300 | H39: Marketing Expense | I39: Expense | J39: 138757.1 | K39: 0 | L39: =J39-K39 -> 138757.1 | M39: Manual period adjustment | N39: DOC-00018 | O39: MANUAL_JE | P39: USR_NA | Q39: USR_AH | R39: 45802.385 | S39: Approved | V39: =AND(C39>=Year_End_Window_Start,C39<=Year_End_Window_End) -> FALSE | W39: =AND(OR(WEEKDAY(C39,2)=5,WEEKDAY(C39,2)=6),'01_Parameters'!$C$11="Enabled") -> FALSE | X39: =AND(HOUR(R39)<Business_Day_Start,HOUR(R39)>=0)+AND(HOUR(R39)>=Business_Day_End,HOUR(R39)<=23)>0 -> FALSE | Y39: =ABS(L39)>High_Value_GL_Threshold -> TRUE | Z39: =AND(ABS(L39)>=Round_Number_Threshold,MOD(ABS(L39),Round_Number_Threshold)=0) -> FALSE
A40: JE-00018 | B40: JE-00018-02 | C40: 45802 | D40: 45802 | E40: 2025 | F40: 5 | G40: 2000 | H40: Trade Payables | I40: Liability | J40: 0 | K40: 138757.1 | L40: =J40-K40 -> -138757.1 | M40: Manual period adjustment | N40: DOC-00018 | O40: MANUAL_JE | P40: USR_NA | Q40: USR_AH | R40: 45802.385 | S40: Approved | V40: =AND(C40>=Year_End_Window_Start,C40<=Year_End_Window_End) -> FALSE | W40: =AND(OR(WEEKDAY(C40,2)=5,WEEKDAY(C40,2)=6),'01_Parameters'!$C$11="Enabled") -> FALSE | X40: =AND(HOUR(R40)<Business_Day_Start,HOUR(R40)>=0)+AND(HOUR(R40)>=Business_Day_End,HOUR(R40)<=23)>0 -> FALSE | Y40: =ABS(L40)>High_Value_GL_Threshold -> TRUE | Z40: =AND(ABS(L40)>=Round_Number_Threshold,MOD(ABS(L40),Round_Number_Threshold)=0) -> FALSE
A41: JE-00019 | B41: JE-00019-01 | C41: 45865 | D41: 45862 | E41: 2025 | F41: 7 | G41: 5000 | H41: Cost of Goods Sold | I41: Expense | J41: 13387.2 | K41: 0 | L41: =J41-K41 -> 13387.2 | M41: Inventory movement | N41: DOC-00019 | O41: AUTO_INVENTORY | P41: USR_NA | Q41: USR_AH | R41: 45865.729 | S41: Approved | V41: =AND(C41>=Year_End_Window_Start,C41<=Year_End_Window_End) -> FALSE | W41: =AND(OR(WEEKDAY(C41,2)=5,WEEKDAY(C41,2)=6),'01_Parameters'!$C$11="Enabled") -> FALSE | X41: =AND(HOUR(R41)<Business_Day_Start,HOUR(R41)>=0)+AND(HOUR(R41)>=Business_Day_End,HOUR(R41)<=23)>0 -> FALSE | Y41: =ABS(L41)>High_Value_GL_Threshold -> FALSE | Z41: =AND(ABS(L41)>=Round_Number_Threshold,MOD(ABS(L41),Round_Number_Threshold)=0) -> FALSE
A42: JE-00019 | B42: JE-00019-02 | C42: 45865 | D42: 45862 | E42: 2025 | F42: 7 | G42: 1200 | H42: Inventory | I42: Asset | J42: 0 | K42: 13387.2 | L42: =J42-K42 -> -13387.2 | M42: Inventory movement | N42: DOC-00019 | O42: AUTO_INVENTORY | P42: USR_NA | Q42: USR_AH | R42: 45865.729 | S42: Approved | V42: =AND(C42>=Year_End_Window_Start,C42<=Year_End_Window_End) -> FALSE | W42: =AND(OR(WEEKDAY(C42,2)=5,WEEKDAY(C42,2)=6),'01_Parameters'!$C$11="Enabled") -> FALSE | X42: =AND(HOUR(R42)<Business_Day_Start,HOUR(R42)>=0)+AND(HOUR(R42)>=Business_Day_End,HOUR(R42)<=23)>0 -> FALSE | Y42: =ABS(L42)>High_Value_GL_Threshold -> FALSE | Z42: =AND(ABS(L42)>=Round_Number_Threshold,MOD(ABS(L42),Round_Number_Threshold)=0) -> FALSE
A43: JE-00020 | B43: JE-00020-01 | C43: 45848 | D43: 45848 | E43: 2025 | F43: 7 | G43: 6600 | H43: Other Operating Expenses | I43: Expense | J43: 78012.15 | K43: 0 | L43: =J43-K43 -> 78012.15 | M43: Supplier invoice posting | N43: INV-00020 | O43: AUTO_AP | P43: USR_RE | Q43: USR_AH | R43: 45848.781 | S43: Approved | T43: V004 | U43: INV-00020 | V43: =AND(C43>=Year_End_Window_Start,C43<=Year_End_Window_End) -> FALSE | W43: =AND(OR(WEEKDAY(C43,2)=5,WEEKDAY(C43,2)=6),'01_Parameters'!$C$11="Enabled") -> FALSE | X43: =AND(HOUR(R43)<Business_Day_Start,HOUR(R43)>=0)+AND(HOUR(R43)>=Business_Day_End,HOUR(R43)<=23)>0 -> TRUE | Y43: =ABS(L43)>High_Value_GL_Threshold -> FALSE | Z43: =AND(ABS(L43)>=Round_Number_Threshold,MOD(ABS(L43),Round_Number_Threshold)=0) -> FALSE
A44: JE-00020 | B44: JE-00020-02 | C44: 45848 | D44: 45848 | E44: 2025 | F44: 7 | G44: 2000 | H44: Trade Payables | I44: Liability | J44: 0 | K44: 78012.15 | L44: =J44-K44 -> -78012.15 | M44: Supplier invoice posting | N44: INV-00020 | O44: AUTO_AP | P44: USR_RE | Q44: USR_AH | R44: 45848.781 | S44: Approved | T44: V004 | U44: INV-00020 | V44: =AND(C44>=Year_End_Window_Start,C44<=Year_End_Window_End) -> FALSE | W44: =AND(OR(WEEKDAY(C44,2)=5,WEEKDAY(C44,2)=6),'01_Parameters'!$C$11="Enabled") -> FALSE | X44: =AND(HOUR(R44)<Business_Day_Start,HOUR(R44)>=0)+AND(HOUR(R44)>=Business_Day_End,HOUR(R44)<=23)>0 -> TRUE | Y44: =ABS(L44)>High_Value_GL_Threshold -> FALSE | Z44: =AND(ABS(L44)>=Round_Number_Threshold,MOD(ABS(L44),Round_Number_Threshold)=0) -> FALSE
A45: JE-00021 | B45: JE-00021-01 | C45: 45914 | D45: 45910 | E45: 2025 | F45: 9 | G45: 6500 | H45: Depreciation Expense | I45: Expense | J45: 70546.03 | K45: 0 | L45: =J45-K45 -> 70546.03 | M45: Monthly depreciation | N45: DOC-00021 | O45: AUTO_DEPR | P45: USR_NA | Q45: USR_OM | R45: 45914.594 | S45: Approved | V45: =AND(C45>=Year_End_Window_Start,C45<=Year_End_Window_End) -> FALSE | W45: =AND(OR(WEEKDAY(C45,2)=5,WEEKDAY(C45,2)=6),'01_Parameters'!$C$11="Enabled") -> FALSE | X45: =AND(HOUR(R45)<Business_Day_Start,HOUR(R45)>=0)+AND(HOUR(R45)>=Business_Day_End,HOUR(R45)<=23)>0 -> FALSE | Y45: =ABS(L45)>High_Value_GL_Threshold -> FALSE | Z45: =AND(ABS(L45)>=Round_Number_Threshold,MOD(ABS(L45),Round_Number_Threshold)=0) -> FALSE
A46: JE-00021 | B46: JE-00021-02 | C46: 45914 | D46: 45910 | E46: 2025 | F46: 9 | G46: 1500 | H46: Property and Equipment | I46: Asset | J46: 0 | K46: 70546.03 | L46: =J46-K46 -> -70546.03 | M46: Monthly depreciation | N46: DOC-00021 | O46: AUTO_DEPR | P46: USR_NA | Q46: USR_OM | R46: 45914.594 | S46: Approved | V46: =AND(C46>=Year_End_Window_Start,C46<=Year_End_Window_End) -> FALSE | W46: =AND(OR(WEEKDAY(C46,2)=5,WEEKDAY(C46,2)=6),'01_Parameters'!$C$11="Enabled") -> FALSE | X46: =AND(HOUR(R46)<Business_Day_Start,HOUR(R46)>=0)+AND(HOUR(R46)>=Business_Day_End,HOUR(R46)<=23)>0 -> FALSE | Y46: =ABS(L46)>High_Value_GL_Threshold -> FALSE | Z46: =AND(ABS(L46)>=Round_Number_Threshold,MOD(ABS(L46),Round_Number_Threshold)=0) -> FALSE
A47: JE-00022 | B47: JE-00022-01 | C47: 45909 | D47: 45906 | E47: 2025 | F47: 9 | G47: 6000 | H47: Salaries Expense | I47: Expense | J47: 56483.11 | K47: 0 | L47: =J47-K47 -> 56483.11 | M47: Monthly payroll accrual | N47: DOC-00022 | O47: AUTO_PAYROLL | P47: USR_OM | Q47: USR_SA | R47: 45909.458 | S47: Approved | V47: =AND(C47>=Year_End_Window_Start,C47<=Year_End_Window_End) -> FALSE | W47: =AND(OR(WEEKDAY(C47,2)=5,WEEKDAY(C47,2)=6),'01_Parameters'!$C$11="Enabled") -> FALSE | X47: =AND(HOUR(R47)<Business_Day_Start,HOUR(R47)>=0)+AND(HOUR(R47)>=Business_Day_End,HOUR(R47)<=23)>0 -> FALSE | Y47: =ABS(L47)>High_Value_GL_Threshold -> FALSE | Z47: =AND(ABS(L47)>=Round_Number_Threshold,MOD(ABS(L47),Round_Number_Threshold)=0) -> FALSE
A48: JE-00022 | B48: JE-00022-02 | C48: 45909 | D48: 45906 | E48: 2025 | F48: 9 | G48: 2100 | H48: Accrued Expenses | I48: Liability | J48: 0 | K48: 56483.11 | L48: =J48-K48 -> -56483.11 | M48: Monthly payroll accrual | N48: DOC-00022 | O48: AUTO_PAYROLL | P48: USR_OM | Q48: USR_SA | R48: 45909.458 | S48: Approved | V48: =AND(C48>=Year_End_Window_Start,C48<=Year_End_Window_End) -> FALSE | W48: =AND(OR(WEEKDAY(C48,2)=5,WEEKDAY(C48,2)=6),'01_Parameters'!$C$11="Enabled") -> FALSE | X48: =AND(HOUR(R48)<Business_Day_Start,HOUR(R48)>=0)+AND(HOUR(R48)>=Business_Day_End,HOUR(R48)<=23)>0 -> FALSE | Y48: =ABS(L48)>High_Value_GL_Threshold -> FALSE | Z48: =AND(ABS(L48)>=Round_Number_Threshold,MOD(ABS(L48),Round_Number_Threshold)=0) -> FALSE
A49: JE-00023 | B49: JE-00023-01 | C49: 45755 | D49: 45755 | E49: 2025 | F49: 4 | G49: 6500 | H49: Depreciation Expense | I49: Expense | J49: 45436.04 | K49: 0 | L49: =J49-K49 -> 45436.04 | M49: Monthly depreciation | N49: DOC-00023 | O49: AUTO_DEPR | P49: USR_RE | Q49: USR_OM | R49: 45755.708 | S49: Approved | V49: =AND(C49>=Year_End_Window_Start,C49<=Year_End_Window_End) -> FALSE | W49: =AND(OR(WEEKDAY(C49,2)=5,WEEKDAY(C49,2)=6),'01_Parameters'!$C$11="Enabled") -> FALSE | X49: =AND(HOUR(R49)<Business_Day_Start,HOUR(R49)>=0)+AND(HOUR(R49)>=Business_Day_End,HOUR(R49)<=23)>0 -> FALSE | Y49: =ABS(L49)>High_Value_GL_Threshold -> FALSE | Z49: =AND(ABS(L49)>=Round_Number_Threshold,MOD(ABS(L49),Round_Number_Threshold)=0) -> FALSE
A50: JE-00023 | B50: JE-00023-02 | C50: 45755 | D50: 45755 | E50: 2025 | F50: 4 | G50: 1500 | H50: Property and Equipment | I50: Asset | J50: 0 | K50: 45436.04 | L50: =J50-K50 -> -45436.04 | M50: Monthly depreciation | N50: DOC-00023 | O50: AUTO_DEPR | P50: USR_RE | Q50: USR_OM | R50: 45755.708 | S50: Approved | V50: =AND(C50>=Year_End_Window_Start,C50<=Year_End_Window_End) -> FALSE | W50: =AND(OR(WEEKDAY(C50,2)=5,WEEKDAY(C50,2)=6),'01_Parameters'!$C$11="Enabled") -> FALSE | X50: =AND(HOUR(R50)<Business_Day_Start,HOUR(R50)>=0)+AND(HOUR(R50)>=Business_Day_End,HOUR(R50)<=23)>0 -> FALSE | Y50: =ABS(L50)>High_Value_GL_Threshold -> FALSE | Z50: =AND(ABS(L50)>=Round_Number_Threshold,MOD(ABS(L50),Round_Number_Threshold)=0) -> FALSE
A51: JE-00024 | B51: JE-00024-01 | C51: 45700 | D51: 45695 | E51: 2025 | F51: 2 | G51: 6500 | H51: Depreciation Expense | I51: Expense | J51: 78153 | K51: 0 | L51: =J51-K51 -> 78153 | M51: Monthly depreciation | N51: DOC-00024 | O51: AUTO_DEPR | P51: USR_FA | Q51: USR_SA | R51: 45700.406 | S51: Approved | V51: =AND(C51>=Year_End_Window_Start,C51<=Year_End_Window_End) -> FALSE | W51: =AND(OR(WEEKDAY(C51,2)=5,WEEKDAY(C51,2)=6),'01_Parameters'!$C$11="Enabled") -> FALSE | X51: =AND(HOUR(R51)<Business_Day_Start,HOUR(R51)>=0)+AND(HOUR(R51)>=Business_Day_End,HOUR(R51)<=23)>0 -> FALSE | Y51: =ABS(L51)>High_Value_GL_Threshold -> FALSE | Z51: =AND(ABS(L51)>=Round_Number_Threshold,MOD(ABS(L51),Round_Number_Threshold)=0) -> FALSE
A52: JE-00024 | B52: JE-00024-02 | C52: 45700 | D52: 45695 | E52: 2025 | F52: 2 | G52: 1500 | H52: Property and Equipment | I52: Asset | J52: 0 | K52: 78153 | L52: =J52-K52 -> -78153 | M52: Monthly depreciation | N52: DOC-00024 | O52: AUTO_DEPR | P52: USR_FA | Q52: USR_SA | R52: 45700.406 | S52: Approved | V52: =AND(C52>=Year_End_Window_Start,C52<=Year_End_Window_End) -> FALSE | W52: =AND(OR(WEEKDAY(C52,2)=5,WEEKDAY(C52,2)=6),'01_Parameters'!$C$11="Enabled") -> FALSE | X52: =AND(HOUR(R52)<Business_Day_Start,HOUR(R52)>=0)+AND(HOUR(R52)>=Business_Day_End,HOUR(R52)<=23)>0 -> FALSE | Y52: =ABS(L52)>High_Value_GL_Threshold -> FALSE | Z52: =AND(ABS(L52)>=Round_Number_Threshold,MOD(ABS(L52),Round_Number_Threshold)=0) -> FALSE
A53: JE-00025 | B53: JE-00025-01 | C53: 45976 | D53: 45973 | E53: 2025 | F53: 11 | G53: 6500 | H53: Depreciation Expense | I53: Expense | J53: 15062 | K53: 0 | L53: =J53-K53 -> 15062 | M53: Monthly depreciation | N53: DOC-00025 | O53: AUTO_DEPR | P53: USR_NA | Q53: USR_SA | R53: 45976.26 | S53: Approved | V53: =AND(C53>=Year_End_Window_Start,C53<=Year_End_Window_End) -> FALSE | W53: =AND(OR(WEEKDAY(C53,2)=5,WEEKDAY(C53,2)=6),'01_Parameters'!$C$11="Enabled") -> TRUE | X53: =AND(HOUR(R53)<Business_Day_Start,HOUR(R53)>=0)+AND(HOUR(R53)>=Business_Day_End,HOUR(R53)<=23)>0 -> TRUE | Y53: =ABS(L53)>High_Value_GL_Threshold -> FALSE | Z53: =AND(ABS(L53)>=Round_Number_Threshold,MOD(ABS(L53),Round_Number_Threshold)=0) -> FALSE
A54: JE-00025 | B54: JE-00025-02 | C54: 45976 | D54: 45973 | E54: 2025 | F54: 11 | G54: 1500 | H54: Property and Equipment | I54: Asset | J54: 0 | K54: 15062 | L54: =J54-K54 -> -15062 | M54: Monthly depreciation | N54: DOC-00025 | O54: AUTO_DEPR | P54: USR_NA | Q54: USR_SA | R54: 45976.26 | S54: Approved | V54: =AND(C54>=Year_End_Window_Start,C54<=Year_End_Window_End) -> FALSE | W54: =AND(OR(WEEKDAY(C54,2)=5,WEEKDAY(C54,2)=6),'01_Parameters'!$C$11="Enabled") -> TRUE | X54: =AND(HOUR(R54)<Business_Day_Start,HOUR(R54)>=0)+AND(HOUR(R54)>=Business_Day_End,HOUR(R54)<=23)>0 -> TRUE | Y54: =ABS(L54)>High_Value_GL_Threshold -> FALSE | Z54: =AND(ABS(L54)>=Round_Number_Threshold,MOD(ABS(L54),Round_Number_Threshold)=0) -> FALSE
A55: JE-00026 | B55: JE-00026-01 | C55: 45692 | D55: 45690 | E55: 2025 | F55: 2 | G55: 6500 | H55: Depreciation Expense | I55: Expense | J55: 70125.39 | K55: 0 | L55: =J55-K55 -> 70125.39 | M55: Monthly depreciation | N55: DOC-00026 | O55: AUTO_DEPR | P55: USR_OM | Q55: USR_RE | R55: 45692.625 | S55: Approved | V55: =AND(C55>=Year_End_Window_Start,C55<=Year_End_Window_End) -> FALSE | W55: =AND(OR(WEEKDAY(C55,2)=5,WEEKDAY(C55,2)=6),'01_Parameters'!$C$11="Enabled") -> FALSE | X55: =AND(HOUR(R55)<Business_Day_Start,HOUR(R55)>=0)+AND(HOUR(R55)>=Business_Day_End,HOUR(R55)<=23)>0 -> FALSE | Y55: =ABS(L55)>High_Value_GL_Threshold -> FALSE | Z55: =AND(ABS(L55)>=Round_Number_Threshold,MOD(ABS(L55),Round_Number_Threshold)=0) -> FALSE
A56: JE-00026 | B56: JE-00026-02 | C56: 45692 | D56: 45690 | E56: 2025 | F56: 2 | G56: 1500 | H56: Property and Equipment | I56: Asset | J56: 0 | K56: 70125.39 | L56: =J56-K56 -> -70125.39 | M56: Monthly depreciation | N56: DOC-00026 | O56: AUTO_DEPR | P56: USR_OM | Q56: USR_RE | R56: 45692.625 | S56: Approved | V56: =AND(C56>=Year_End_Window_Start,C56<=Year_End_Window_End) -> FALSE | W56: =AND(OR(WEEKDAY(C56,2)=5,WEEKDAY(C56,2)=6),'01_Parameters'!$C$11="Enabled") -> FALSE | X56: =AND(HOUR(R56)<Business_Day_Start,HOUR(R56)>=0)+AND(HOUR(R56)>=Business_Day_End,HOUR(R56)<=23)>0 -> FALSE | Y56: =ABS(L56)>High_Value_GL_Threshold -> FALSE | Z56: =AND(ABS(L56)>=Round_Number_Threshold,MOD(ABS(L56),Round_Number_Threshold)=0) -> FALSE
... A72: JE-00034 | B72: JE-00034-02 | C72: 45915 | D72: 45913 | E72: 2025 | F72: 9 | G72: 1200 | H72: Inventory | I72: Asset | J72: 0 | K72: 68838.5 | L72: =J72-K72 -> -68838.5 | M72: Inventory movement | N72: DOC-00034 | O72: AUTO_INVENTORY | P72: USR_OM | Q72: USR_SA | R72: 45915.5 | S72: Approved | V72: =AND(C72>=Year_End_Window_Start,C72<=Year_End_Window_End) -> FALSE | W72: =AND(OR(WEEKDAY(C72,2)=5,WEEKDAY(C72,2)=6),'01_Parameters'!$C$11="Enabled") -> FALSE | X72: =AND(HOUR(R72)<Business_Day_Start,HOUR(R72)>=0)+AND(HOUR(R72)>=Business_Day_End,HOUR(R72)<=23)>0 -> FALSE | Y72: =ABS(L72)>High_Value_GL_Threshold -> FALSE | Z72: =AND(ABS(L72)>=Round_Number_Threshold,MOD(ABS(L72),Round_Number_Threshold)=0) -> FALSE
A73: JE-00035 | B73: JE-00035-01 | C73: 45782 | D73: 45780 | E73: 2025 | F73: 5 | G73: 6400 | H73: Professional Fees | I73: Expense | J73: 32971.74 | K73: 0 | L73: =J73-K73 -> 32971.74 | M73: Supplier invoice posting | N73: INV-00035 | O73: AUTO_AP | P73: USR_NA | Q73: USR_AH | R73: 45782.896 | S73: Approved | T73: V001 | U73: INV-00035 | V73: =AND(C73>=Year_End_Window_Start,C73<=Year_End_Window_End) -> FALSE | W73: =AND(OR(WEEKDAY(C73,2)=5,WEEKDAY(C73,2)=6),'01_Parameters'!$C$11="Enabled") -> FALSE | X73: =AND(HOUR(R73)<Business_Day_Start,HOUR(R73)>=0)+AND(HOUR(R73)>=Business_Day_End,HOUR(R73)<=23)>0 -> TRUE | Y73: =ABS(L73)>High_Value_GL_Threshold -> FALSE | Z73: =AND(ABS(L73)>=Round_Number_Threshold,MOD(ABS(L73),Round_Number_Threshold)=0) -> FALSE
A74: JE-00035 | B74: JE-00035-02 | C74: 45782 | D74: 45780 | E74: 2025 | F74: 5 | G74: 2000 | H74: Trade Payables | I74: Liability | J74: 0 | K74: 32971.74 | L74: =J74-K74 -> -32971.74 | M74: Supplier invoice posting | N74: INV-00035 | O74: AUTO_AP | P74: USR_NA | Q74: USR_AH | R74: 45782.896 | S74: Approved | T74: V001 | U74: INV-00035 | V74: =AND(C74>=Year_End_Window_Start,C74<=Year_End_Window_End) -> FALSE | W74: =AND(OR(WEEKDAY(C74,2)=5,WEEKDAY(C74,2)=6),'01_Parameters'!$C$11="Enabled") -> FALSE | X74: =AND(HOUR(R74)<Business_Day_Start,HOUR(R74)>=0)+AND(HOUR(R74)>=Business_Day_End,HOUR(R74)<=23)>0 -> TRUE | Y74: =ABS(L74)>High_Value_GL_Threshold -> FALSE | Z74: =AND(ABS(L74)>=Round_Number_Threshold,MOD(ABS(L74),Round_Number_Threshold)=0) -> FALSE
A75: JE-00036 | B75: JE-00036-01 | C75: 45961 | D75: 45961 | E75: 2025 | F75: 10 | G75: 6300 | H75: Marketing Expense | I75: Expense | J75: 44062.26 | K75: 0 | L75: =J75-K75 -> 44062.26 | M75: Supplier invoice posting | N75: INV-00036 | O75: AUTO_AP | P75: USR_NA | Q75: USR_SA | R75: 45961.49 | S75: Approved | T75: V010 | U75: INV-00036 | V75: =AND(C75>=Year_End_Window_Start,C75<=Year_End_Window_End) -> FALSE | W75: =AND(OR(WEEKDAY(C75,2)=5,WEEKDAY(C75,2)=6),'01_Parameters'!$C$11="Enabled") -> TRUE | X75: =AND(HOUR(R75)<Business_Day_Start,HOUR(R75)>=0)+AND(HOUR(R75)>=Business_Day_End,HOUR(R75)<=23)>0 -> FALSE | Y75: =ABS(L75)>High_Value_GL_Threshold -> FALSE | Z75: =AND(ABS(L75)>=Round_Number_Threshold,MOD(ABS(L75),Round_Number_Threshold)=0) -> FALSE
A76: JE-00036 | B76: JE-00036-02 | C76: 45961 | D76: 45961 | E76: 2025 | F76: 10 | G76: 2000 | H76: Trade Payables | I76: Liability | J76: 0 | K76: 44062.26 | L76: =J76-K76 -> -44062.26 | M76: Supplier invoice posting | N76: INV-00036 | O76: AUTO_AP | P76: USR_NA | Q76: USR_SA | R76: 45961.49 | S76: Approved | T76: V010 | U76: INV-00036 | V76: =AND(C76>=Year_End_Window_Start,C76<=Year_End_Window_End) -> FALSE | W76: =AND(OR(WEEKDAY(C76,2)=5,WEEKDAY(C76,2)=6),'01_Parameters'!$C$11="Enabled") -> TRUE | X76: =AND(HOUR(R76)<Business_Day_Start,HOUR(R76)>=0)+AND(HOUR(R76)>=Business_Day_End,HOUR(R76)<=23)>0 -> FALSE | Y76: =ABS(L76)>High_Value_GL_Threshold -> FALSE | Z76: =AND(ABS(L76)>=Round_Number_Threshold,MOD(ABS(L76),Round_Number_Threshold)=0) -> FALSE
A77: JE-00037 | B77: JE-00037-01 | C77: 45898 | D77: 45896 | E77: 2025 | F77: 8 | G77: 6200 | H77: Utilities Expense | I77: Expense | J77: 12910.41 | K77: 0 | L77: =J77-K77 -> 12910.41 | M77: Supplier invoice posting | N77: INV-00037 | O77: AUTO_AP | P77: USR_SA | Q77: USR_RE | R77: 45898.917 | S77: Approved | T77: V002 | U77: INV-00037 | V77: =AND(C77>=Year_End_Window_Start,C77<=Year_End_Window_End) -> FALSE | W77: =AND(OR(WEEKDAY(C77,2)=5,WEEKDAY(C77,2)=6),'01_Parameters'!$C$11="Enabled") -> TRUE | X77: =AND(HOUR(R77)<Business_Day_Start,HOUR(R77)>=0)+AND(HOUR(R77)>=Business_Day_End,HOUR(R77)<=23)>0 -> TRUE | Y77: =ABS(L77)>High_Value_GL_Threshold -> FALSE | Z77: =AND(ABS(L77)>=Round_Number_Threshold,MOD(ABS(L77),Round_Number_Threshold)=0) -> FALSE
A78: JE-00037 | B78: JE-00037-02 | C78: 45898 | D78: 45896 | E78: 2025 | F78: 8 | G78: 2000 | H78: Trade Payables | I78: Liability | J78: 0 | K78: 12910.41 | L78: =J78-K78 -> -12910.41 | M78: Supplier invoice posting | N78: INV-00037 | O78: AUTO_AP | P78: USR_SA | Q78: USR_RE | R78: 45898.917 | S78: Approved | T78: V002 | U78: INV-00037 | V78: =AND(C78>=Year_End_Window_Start,C78<=Year_End_Window_End) -> FALSE | W78: =AND(OR(WEEKDAY(C78,2)=5,WEEKDAY(C78,2)=6),'01_Parameters'!$C$11="Enabled") -> TRUE | X78: =AND(HOUR(R78)<Business_Day_Start,HOUR(R78)>=0)+AND(HOUR(R78)>=Business_Day_End,HOUR(R78)<=23)>0 -> TRUE | Y78: =ABS(L78)>High_Value_GL_Threshold -> FALSE | Z78: =AND(ABS(L78)>=Round_Number_Threshold,MOD(ABS(L78),Round_Number_Threshold)=0) -> FALSE
A79: JE-00038 | B79: JE-00038-01 | C79: 45921 | D79: 45921 | E79: 2025 | F79: 9 | G79: 1200 | H79: Inventory | I79: Asset | J79: 14806.47 | K79: 0 | L79: =J79-K79 -> 14806.47 | M79: Supplier invoice posting | N79: INV-00038 | O79: AUTO_AP | P79: USR_OM | Q79: USR_AH | R79: 45921.635 | S79: Approved | T79: V005 | U79: INV-00038 | V79: =AND(C79>=Year_End_Window_Start,C79<=Year_End_Window_End) -> FALSE | W79: =AND(OR(WEEKDAY(C79,2)=5,WEEKDAY(C79,2)=6),'01_Parameters'!$C$11="Enabled") -> FALSE | X79: =AND(HOUR(R79)<Business_Day_Start,HOUR(R79)>=0)+AND(HOUR(R79)>=Business_Day_End,HOUR(R79)<=23)>0 -> FALSE | Y79: =ABS(L79)>High_Value_GL_Threshold -> FALSE | Z79: =AND(ABS(L79)>=Round_Number_Threshold,MOD(ABS(L79),Round_Number_Threshold)=0) -> FALSE
A80: JE-00038 | B80: JE-00038-02 | C80: 45921 | D80: 45921 | E80: 2025 | F80: 9 | G80: 2000 | H80: Trade Payables | I80: Liability | J80: 0 | K80: 14806.47 | L80: =J80-K80 -> -14806.47 | M80: Supplier invoice posting | N80: INV-00038 | O80: AUTO_AP | P80: USR_OM | Q80: USR_AH | R80: 45921.635 | S80: Approved | T80: V005 | U80: INV-00038 | V80: =AND(C80>=Year_End_Window_Start,C80<=Year_End_Window_End) -> FALSE | W80: =AND(OR(WEEKDAY(C80,2)=5,WEEKDAY(C80,2)=6),'01_Parameters'!$C$11="Enabled") -> FALSE | X80: =AND(HOUR(R80)<Business_Day_Start,HOUR(R80)>=0)+AND(HOUR(R80)>=Business_Day_End,HOUR(R80)<=23)>0 -> FALSE | Y80: =ABS(L80)>High_Value_GL_Threshold -> FALSE | Z80: =AND(ABS(L80)>=Round_Number_Threshold,MOD(ABS(L80),Round_Number_Threshold)=0) -> FALSE
A81: JE-00039 | B81: JE-00039-01 | C81: 45822 | D81: 45817 | E81: 2025 | F81: 6 | G81: 6500 | H81: Depreciation Expense | I81: Expense | J81: 53598.46 | K81: 0 | L81: =J81-K81 -> 53598.46 | M81: Monthly depreciation | N81: DOC-00039 | O81: AUTO_DEPR | P81: USR_SA | Q81: USR_NA | R81: 45822.823 | S81: Approved | V81: =AND(C81>=Year_End_Window_Start,C81<=Year_End_Window_End) -> FALSE | W81: =AND(OR(WEEKDAY(C81,2)=5,WEEKDAY(C81,2)=6),'01_Parameters'!$C$11="Enabled") -> TRUE | X81: =AND(HOUR(R81)<Business_Day_Start,HOUR(R81)>=0)+AND(HOUR(R81)>=Business_Day_End,HOUR(R81)<=23)>0 -> TRUE | Y81: =ABS(L81)>High_Value_GL_Threshold -> FALSE | Z81: =AND(ABS(L81)>=Round_Number_Threshold,MOD(ABS(L81),Round_Number_Threshold)=0) -> FALSE
A82: JE-00039 | B82: JE-00039-02 | C82: 45822 | D82: 45817 | E82: 2025 | F82: 6 | G82: 1500 | H82: Property and Equipment | I82: Asset | J82: 0 | K82: 53598.46 | L82: =J82-K82 -> -53598.46 | M82: Monthly depreciation | N82: DOC-00039 | O82: AUTO_DEPR | P82: USR_SA | Q82: USR_NA | R82: 45822.823 | S82: Approved | V82: =AND(C82>=Year_End_Window_Start,C82<=Year_End_Window_End) -> FALSE | W82: =AND(OR(WEEKDAY(C82,2)=5,WEEKDAY(C82,2)=6),'01_Parameters'!$C$11="Enabled") -> TRUE | X82: =AND(HOUR(R82)<Business_Day_Start,HOUR(R82)>=0)+AND(HOUR(R82)>=Business_Day_End,HOUR(R82)<=23)>0 -> TRUE | Y82: =ABS(L82)>High_Value_GL_Threshold -> FALSE | Z82: =AND(ABS(L82)>=Round_Number_Threshold,MOD(ABS(L82),Round_Number_Threshold)=0) -> FALSE
A83: JE-00040 | B83: JE-00040-01 | C83: 45728 | D83: 45726 | E83: 2025 | F83: 3 | G83: 6100 | H83: Rent Expense | I83: Expense | J83: 134573.13 | K83: 0 | L83: =J83-K83 -> 134573.13 | M83: Manual period adjustment | N83: DOC-00040 | O83: MANUAL_JE | P83: USR_NA | Q83: USR_RE | R83: 45728.667 | S83: Approved | V83: =AND(C83>=Year_End_Window_Start,C83<=Year_End_Window_End) -> FALSE | W83: =AND(OR(WEEKDAY(C83,2)=5,WEEKDAY(C83,2)=6),'01_Parameters'!$C$11="Enabled") -> FALSE | X83: =AND(HOUR(R83)<Business_Day_Start,HOUR(R83)>=0)+AND(HOUR(R83)>=Business_Day_End,HOUR(R83)<=23)>0 -> FALSE | Y83: =ABS(L83)>High_Value_GL_Threshold -> TRUE | Z83: =AND(ABS(L83)>=Round_Number_Threshold,MOD(ABS(L83),Round_Number_Threshold)=0) -> FALSE
A84: JE-00040 | B84: JE-00040-02 | C84: 45728 | D84: 45726 | E84: 2025 | F84: 3 | G84: 2000 | H84: Trade Payables | I84: Liability | J84: 0 | K84: 134573.13 | L84: =J84-K84 -> -134573.13 | M84: Manual period adjustment | N84: DOC-00040 | O84: MANUAL_JE | P84: USR_NA | Q84: USR_RE | R84: 45728.667 | S84: Approved | V84: =AND(C84>=Year_End_Window_Start,C84<=Year_End_Window_End) -> FALSE | W84: =AND(OR(WEEKDAY(C84,2)=5,WEEKDAY(C84,2)=6),'01_Parameters'!$C$11="Enabled") -> FALSE | X84: =AND(HOUR(R84)<Business_Day_Start,HOUR(R84)>=0)+AND(HOUR(R84)>=Business_Day_End,HOUR(R84)<=23)>0 -> FALSE | Y84: =ABS(L84)>High_Value_GL_Threshold -> TRUE | Z84: =AND(ABS(L84)>=Round_Number_Threshold,MOD(ABS(L84),Round_Number_Threshold)=0) -> FALSE
A85: JE-00041 | B85: JE-00041-01 | C85: 45876 | D85: 45876 | E85: 2025 | F85: 8 | G85: 6200 | H85: Utilities Expense | I85: Expense | J85: 49052.93 | K85: 0 | L85: =J85-K85 -> 49052.93 | M85: Supplier invoice posting | N85: INV-00041 | O85: AUTO_AP | P85: USR_NA | Q85: USR_RE | R85: 45876.323 | S85: Approved | T85: V004 | U85: INV-00041 | V85: =AND(C85>=Year_End_Window_Start,C85<=Year_End_Window_End) -> FALSE | W85: =AND(OR(WEEKDAY(C85,2)=5,WEEKDAY(C85,2)=6),'01_Parameters'!$C$11="Enabled") -> FALSE | X85: =AND(HOUR(R85)<Business_Day_Start,HOUR(R85)>=0)+AND(HOUR(R85)>=Business_Day_End,HOUR(R85)<=23)>0 -> TRUE | Y85: =ABS(L85)>High_Value_GL_Threshold -> FALSE | Z85: =AND(ABS(L85)>=Round_Number_Threshold,MOD(ABS(L85),Round_Number_Threshold)=0) -> FALSE
A86: JE-00041 | B86: JE-00041-02 | C86: 45876 | D86: 45876 | E86: 2025 | F86: 8 | G86: 2000 | H86: Trade Payables | I86: Liability | J86: 0 | K86: 49052.93 | L86: =J86-K86 -> -49052.93 | M86: Supplier invoice posting | N86: INV-00041 | O86: AUTO_AP | P86: USR_NA | Q86: USR_RE | R86: 45876.323 | S86: Approved | T86: V004 | U86: INV-00041 | V86: =AND(C86>=Year_End_Window_Start,C86<=Year_End_Window_End) -> FALSE | W86: =AND(OR(WEEKDAY(C86,2)=5,WEEKDAY(C86,2)=6),'01_Parameters'!$C$11="Enabled") -> FALSE | X86: =AND(HOUR(R86)<Business_Day_Start,HOUR(R86)>=0)+AND(HOUR(R86)>=Business_Day_End,HOUR(R86)<=23)>0 -> TRUE | Y86: =ABS(L86)>High_Value_GL_Threshold -> FALSE | Z86: =AND(ABS(L86)>=Round_Number_Threshold,MOD(ABS(L86),Round_Number_Threshold)=0) -> FALSE
A87: JE-00042 | B87: JE-00042-01 | C87: 45743 | D87: 45740 | E87: 2025 | F87: 3 | G87: 6600 | H87: Other Operating Expenses | I87: Expense | J87: 12990.5 | K87: 0 | L87: =J87-K87 -> 12990.5 | M87: Supplier invoice posting | N87: INV-00042 | O87: AUTO_AP | P87: USR_FA | Q87: USR_OM | R87: 45743.917 | S87: Approved | T87: V004 | U87: INV-00042 | V87: =AND(C87>=Year_End_Window_Start,C87<=Year_End_Window_End) -> FALSE | W87: =AND(OR(WEEKDAY(C87,2)=5,WEEKDAY(C87,2)=6),'01_Parameters'!$C$11="Enabled") -> FALSE | X87: =AND(HOUR(R87)<Business_Day_Start,HOUR(R87)>=0)+AND(HOUR(R87)>=Business_Day_End,HOUR(R87)<=23)>0 -> TRUE | Y87: =ABS(L87)>High_Value_GL_Threshold -> FALSE | Z87: =AND(ABS(L87)>=Round_Number_Threshold,MOD(ABS(L87),Round_Number_Threshold)=0) -> FALSE
A88: JE-00042 | B88: JE-00042-02 | C88: 45743 | D88: 45740 | E88: 2025 | F88: 3 | G88: 2000 | H88: Trade Payables | I88: Liability | J88: 0 | K88: 12990.5 | L88: =J88-K88 -> -12990.5 | M88: Supplier invoice posting | N88: INV-00042 | O88: AUTO_AP | P88: USR_FA | Q88: USR_OM | R88: 45743.917 | S88: Approved | T88: V004 | U88: INV-00042 | V88: =AND(C88>=Year_End_Window_Start,C88<=Year_End_Window_End) -> FALSE | W88: =AND(OR(WEEKDAY(C88,2)=5,WEEKDAY(C88,2)=6),'01_Parameters'!$C$11="Enabled") -> FALSE | X88: =AND(HOUR(R88)<Business_Day_Start,HOUR(R88)>=0)+AND(HOUR(R88)>=Business_Day_End,HOUR(R88)<=23)>0 -> TRUE | Y88: =ABS(L88)>High_Value_GL_Threshold -> FALSE | Z88: =AND(ABS(L88)>=Round_Number_Threshold,MOD(ABS(L88),Round_Number_Threshold)=0) -> FALSE
A89: JE-00043 | B89: JE-00043-01 | C89: 45694 | D89: 45690 | E89: 2025 | F89: 2 | G89: 6600 | H89: Other Operating Expenses | I89: Expense | J89: 4265.65 | K89: 0 | L89: =J89-K89 -> 4265.65 | M89: Supplier invoice posting | N89: INV-00043 | O89: AUTO_AP | P89: USR_NA | Q89: USR_SA | R89: 45694.688 | S89: Approved | T89: V003 | U89: INV-00043 | V89: =AND(C89>=Year_End_Window_Start,C89<=Year_End_Window_End) -> FALSE | W89: =AND(OR(WEEKDAY(C89,2)=5,WEEKDAY(C89,2)=6),'01_Parameters'!$C$11="Enabled") -> FALSE | X89: =AND(HOUR(R89)<Business_Day_Start,HOUR(R89)>=0)+AND(HOUR(R89)>=Business_Day_End,HOUR(R89)<=23)>0 -> FALSE | Y89: =ABS(L89)>High_Value_GL_Threshold -> FALSE | Z89: =AND(ABS(L89)>=Round_Number_Threshold,MOD(ABS(L89),Round_Number_Threshold)=0) -> FALSE
A90: JE-00043 | B90: JE-00043-02 | C90: 45694 | D90: 45690 | E90: 2025 | F90: 2 | G90: 2000 | H90: Trade Payables | I90: Liability | J90: 0 | K90: 4265.65 | L90: =J90-K90 -> -4265.65 | M90: Supplier invoice posting | N90: INV-00043 | O90: AUTO_AP | P90: USR_NA | Q90: USR_SA | R90: 45694.688 | S90: Approved | T90: V003 | U90: INV-00043 | V90: =AND(C90>=Year_End_Window_Start,C90<=Year_End_Window_End) -> FALSE | W90: =AND(OR(WEEKDAY(C90,2)=5,WEEKDAY(C90,2)=6),'01_Parameters'!$C$11="Enabled") -> FALSE | X90: =AND(HOUR(R90)<Business_Day_Start,HOUR(R90)>=0)+AND(HOUR(R90)>=Business_Day_End,HOUR(R90)<=23)>0 -> FALSE | Y90: =ABS(L90)>High_Value_GL_Threshold -> FALSE | Z90: =AND(ABS(L90)>=Round_Number_Threshold,MOD(ABS(L90),Round_Number_Threshold)=0) -> FALSE
A91: JE-00044 | B91: JE-00044-01 | C91: 45681 | D91: 45680 | E91: 2025 | F91: 1 | G91: 1100 | H91: Trade Receivables | I91: Asset | J91: 21797.53 | K91: 0 | L91: =J91-K91 -> 21797.53 | M91: Daily retail sales | N91: DOC-00044 | O91: AUTO_SALES | P91: USR_AH | Q91: USR_SA | R91: 45681.646 | S91: Approved | V91: =AND(C91>=Year_End_Window_Start,C91<=Year_End_Window_End) -> FALSE | W91: =AND(OR(WEEKDAY(C91,2)=5,WEEKDAY(C91,2)=6),'01_Parameters'!$C$11="Enabled") -> TRUE | X91: =AND(HOUR(R91)<Business_Day_Start,HOUR(R91)>=0)+AND(HOUR(R91)>=Business_Day_End,HOUR(R91)<=23)>0 -> FALSE | Y91: =ABS(L91)>High_Value_GL_Threshold -> FALSE | Z91: =AND(ABS(L91)>=Round_Number_Threshold,MOD(ABS(L91),Round_Number_Threshold)=0) -> FALSE
A92: JE-00044 | B92: JE-00044-02 | C92: 45681 | D92: 45680 | E92: 2025 | F92: 1 | G92: 4000 | H92: Sales Revenue | I92: Revenue | J92: 0 | K92: 21797.53 | L92: =J92-K92 -> -21797.53 | M92: Daily retail sales | N92: DOC-00044 | O92: AUTO_SALES | P92: USR_AH | Q92: USR_SA | R92: 45681.646 | S92: Approved | V92: =AND(C92>=Year_End_Window_Start,C92<=Year_End_Window_End) -> FALSE | W92: =AND(OR(WEEKDAY(C92,2)=5,WEEKDAY(C92,2)=6),'01_Parameters'!$C$11="Enabled") -> TRUE | X92: =AND(HOUR(R92)<Business_Day_Start,HOUR(R92)>=0)+AND(HOUR(R92)>=Business_Day_End,HOUR(R92)<=23)>0 -> FALSE | Y92: =ABS(L92)>High_Value_GL_Threshold -> FALSE | Z92: =AND(ABS(L92)>=Round_Number_Threshold,MOD(ABS(L92),Round_Number_Threshold)=0) -> FALSE
A93: JE-00045 | B93: JE-00045-01 | C93: 45876 | D93: 45871 | E93: 2025 | F93: 8 | G93: 6300 | H93: Marketing Expense | I93: Expense | J93: 145000 | K93: 0 | L93: =J93-K93 -> 145000 | M93: Supplier invoice posting | N93: INV-00045 | O93: AUTO_AP | P93: USR_NA | Q93: USR_SA | R93: 45876.865 | S93: Approved | T93: V005 | U93: INV-00045 | V93: =AND(C93>=Year_End_Window_Start,C93<=Year_End_Window_End) -> FALSE | W93: =AND(OR(WEEKDAY(C93,2)=5,WEEKDAY(C93,2)=6),'01_Parameters'!$C$11="Enabled") -> FALSE | X93: =AND(HOUR(R93)<Business_Day_Start,HOUR(R93)>=0)+AND(HOUR(R93)>=Business_Day_End,HOUR(R93)<=23)>0 -> TRUE | Y93: =ABS(L93)>High_Value_GL_Threshold -> TRUE | Z93: =AND(ABS(L93)>=Round_Number_Threshold,MOD(ABS(L93),Round_Number_Threshold)=0) -> FALSE
A94: JE-00045 | B94: JE-00045-02 | C94: 45876 | D94: 45871 | E94: 2025 | F94: 8 | G94: 2000 | H94: Trade Payables | I94: Liability | J94: 0 | K94: 145000 | L94: =J94-K94 -> -145000 | M94: Supplier invoice posting | N94: INV-00045 | O94: AUTO_AP | P94: USR_NA | Q94: USR_SA | R94: 45876.865 | S94: Approved | T94: V005 | U94: INV-00045 | V94: =AND(C94>=Year_End_Window_Start,C94<=Year_End_Window_End) -> FALSE | W94: =AND(OR(WEEKDAY(C94,2)=5,WEEKDAY(C94,2)=6),'01_Parameters'!$C$11="Enabled") -> FALSE | X94: =AND(HOUR(R94)<Business_Day_Start,HOUR(R94)>=0)+AND(HOUR(R94)>=Business_Day_End,HOUR(R94)<=23)>0 -> TRUE | Y94: =ABS(L94)>High_Value_GL_Threshold -> TRUE | Z94: =AND(ABS(L94)>=Round_Number_Threshold,MOD(ABS(L94),Round_Number_Threshold)=0) -> FALSE
A95: JE-00046 | B95: JE-00046-01 | C95: 45784 | D95: 45782 | E95: 2025 | F95: 5 | G95: 6500 | H95: Depreciation Expense | I95: Expense | J95: 2364.12 | K95: 0 | L95: =J95-K95 -> 2364.12 | M95: Monthly depreciation | N95: DOC-00046 | O95: AUTO_DEPR | P95: USR_FA | Q95: USR_OM | R95: 45784.49 | S95: Approved | V95: =AND(C95>=Year_End_Window_Start,C95<=Year_End_Window_End) -> FALSE | W95: =AND(OR(WEEKDAY(C95,2)=5,WEEKDAY(C95,2)=6),'01_Parameters'!$C$11="Enabled") -> FALSE | X95: =AND(HOUR(R95)<Business_Day_Start,HOUR(R95)>=0)+AND(HOUR(R95)>=Business_Day_End,HOUR(R95)<=23)>0 -> FALSE | Y95: =ABS(L95)>High_Value_GL_Threshold -> FALSE | Z95: =AND(ABS(L95)>=Round_Number_Threshold,MOD(ABS(L95),Round_Number_Threshold)=0) -> FALSE
A96: JE-00046 | B96: JE-00046-02 | C96: 45784 | D96: 45782 | E96: 2025 | F96: 5 | G96: 1500 | H96: Property and Equipment | I96: Asset | J96: 0 | K96: 2364.12 | L96: =J96-K96 -> -2364.12 | M96: Monthly depreciation | N96: DOC-00046 | O96: AUTO_DEPR | P96: USR_FA | Q96: USR_OM | R96: 45784.49 | S96: Approved | V96: =AND(C96>=Year_End_Window_Start,C96<=Year_End_Window_End) -> FALSE | W96: =AND(OR(WEEKDAY(C96,2)=5,WEEKDAY(C96,2)=6),'01_Parameters'!$C$11="Enabled") -> FALSE | X96: =AND(HOUR(R96)<Business_Day_Start,HOUR(R96)>=0)+AND(HOUR(R96)>=Business_Day_End,HOUR(R96)<=23)>0 -> FALSE | Y96: =ABS(L96)>High_Value_GL_Threshold -> FALSE | Z96: =AND(ABS(L96)>=Round_Number_Threshold,MOD(ABS(L96),Round_Number_Threshold)=0) -> FALSE
A97: JE-00047 | B97: JE-00047-01 | C97: 45739 | D97: 45737 | E97: 2025 | F97: 3 | G97: 1100 | H97: Trade Receivables | I97: Asset | J97: 48342.6 | K97: 0 | L97: =J97-K97 -> 48342.6 | M97: Daily retail sales | N97: DOC-00047 | O97: AUTO_SALES | P97: USR_AH | Q97: USR_SA | R97: 45739.688 | S97: Approved | V97: =AND(C97>=Year_End_Window_Start,C97<=Year_End_Window_End) -> FALSE | W97: =AND(OR(WEEKDAY(C97,2)=5,WEEKDAY(C97,2)=6),'01_Parameters'!$C$11="Enabled") -> FALSE | X97: =AND(HOUR(R97)<Business_Day_Start,HOUR(R97)>=0)+AND(HOUR(R97)>=Business_Day_End,HOUR(R97)<=23)>0 -> FALSE | Y97: =ABS(L97)>High_Value_GL_Threshold -> FALSE | Z97: =AND(ABS(L97)>=Round_Number_Threshold,MOD(ABS(L97),Round_Number_Threshold)=0) -> FALSE
A98: JE-00047 | B98: JE-00047-02 | C98: 45739 | D98: 45737 | E98: 2025 | F98: 3 | G98: 4000 | H98: Sales Revenue | I98: Revenue | J98: 0 | K98: 48342.6 | L98: =J98-K98 -> -48342.6 | M98: Daily retail sales | N98: DOC-00047 | O98: AUTO_SALES | P98: USR_AH | Q98: USR_SA | R98: 45739.688 | S98: Approved | V98: =AND(C98>=Year_End_Window_Start,C98<=Year_End_Window_End) -> FALSE | W98: =AND(OR(WEEKDAY(C98,2)=5,WEEKDAY(C98,2)=6),'01_Parameters'!$C$11="Enabled") -> FALSE | X98: =AND(HOUR(R98)<Business_Day_Start,HOUR(R98)>=0)+AND(HOUR(R98)>=Business_Day_End,HOUR(R98)<=23)>0 -> FALSE | Y98: =ABS(L98)>High_Value_GL_Threshold -> FALSE | Z98: =AND(ABS(L98)>=Round_Number_Threshold,MOD(ABS(L98),Round_Number_Threshold)=0) -> FALSE
A99: JE-00048 | B99: JE-00048-01 | C99: 45726 | D99: 45725 | E99: 2025 | F99: 3 | G99: 6100 | H99: Rent Expense | I99: Expense | J99: 163301.84 | K99: 0 | L99: =J99-K99 -> 163301.84 | M99: Manual period adjustment | N99: DOC-00048 | O99: MANUAL_JE | P99: USR_RE | Q99: USR_SA | R99: 45726.635 | S99: Approved | V99: =AND(C99>=Year_End_Window_Start,C99<=Year_End_Window_End) -> FALSE | W99: =AND(OR(WEEKDAY(C99,2)=5,WEEKDAY(C99,2)=6),'01_Parameters'!$C$11="Enabled") -> FALSE | X99: =AND(HOUR(R99)<Business_Day_Start,HOUR(R99)>=0)+AND(HOUR(R99)>=Business_Day_End,HOUR(R99)<=23)>0 -> FALSE | Y99: =ABS(L99)>High_Value_GL_Threshold -> TRUE | Z99: =AND(ABS(L99)>=Round_Number_Threshold,MOD(ABS(L99),Round_Number_Threshold)=0) -> FALSE
A100: JE-00048 | B100: JE-00048-02 | C100: 45726 | D100: 45725 | E100: 2025 | F100: 3 | G100: 2000 | H100: Trade Payables | I100: Liability | J100: 0 | K100: 163301.84 | L100: =J100-K100 -> -163301.84 | M100: Manual period adjustment | N100: DOC-00048 | O100: MANUAL_JE | P100: USR_RE | Q100: USR_SA | R100: 45726.635 | S100: Approved | V100: =AND(C100>=Year_End_Window_Start,C100<=Year_End_Window_End) -> FALSE | W100: =AND(OR(WEEKDAY(C100,2)=5,WEEKDAY(C100,2)=6),'01_Parameters'!$C$11="Enabled") -> FALSE | X100: =AND(HOUR(R100)<Business_Day_Start,HOUR(R100)>=0)+AND(HOUR(R100)>=Business_Day_End,HOUR(R100)<=23)>0 -> FALSE | Y100: =ABS(L100)>High_Value_GL_Threshold -> TRUE | Z100: =AND(ABS(L100)>=Round_Number_Threshold,MOD(ABS(L100),Round_Number_Threshold)=0) -> FALSE
A101: JE-00049 | B101: JE-00049-01 | C101: 45686 | D101: 45681 | E101: 2025 | F101: 1 | G101: 5000 | H101: Cost of Goods Sold | I101: Expense | J101: 76858.06 | K101: 0 | L101: =J101-K101 -> 76858.06 | M101: Inventory movement | N101: DOC-00049 | O101: AUTO_INVENTORY | P101: USR_SA | Q101: USR_OM | R101: 45686.594 | S101: Approved | V101: =AND(C101>=Year_End_Window_Start,C101<=Year_End_Window_End) -> FALSE | W101: =AND(OR(WEEKDAY(C101,2)=5,WEEKDAY(C101,2)=6),'01_Parameters'!$C$11="Enabled") -> FALSE | X101: =AND(HOUR(R101)<Business_Day_Start,HOUR(R101)>=0)+AND(HOUR(R101)>=Business_Day_End,HOUR(R101)<=23)>0 -> FALSE | Y101: =ABS(L101)>High_Value_GL_Threshold -> FALSE | Z101: =AND(ABS(L101)>=Round_Number_Threshold,MOD(ABS(L101),Round_Number_Threshold)=0) -> FALSE
A102: JE-00049 | B102: JE-00049-02 | C102: 45686 | D102: 45681 | E102: 2025 | F102: 1 | G102: 1200 | H102: Inventory | I102: Asset | J102: 0 | K102: 76858.06 | L102: =J102-K102 -> -76858.06 | M102: Inventory movement | N102: DOC-00049 | O102: AUTO_INVENTORY | P102: USR_SA | Q102: USR_OM | R102: 45686.594 | S102: Approved | V102: =AND(C102>=Year_End_Window_Start,C102<=Year_End_Window_End) -> FALSE | W102: =AND(OR(WEEKDAY(C102,2)=5,WEEKDAY(C102,2)=6),'01_Parameters'!$C$11="Enabled") -> FALSE | X102: =AND(HOUR(R102)<Business_Day_Start,HOUR(R102)>=0)+AND(HOUR(R102)>=Business_Day_End,HOUR(R102)<=23)>0 -> FALSE | Y102: =ABS(L102)>High_Value_GL_Threshold -> FALSE | Z102: =AND(ABS(L102)>=Round_Number_Threshold,MOD(ABS(L102),Round_Number_Threshold)=0) -> FALSE
A103: JE-00050 | B103: JE-00050-01 | C103: 45908 | D103: 45904 | E103: 2025 | F103: 9 | G103: 1100 | H103: Trade Receivables | I103: Asset | J103: 11358.33 | K103: 0 | L103: =J103-K103 -> 11358.33 | M103: Daily retail sales | N103: DOC-00050 | O103: AUTO_SALES | P103: USR_RE | Q103: USR_NA | R103: 45908.688 | S103: Approved | V103: =AND(C103>=Year_End_Window_Start,C103<=Year_End_Window_End) -> FALSE | W103: =AND(OR(WEEKDAY(C103,2)=5,WEEKDAY(C103,2)=6),'01_Parameters'!$C$11="Enabled") -> FALSE | X103: =AND(HOUR(R103)<Business_Day_Start,HOUR(R103)>=0)+AND(HOUR(R103)>=Business_Day_End,HOUR(R103)<=23)>0 -> FALSE | Y103: =ABS(L103)>High_Value_GL_Threshold -> FALSE | Z103: =AND(ABS(L103)>=Round_Number_Threshold,MOD(ABS(L103),Round_Number_Threshold)=0) -> FALSE
A104: JE-00050 | B104: JE-00050-02 | C104: 45908 | D104: 45904 | E104: 2025 | F104: 9 | G104: 4000 | H104: Sales Revenue | I104: Revenue | J104: 0 | K104: 11358.33 | L104: =J104-K104 -> -11358.33 | M104: Daily retail sales | N104: DOC-00050 | O104: AUTO_SALES | P104: USR_RE | Q104: USR_NA | R104: 45908.688 | S104: Approved | V104: =AND(C104>=Year_End_Window_Start,C104<=Year_End_Window_End) -> FALSE | W104: =AND(OR(WEEKDAY(C104,2)=5,WEEKDAY(C104,2)=6),'01_Parameters'!$C$11="Enabled") -> FALSE | X104: =AND(HOUR(R104)<Business_Day_Start,HOUR(R104)>=0)+AND(HOUR(R104)>=Business_Day_End,HOUR(R104)<=23)>0 -> FALSE | Y104: =ABS(L104)>High_Value_GL_Threshold -> FALSE | Z104: =AND(ABS(L104)>=Round_Number_Threshold,MOD(ABS(L104),Round_Number_Threshold)=0) -> FALSE
A105: JE-00051 | B105: JE-00051-01 | C105: 45780 | D105: 45775 | E105: 2025 | F105: 5 | G105: 6600 | H105: Other Operating Expenses | I105: Expense | J105: 137339.27 | K105: 0 | L105: =J105-K105 -> 137339.27 | M105: Manual period adjustment | N105: DOC-00051 | O105: MANUAL_JE | P105: USR_AH | Q105: USR_FA | R105: 45780.625 | S105: Approved | V105: =AND(C105>=Year_End_Window_Start,C105<=Year_End_Window_End) -> FALSE | W105: =AND(OR(WEEKDAY(C105,2)=5,WEEKDAY(C105,2)=6),'01_Parameters'!$C$11="Enabled") -> TRUE | X105: =AND(HOUR(R105)<Business_Day_Start,HOUR(R105)>=0)+AND(HOUR(R105)>=Business_Day_End,HOUR(R105)<=23)>0 -> FALSE | Y105: =ABS(L105)>High_Value_GL_Threshold -> TRUE | Z105: =AND(ABS(L105)>=Round_Number_Threshold,MOD(ABS(L105),Round_Number_Threshold)=0) -> FALSE
A106: JE-00051 | B106: JE-00051-02 | C106: 45780 | D106: 45775 | E106: 2025 | F106: 5 | G106: 2000 | H106: Trade Payables | I106: Liability | J106: 0 | K106: 137339.27 | L106: =J106-K106 -> -137339.27 | M106: Manual period adjustment | N106: DOC-00051 | O106: MANUAL_JE | P106: USR_AH | Q106: USR_FA | R106: 45780.625 | S106: Approved | V106: =AND(C106>=Year_End_Window_Start,C106<=Year_End_Window_End) -> FALSE | W106: =AND(OR(WEEKDAY(C106,2)=5,WEEKDAY(C106,2)=6),'01_Parameters'!$C$11="Enabled") -> TRUE | X106: =AND(HOUR(R106)<Business_Day_Start,HOUR(R106)>=0)+AND(HOUR(R106)>=Business_Day_End,HOUR(R106)<=23)>0 -> FALSE | Y106: =ABS(L106)>High_Value_GL_Threshold -> TRUE | Z106: =AND(ABS(L106)>=Round_Number_Threshold,MOD(ABS(L106),Round_Number_Threshold)=0) -> FALSE
... A132: JE-00064 | B132: JE-00064-02 | C132: 45678 | D132: 45677 | E132: 2025 | F132: 1 | G132: 1500 | H132: Property and Equipment | I132: Asset | J132: 0 | K132: 80133.89 | L132: =J132-K132 -> -80133.89 | M132: Monthly depreciation | N132: DOC-00064 | O132: AUTO_DEPR | P132: USR_SA | Q132: USR_AH | R132: 45678.708 | S132: Approved | V132: =AND(C132>=Year_End_Window_Start,C132<=Year_End_Window_End) -> FALSE | W132: =AND(OR(WEEKDAY(C132,2)=5,WEEKDAY(C132,2)=6),'01_Parameters'!$C$11="Enabled") -> FALSE | X132: =AND(HOUR(R132)<Business_Day_Start,HOUR(R132)>=0)+AND(HOUR(R132)>=Business_Day_End,HOUR(R132)<=23)>0 -> FALSE | Y132: =ABS(L132)>High_Value_GL_Threshold -> FALSE | Z132: =AND(ABS(L132)>=Round_Number_Threshold,MOD(ABS(L132),Round_Number_Threshold)=0) -> FALSE
A133: JE-00065 | B133: JE-00065-01 | C133: 45678 | D133: 45674 | E133: 2025 | F133: 1 | G133: 6400 | H133: Professional Fees | I133: Expense | J133: 31517.43 | K133: 0 | L133: =J133-K133 -> 31517.43 | M133: Supplier invoice posting | N133: INV-00065 | O133: AUTO_AP | P133: USR_AH | Q133: USR_FA | R133: 45678.896 | S133: Approved | T133: V006 | U133: INV-00065 | V133: =AND(C133>=Year_End_Window_Start,C133<=Year_End_Window_End) -> FALSE | W133: =AND(OR(WEEKDAY(C133,2)=5,WEEKDAY(C133,2)=6),'01_Parameters'!$C$11="Enabled") -> FALSE | X133: =AND(HOUR(R133)<Business_Day_Start,HOUR(R133)>=0)+AND(HOUR(R133)>=Business_Day_End,HOUR(R133)<=23)>0 -> TRUE | Y133: =ABS(L133)>High_Value_GL_Threshold -> FALSE | Z133: =AND(ABS(L133)>=Round_Number_Threshold,MOD(ABS(L133),Round_Number_Threshold)=0) -> FALSE
A134: JE-00065 | B134: JE-00065-02 | C134: 45678 | D134: 45674 | E134: 2025 | F134: 1 | G134: 2000 | H134: Trade Payables | I134: Liability | J134: 0 | K134: 31517.43 | L134: =J134-K134 -> -31517.43 | M134: Supplier invoice posting | N134: INV-00065 | O134: AUTO_AP | P134: USR_AH | Q134: USR_FA | R134: 45678.896 | S134: Approved | T134: V006 | U134: INV-00065 | V134: =AND(C134>=Year_End_Window_Start,C134<=Year_End_Window_End) -> FALSE | W134: =AND(OR(WEEKDAY(C134,2)=5,WEEKDAY(C134,2)=6),'01_Parameters'!$C$11="Enabled") -> FALSE | X134: =AND(HOUR(R134)<Business_Day_Start,HOUR(R134)>=0)+AND(HOUR(R134)>=Business_Day_End,HOUR(R134)<=23)>0 -> TRUE | Y134: =ABS(L134)>High_Value_GL_Threshold -> FALSE | Z134: =AND(ABS(L134)>=Round_Number_Threshold,MOD(ABS(L134),Round_Number_Threshold)=0) -> FALSE
A135: JE-00066 | B135: JE-00066-01 | C135: 45891 | D135: 45886 | E135: 2025 | F135: 8 | G135: 5000 | H135: Cost of Goods Sold | I135: Expense | J135: 34911.12 | K135: 0 | L135: =J135-K135 -> 34911.12 | M135: Inventory movement | N135: DOC-00066 | O135: AUTO_INVENTORY | P135: USR_FA | Q135: USR_NA | R135: 45891.271 | S135: Pending | V135: =AND(C135>=Year_End_Window_Start,C135<=Year_End_Window_End) -> FALSE | W135: =AND(OR(WEEKDAY(C135,2)=5,WEEKDAY(C135,2)=6),'01_Parameters'!$C$11="Enabled") -> TRUE | X135: =AND(HOUR(R135)<Business_Day_Start,HOUR(R135)>=0)+AND(HOUR(R135)>=Business_Day_End,HOUR(R135)<=23)>0 -> TRUE | Y135: =ABS(L135)>High_Value_GL_Threshold -> FALSE | Z135: =AND(ABS(L135)>=Round_Number_Threshold,MOD(ABS(L135),Round_Number_Threshold)=0) -> FALSE
A136: JE-00066 | B136: JE-00066-02 | C136: 45891 | D136: 45886 | E136: 2025 | F136: 8 | G136: 1200 | H136: Inventory | I136: Asset | J136: 0 | K136: 34911.12 | L136: =J136-K136 -> -34911.12 | M136: Inventory movement | N136: DOC-00066 | O136: AUTO_INVENTORY | P136: USR_FA | Q136: USR_NA | R136: 45891.271 | S136: Pending | V136: =AND(C136>=Year_End_Window_Start,C136<=Year_End_Window_End) -> FALSE | W136: =AND(OR(WEEKDAY(C136,2)=5,WEEKDAY(C136,2)=6),'01_Parameters'!$C$11="Enabled") -> TRUE | X136: =AND(HOUR(R136)<Business_Day_Start,HOUR(R136)>=0)+AND(HOUR(R136)>=Business_Day_End,HOUR(R136)<=23)>0 -> TRUE | Y136: =ABS(L136)>High_Value_GL_Threshold -> FALSE | Z136: =AND(ABS(L136)>=Round_Number_Threshold,MOD(ABS(L136),Round_Number_Threshold)=0) -> FALSE
A137: JE-00067 | B137: JE-00067-01 | C137: 45891 | D137: 45887 | E137: 2025 | F137: 8 | G137: 6300 | H137: Marketing Expense | I137: Expense | J137: 63290.74 | K137: 0 | L137: =J137-K137 -> 63290.74 | M137: Supplier invoice posting | N137: INV-00067 | O137: AUTO_AP | P137: USR_RE | Q137: USR_AH | R137: 45891.688 | S137: Pending | T137: V006 | U137: INV-00067 | V137: =AND(C137>=Year_End_Window_Start,C137<=Year_End_Window_End) -> FALSE | W137: =AND(OR(WEEKDAY(C137,2)=5,WEEKDAY(C137,2)=6),'01_Parameters'!$C$11="Enabled") -> TRUE | X137: =AND(HOUR(R137)<Business_Day_Start,HOUR(R137)>=0)+AND(HOUR(R137)>=Business_Day_End,HOUR(R137)<=23)>0 -> FALSE | Y137: =ABS(L137)>High_Value_GL_Threshold -> FALSE | Z137: =AND(ABS(L137)>=Round_Number_Threshold,MOD(ABS(L137),Round_Number_Threshold)=0) -> FALSE
A138: JE-00067 | B138: JE-00067-02 | C138: 45891 | D138: 45887 | E138: 2025 | F138: 8 | G138: 2000 | H138: Trade Payables | I138: Liability | J138: 0 | K138: 63290.74 | L138: =J138-K138 -> -63290.74 | M138: Supplier invoice posting | N138: INV-00067 | O138: AUTO_AP | P138: USR_RE | Q138: USR_AH | R138: 45891.688 | S138: Pending | T138: V006 | U138: INV-00067 | V138: =AND(C138>=Year_End_Window_Start,C138<=Year_End_Window_End) -> FALSE | W138: =AND(OR(WEEKDAY(C138,2)=5,WEEKDAY(C138,2)=6),'01_Parameters'!$C$11="Enabled") -> TRUE | X138: =AND(HOUR(R138)<Business_Day_Start,HOUR(R138)>=0)+AND(HOUR(R138)>=Business_Day_End,HOUR(R138)<=23)>0 -> FALSE | Y138: =ABS(L138)>High_Value_GL_Threshold -> FALSE | Z138: =AND(ABS(L138)>=Round_Number_Threshold,MOD(ABS(L138),Round_Number_Threshold)=0) -> FALSE
A139: JE-00068 | B139: JE-00068-01 | C139: 45915 | D139: 45914 | E139: 2025 | F139: 9 | G139: 6300 | H139: Marketing Expense | I139: Expense | J139: 112027.97 | K139: 0 | L139: =J139-K139 -> 112027.97 | M139: Manual period adjustment | N139: DOC-00068 | O139: MANUAL_JE | P139: USR_FA | Q139: USR_SA | R139: 45915.271 | S139: Approved | V139: =AND(C139>=Year_End_Window_Start,C139<=Year_End_Window_End) -> FALSE | W139: =AND(OR(WEEKDAY(C139,2)=5,WEEKDAY(C139,2)=6),'01_Parameters'!$C$11="Enabled") -> FALSE | X139: =AND(HOUR(R139)<Business_Day_Start,HOUR(R139)>=0)+AND(HOUR(R139)>=Business_Day_End,HOUR(R139)<=23)>0 -> TRUE | Y139: =ABS(L139)>High_Value_GL_Threshold -> TRUE | Z139: =AND(ABS(L139)>=Round_Number_Threshold,MOD(ABS(L139),Round_Number_Threshold)=0) -> FALSE
A140: JE-00068 | B140: JE-00068-02 | C140: 45915 | D140: 45914 | E140: 2025 | F140: 9 | G140: 2000 | H140: Trade Payables | I140: Liability | J140: 0 | K140: 112027.97 | L140: =J140-K140 -> -112027.97 | M140: Manual period adjustment | N140: DOC-00068 | O140: MANUAL_JE | P140: USR_FA | Q140: USR_SA | R140: 45915.271 | S140: Approved | V140: =AND(C140>=Year_End_Window_Start,C140<=Year_End_Window_End) -> FALSE | W140: =AND(OR(WEEKDAY(C140,2)=5,WEEKDAY(C140,2)=6),'01_Parameters'!$C$11="Enabled") -> FALSE | X140: =AND(HOUR(R140)<Business_Day_Start,HOUR(R140)>=0)+AND(HOUR(R140)>=Business_Day_End,HOUR(R140)<=23)>0 -> TRUE | Y140: =ABS(L140)>High_Value_GL_Threshold -> TRUE | Z140: =AND(ABS(L140)>=Round_Number_Threshold,MOD(ABS(L140),Round_Number_Threshold)=0) -> FALSE
A141: JE-00069 | B141: JE-00069-01 | C141: 45891 | D141: 45887 | E141: 2025 | F141: 8 | G141: 7000 | H141: Finance Costs | I141: Expense | J141: 59506.8 | K141: 0 | L141: =J141-K141 -> 59506.8 | M141: Manual period adjustment | N141: DOC-00069 | O141: MANUAL_JE | P141: USR_OM | Q141: USR_FA | R141: 45891.927 | S141: Approved | V141: =AND(C141>=Year_End_Window_Start,C141<=Year_End_Window_End) -> FALSE | W141: =AND(OR(WEEKDAY(C141,2)=5,WEEKDAY(C141,2)=6),'01_Parameters'!$C$11="Enabled") -> TRUE | X141: =AND(HOUR(R141)<Business_Day_Start,HOUR(R141)>=0)+AND(HOUR(R141)>=Business_Day_End,HOUR(R141)<=23)>0 -> TRUE | Y141: =ABS(L141)>High_Value_GL_Threshold -> FALSE | Z141: =AND(ABS(L141)>=Round_Number_Threshold,MOD(ABS(L141),Round_Number_Threshold)=0) -> FALSE
A142: JE-00069 | B142: JE-00069-02 | C142: 45891 | D142: 45887 | E142: 2025 | F142: 8 | G142: 2000 | H142: Trade Payables | I142: Liability | J142: 0 | K142: 59506.8 | L142: =J142-K142 -> -59506.8 | M142: Manual period adjustment | N142: DOC-00069 | O142: MANUAL_JE | P142: USR_OM | Q142: USR_FA | R142: 45891.927 | S142: Approved | V142: =AND(C142>=Year_End_Window_Start,C142<=Year_End_Window_End) -> FALSE | W142: =AND(OR(WEEKDAY(C142,2)=5,WEEKDAY(C142,2)=6),'01_Parameters'!$C$11="Enabled") -> TRUE | X142: =AND(HOUR(R142)<Business_Day_Start,HOUR(R142)>=0)+AND(HOUR(R142)>=Business_Day_End,HOUR(R142)<=23)>0 -> TRUE | Y142: =ABS(L142)>High_Value_GL_Threshold -> FALSE | Z142: =AND(ABS(L142)>=Round_Number_Threshold,MOD(ABS(L142),Round_Number_Threshold)=0) -> FALSE
A143: JE-00070 | B143: JE-00070-01 | C143: 45714 | D143: 45712 | E143: 2025 | F143: 2 | G143: 1100 | H143: Trade Receivables | I143: Asset | J143: 19313.52 | K143: 0 | L143: =J143-K143 -> 19313.52 | M143: Daily retail sales | N143: DOC-00070 | O143: AUTO_SALES | P143: USR_AH | Q143: USR_RE | R143: 45714.76 | S143: Approved | V143: =AND(C143>=Year_End_Window_Start,C143<=Year_End_Window_End) -> FALSE | W143: =AND(OR(WEEKDAY(C143,2)=5,WEEKDAY(C143,2)=6),'01_Parameters'!$C$11="Enabled") -> FALSE | X143: =AND(HOUR(R143)<Business_Day_Start,HOUR(R143)>=0)+AND(HOUR(R143)>=Business_Day_End,HOUR(R143)<=23)>0 -> TRUE | Y143: =ABS(L143)>High_Value_GL_Threshold -> FALSE | Z143: =AND(ABS(L143)>=Round_Number_Threshold,MOD(ABS(L143),Round_Number_Threshold)=0) -> FALSE
A144: JE-00070 | B144: JE-00070-02 | C144: 45714 | D144: 45712 | E144: 2025 | F144: 2 | G144: 4000 | H144: Sales Revenue | I144: Revenue | J144: 0 | K144: 19313.52 | L144: =J144-K144 -> -19313.52 | M144: Daily retail sales | N144: DOC-00070 | O144: AUTO_SALES | P144: USR_AH | Q144: USR_RE | R144: 45714.76 | S144: Approved | V144: =AND(C144>=Year_End_Window_Start,C144<=Year_End_Window_End) -> FALSE | W144: =AND(OR(WEEKDAY(C144,2)=5,WEEKDAY(C144,2)=6),'01_Parameters'!$C$11="Enabled") -> FALSE | X144: =AND(HOUR(R144)<Business_Day_Start,HOUR(R144)>=0)+AND(HOUR(R144)>=Business_Day_End,HOUR(R144)<=23)>0 -> TRUE | Y144: =ABS(L144)>High_Value_GL_Threshold -> FALSE | Z144: =AND(ABS(L144)>=Round_Number_Threshold,MOD(ABS(L144),Round_Number_Threshold)=0) -> FALSE
A145: JE-00071 | B145: JE-00071-01 | C145: 45894 | D145: 45890 | E145: 2025 | F145: 8 | G145: 6000 | H145: Salaries Expense | I145: Expense | J145: 61809.74 | K145: 0 | L145: =J145-K145 -> 61809.74 | M145: Monthly payroll accrual | N145: DOC-00071 | O145: AUTO_PAYROLL | P145: USR_NA | Q145: USR_SA | R145: 45894.74 | S145: Approved | V145: =AND(C145>=Year_End_Window_Start,C145<=Year_End_Window_End) -> FALSE | W145: =AND(OR(WEEKDAY(C145,2)=5,WEEKDAY(C145,2)=6),'01_Parameters'!$C$11="Enabled") -> FALSE | X145: =AND(HOUR(R145)<Business_Day_Start,HOUR(R145)>=0)+AND(HOUR(R145)>=Business_Day_End,HOUR(R145)<=23)>0 -> FALSE | Y145: =ABS(L145)>High_Value_GL_Threshold -> FALSE | Z145: =AND(ABS(L145)>=Round_Number_Threshold,MOD(ABS(L145),Round_Number_Threshold)=0) -> FALSE
A146: JE-00071 | B146: JE-00071-02 | C146: 45894 | D146: 45890 | E146: 2025 | F146: 8 | G146: 2100 | H146: Accrued Expenses | I146: Liability | J146: 0 | K146: 61809.74 | L146: =J146-K146 -> -61809.74 | M146: Monthly payroll accrual | N146: DOC-00071 | O146: AUTO_PAYROLL | P146: USR_NA | Q146: USR_SA | R146: 45894.74 | S146: Approved | V146: =AND(C146>=Year_End_Window_Start,C146<=Year_End_Window_End) -> FALSE | W146: =AND(OR(WEEKDAY(C146,2)=5,WEEKDAY(C146,2)=6),'01_Parameters'!$C$11="Enabled") -> FALSE | X146: =AND(HOUR(R146)<Business_Day_Start,HOUR(R146)>=0)+AND(HOUR(R146)>=Business_Day_End,HOUR(R146)<=23)>0 -> FALSE | Y146: =ABS(L146)>High_Value_GL_Threshold -> FALSE | Z146: =AND(ABS(L146)>=Round_Number_Threshold,MOD(ABS(L146),Round_Number_Threshold)=0) -> FALSE
A147: JE-00072 | B147: JE-00072-01 | C147: 45794 | D147: 45793 | E147: 2025 | F147: 5 | G147: 6100 | H147: Rent Expense | I147: Expense | J147: 65828.99 | K147: 0 | L147: =J147-K147 -> 65828.99 | M147: Manual period adjustment | N147: DOC-00072 | O147: MANUAL_JE | P147: USR_SA | Q147: USR_RE | R147: 45794.771 | S147: Approved | V147: =AND(C147>=Year_End_Window_Start,C147<=Year_End_Window_End) -> FALSE | W147: =AND(OR(WEEKDAY(C147,2)=5,WEEKDAY(C147,2)=6),'01_Parameters'!$C$11="Enabled") -> TRUE | X147: =AND(HOUR(R147)<Business_Day_Start,HOUR(R147)>=0)+AND(HOUR(R147)>=Business_Day_End,HOUR(R147)<=23)>0 -> TRUE | Y147: =ABS(L147)>High_Value_GL_Threshold -> FALSE | Z147: =AND(ABS(L147)>=Round_Number_Threshold,MOD(ABS(L147),Round_Number_Threshold)=0) -> FALSE
A148: JE-00072 | B148: JE-00072-02 | C148: 45794 | D148: 45793 | E148: 2025 | F148: 5 | G148: 2000 | H148: Trade Payables | I148: Liability | J148: 0 | K148: 65828.99 | L148: =J148-K148 -> -65828.99 | M148: Manual period adjustment | N148: DOC-00072 | O148: MANUAL_JE | P148: USR_SA | Q148: USR_RE | R148: 45794.771 | S148: Approved | V148: =AND(C148>=Year_End_Window_Start,C148<=Year_End_Window_End) -> FALSE | W148: =AND(OR(WEEKDAY(C148,2)=5,WEEKDAY(C148,2)=6),'01_Parameters'!$C$11="Enabled") -> TRUE | X148: =AND(HOUR(R148)<Business_Day_Start,HOUR(R148)>=0)+AND(HOUR(R148)>=Business_Day_End,HOUR(R148)<=23)>0 -> TRUE | Y148: =ABS(L148)>High_Value_GL_Threshold -> FALSE | Z148: =AND(ABS(L148)>=Round_Number_Threshold,MOD(ABS(L148),Round_Number_Threshold)=0) -> FALSE
...

Sheet 03_AP_Data
A1: 03_AP_Data — Synthetic Accounts Payable Population
A2: Approximately 300 fictional supplier invoices. Amount convention: Gross = Net + VAT (illustrative 15% VAT).
A4: Invoice_ID | B4: Vendor_ID | C4: Vendor_Name | D4: Vendor_Invoice_Number | E4: Invoice_Date | F4: Posting_Date | G4: Due_Date | H4: Gross_Amount | I4: VAT_Amount | J4: Net_Amount | K4: Purchase_Order_ID | L4: Goods_Receipt_ID | M4: Payment_Reference | N4: Payment_Date | O4: Payment_Status | P4: Invoice_Description | Q4: Entered_By | R4: Approved_By | S4: Approval_Status | T4: Supporting_Document_Status | U4: Days_Invoice_to_Posting | V4: Is_High_Value | W4: Is_Potential_Duplicate | X4: Is_Missing_PO | Y4: Is_Missing_Receipt | Z4: Is_Potential_Cutoff | AA4: Exception_Notes
A5: INV-00001 | B5: V009 | C5: Afaq Professional Services | D5: 009-2025-0001 | E5: 45700 | F5: 45715 | G5: 45745 | H5: 70828.4 | I5: 9238.49 | J5: 61589.91 | K5: PO-00001 | M5: PAY-00001 | N5: 45756 | O5: Paid | P5: Utility service | Q5: USR_FA | R5: USR_FA | S5: Approved | T5: Partial | U5: =F5-E5 -> 15 | V5: =H5>High_Value_AP_Threshold -> FALSE | W5: =COUNTIFS($B$5:$B$304,B5,$D$5:$D$304,D5)>1 -> FALSE | X5: =AND(K5="",P5<>"Utility service",P5<>"Campaign services") -> FALSE | Y5: =AND(L5="",OR(P5="Merchandise replenishment",P5="Office supplies",P5="Transport and logistics")) -> FALSE | Z5: =OR(F5>Year_End_Window_End,AND(E5>=Year_End_Window_Start,F5>=Year_End_Window_Start)) -> FALSE
A6: INV-00002 | B6: V002 | C6: Red Sand Facilities LLC | D6: 002-2025-0002 | E6: 45680 | F6: 45681 | G6: 45711 | H6: 57567.48 | I6: 7508.8 | J6: 50058.68 | K6: PO-00002 | M6: PAY-00002 | N6: 45725 | O6: Paid | P6: Campaign services | Q6: USR_AH | R6: USR_SA | S6: Approved | T6: Partial | U6: =F6-E6 -> 1 | V6: =H6>High_Value_AP_Threshold -> FALSE | W6: =COUNTIFS($B$5:$B$304,B6,$D$5:$D$304,D6)>1 -> FALSE | X6: =AND(K6="",P6<>"Utility service",P6<>"Campaign services") -> FALSE | Y6: =AND(L6="",OR(P6="Merchandise replenishment",P6="Office supplies",P6="Transport and logistics")) -> FALSE | Z6: =OR(F6>Year_End_Window_End,AND(E6>=Year_End_Window_Start,F6>=Year_End_Window_Start)) -> FALSE
A7: INV-00003 | B7: V004 | C7: Wadi Marketing Studio | D7: 004-2025-0003 | E7: 45754 | F7: 45754 | G7: 45784 | H7: 53208.61 | I7: 6940.25 | J7: 46268.36 | K7: PO-00003 | L7: GR-00003 | M7: PAY-00003 | N7: 45788 | O7: Paid | P7: Transport and logistics | Q7: USR_NA | R7: USR_SA | S7: Approved | T7: Complete | U7: =F7-E7 -> 0 | V7: =H7>High_Value_AP_Threshold -> FALSE | W7: =COUNTIFS($B$5:$B$304,B7,$D$5:$D$304,D7)>1 -> FALSE | X7: =AND(K7="",P7<>"Utility service",P7<>"Campaign services") -> FALSE | Y7: =AND(L7="",OR(P7="Merchandise replenishment",P7="Office supplies",P7="Transport and logistics")) -> FALSE | Z7: =OR(F7>Year_End_Window_End,AND(E7>=Year_End_Window_Start,F7>=Year_End_Window_Start)) -> FALSE
A8: INV-00004 | B8: V010 | C8: Thuraya Packaging | D8: 010-2025-0004 | E8: 45714 | F8: 45744 | G8: 45774 | H8: 15545.94 | I8: 2027.73 | J8: 13518.21 | K8: PO-00004 | L8: GR-00004 | M8: PAY-00004 | N8: 45756 | O8: Paid | P8: Merchandise replenishment | Q8: USR_FA | R8: USR_SA | S8: Approved | T8: Complete | U8: =F8-E8 -> 30 | V8: =H8>High_Value_AP_Threshold -> FALSE | W8: =COUNTIFS($B$5:$B$304,B8,$D$5:$D$304,D8)>1 -> FALSE | X8: =AND(K8="",P8<>"Utility service",P8<>"Campaign services") -> FALSE | Y8: =AND(L8="",OR(P8="Merchandise replenishment",P8="Office supplies",P8="Transport and logistics")) -> FALSE | Z8: =OR(F8>Year_End_Window_End,AND(E8>=Year_End_Window_Start,F8>=Year_End_Window_Start)) -> FALSE
A9: INV-00005 | B9: V002 | C9: Red Sand Facilities LLC | D9: 002-2025-0005 | E9: 45958 | F9: 45973 | G9: 46003 | H9: 57408.59 | I9: 7488.08 | J9: 49920.51 | K9: PO-00005 | M9: PAY-00005 | N9: 45998 | O9: Paid | P9: Campaign services | Q9: USR_RE | R9: USR_RE | S9: Approved | T9: Partial | U9: =F9-E9 -> 15 | V9: =H9>High_Value_AP_Threshold -> FALSE | W9: =COUNTIFS($B$5:$B$304,B9,$D$5:$D$304,D9)>1 -> FALSE | X9: =AND(K9="",P9<>"Utility service",P9<>"Campaign services") -> FALSE | Y9: =AND(L9="",OR(P9="Merchandise replenishment",P9="Office supplies",P9="Transport and logistics")) -> FALSE | Z9: =OR(F9>Year_End_Window_End,AND(E9>=Year_End_Window_Start,F9>=Year_End_Window_Start)) -> FALSE
A10: INV-00006 | B10: V008 | C10: Desert Star Maintenance | D10: 008-2025-0006 | E10: 45862 | F10: 45863 | G10: 45893 | H10: 56810.71 | I10: 7410.09 | J10: 49400.62 | K10: PO-00006 | M10: PAY-00006 | N10: 45889 | O10: Paid | P10: Utility service | Q10: USR_RE | R10: USR_NA | S10: Approved | T10: Partial | U10: =F10-E10 -> 1 | V10: =H10>High_Value_AP_Threshold -> FALSE | W10: =COUNTIFS($B$5:$B$304,B10,$D$5:$D$304,D10)>1 -> FALSE | X10: =AND(K10="",P10<>"Utility service",P10<>"Campaign services") -> FALSE | Y10: =AND(L10="",OR(P10="Merchandise replenishment",P10="Office supplies",P10="Transport and logistics")) -> FALSE | Z10: =OR(F10>Year_End_Window_End,AND(E10>=Year_End_Window_Start,F10>=Year_End_Window_Start)) -> FALSE
A11: INV-00007 | B11: V009 | C11: Afaq Professional Services | D11: 009-2025-0007 | E11: 45929 | F11: 45934 | G11: 45964 | H11: 12800.93 | I11: 1669.69 | J11: 11131.24 | K11: PO-00007 | O11: Pending | P11: Cloud support services | Q11: USR_NA | R11: USR_OM | S11: Approved | T11: Partial | U11: =F11-E11 -> 5 | V11: =H11>High_Value_AP_Threshold -> FALSE | W11: =COUNTIFS($B$5:$B$304,B11,$D$5:$D$304,D11)>1 -> FALSE | X11: =AND(K11="",P11<>"Utility service",P11<>"Campaign services") -> FALSE | Y11: =AND(L11="",OR(P11="Merchandise replenishment",P11="Office supplies",P11="Transport and logistics")) -> FALSE | Z11: =OR(F11>Year_End_Window_End,AND(E11>=Year_End_Window_Start,F11>=Year_End_Window_Start)) -> FALSE
A12: INV-00008 | B12: V003 | C12: Sahab IT Services | D12: 003-2025-0008 | E12: 45999 | F12: 46004 | G12: 46034 | H12: 41203.64 | I12: 5374.39 | J12: 35829.25 | K12: PO-00008 | M12: PAY-00008 | N12: 46009 | O12: Paid | P12: Utility service | Q12: USR_NA | R12: USR_SA | S12: Approved | T12: Partial | U12: =F12-E12 -> 5 | V12: =H12>High_Value_AP_Threshold -> FALSE | W12: =COUNTIFS($B$5:$B$304,B12,$D$5:$D$304,D12)>1 -> FALSE | X12: =AND(K12="",P12<>"Utility service",P12<>"Campaign services") -> FALSE | Y12: =AND(L12="",OR(P12="Merchandise replenishment",P12="Office supplies",P12="Transport and logistics")) -> FALSE | Z12: =OR(F12>Year_End_Window_End,AND(E12>=Year_End_Window_Start,F12>=Year_End_Window_Start)) -> FALSE
A13: INV-00009 | B13: V010 | C13: Thuraya Packaging | D13: 010-2025-0009 | E13: 45934 | F13: 45964 | G13: 45994 | H13: 43093.15 | I13: 5620.85 | J13: 37472.3 | O13: Pending | P13: Utility service | Q13: USR_RE | R13: USR_NA | S13: Approved | T13: Missing | U13: =F13-E13 -> 30 | V13: =H13>High_Value_AP_Threshold -> FALSE | W13: =COUNTIFS($B$5:$B$304,B13,$D$5:$D$304,D13)>1 -> FALSE | X13: =AND(K13="",P13<>"Utility service",P13<>"Campaign services") -> FALSE | Y13: =AND(L13="",OR(P13="Merchandise replenishment",P13="Office supplies",P13="Transport and logistics")) -> FALSE | Z13: =OR(F13>Year_End_Window_End,AND(E13>=Year_End_Window_Start,F13>=Year_End_Window_Start)) -> FALSE
A14: INV-00010 | B14: V001 | C14: Najd Merchandising Co. | D14: 001-2025-0010 | E14: 45916 | F14: 45926 | G14: 45956 | H14: 51669.22 | I14: 6739.46 | J14: 44929.76 | K14: PO-00010 | M14: PAY-00010 | N14: 45944 | O14: Paid | P14: Store maintenance | Q14: USR_FA | R14: USR_NA | S14: Approved | T14: Partial | U14: =F14-E14 -> 10 | V14: =H14>High_Value_AP_Threshold -> FALSE | W14: =COUNTIFS($B$5:$B$304,B14,$D$5:$D$304,D14)>1 -> FALSE | X14: =AND(K14="",P14<>"Utility service",P14<>"Campaign services") -> FALSE | Y14: =AND(L14="",OR(P14="Merchandise replenishment",P14="Office supplies",P14="Transport and logistics")) -> FALSE | Z14: =OR(F14>Year_End_Window_End,AND(E14>=Year_End_Window_Start,F14>=Year_End_Window_Start)) -> FALSE
A15: INV-00011 | B15: V010 | C15: Thuraya Packaging | D15: 010-2025-0011 | E15: 45735 | F15: 45740 | G15: 45770 | H15: 38578.42 | I15: 5031.97 | J15: 33546.45 | K15: PO-00011 | L15: GR-00011 | M15: PAY-00011 | N15: 45754 | O15: Paid | P15: Merchandise replenishment | Q15: USR_FA | R15: USR_NA | S15: Approved | T15: Complete | U15: =F15-E15 -> 5 | V15: =H15>High_Value_AP_Threshold -> FALSE | W15: =COUNTIFS($B$5:$B$304,B15,$D$5:$D$304,D15)>1 -> FALSE | X15: =AND(K15="",P15<>"Utility service",P15<>"Campaign services") -> FALSE | Y15: =AND(L15="",OR(P15="Merchandise replenishment",P15="Office supplies",P15="Transport and logistics")) -> FALSE | Z15: =OR(F15>Year_End_Window_End,AND(E15>=Year_End_Window_Start,F15>=Year_End_Window_Start)) -> FALSE
A16: INV-00012 | B16: V005 | C16: Rimal Utilities Provider | D16: 005-2025-0012 | E16: 46007 | F16: 46009 | G16: 46039 | H16: 54819.71 | I16: 7150.4 | J16: 47669.31 | K16: PO-00012 | O16: Pending | P16: Cloud support services | Q16: USR_FA | R16: USR_RE | S16: Approved | T16: Partial | U16: =F16-E16 -> 2 | V16: =H16>High_Value_AP_Threshold -> FALSE | W16: =COUNTIFS($B$5:$B$304,B16,$D$5:$D$304,D16)>1 -> FALSE | X16: =AND(K16="",P16<>"Utility service",P16<>"Campaign services") -> FALSE | Y16: =AND(L16="",OR(P16="Merchandise replenishment",P16="Office supplies",P16="Transport and logistics")) -> FALSE | Z16: =OR(F16>Year_End_Window_End,AND(E16>=Year_End_Window_Start,F16>=Year_End_Window_Start)) -> TRUE
A17: INV-00013 | B17: V004 | C17: Wadi Marketing Studio | D17: 004-2025-0013 | E17: 45967 | F17: 45982 | G17: 46012 | H17: 59402.32 | I17: 7748.13 | J17: 51654.19 | K17: PO-00013 | L17: GR-00013 | M17: PAY-00013 | N17: 46002 | O17: Paid | P17: Merchandise replenishment | Q17: USR_SA | R17: USR_RE | S17: Approved | T17: Complete | U17: =F17-E17 -> 15 | V17: =H17>High_Value_AP_Threshold -> FALSE | W17: =COUNTIFS($B$5:$B$304,B17,$D$5:$D$304,D17)>1 -> TRUE | X17: =AND(K17="",P17<>"Utility service",P17<>"Campaign services") -> FALSE | Y17: =AND(L17="",OR(P17="Merchandise replenishment",P17="Office supplies",P17="Transport and logistics")) -> FALSE | Z17: =OR(F17>Year_End_Window_End,AND(E17>=Year_End_Window_Start,F17>=Year_End_Window_Start)) -> FALSE
A18: INV-00014 | B18: V010 | C18: Thuraya Packaging | D18: 010-2025-0014 | E18: 45943 | F18: 45946 | G18: 45976 | H18: 1655.11 | I18: 215.88 | J18: 1439.23 | K18: PO-00014 | L18: GR-00014 | O18: Pending | P18: Transport and logistics | Q18: USR_NA | R18: USR_SA | S18: Approved | T18: Complete | U18: =F18-E18 -> 3 | V18: =H18>High_Value_AP_Threshold -> FALSE | W18: =COUNTIFS($B$5:$B$304,B18,$D$5:$D$304,D18)>1 -> FALSE | X18: =AND(K18="",P18<>"Utility service",P18<>"Campaign services") -> FALSE | Y18: =AND(L18="",OR(P18="Merchandise replenishment",P18="Office supplies",P18="Transport and logistics")) -> FALSE | Z18: =OR(F18>Year_End_Window_End,AND(E18>=Year_End_Window_Start,F18>=Year_End_Window_Start)) -> FALSE
A19: INV-00015 | B19: V005 | C19: Rimal Utilities Provider | D19: 005-2025-0015 | E19: 45692 | F19: 45694 | G19: 45724 | H19: 23627.53 | I19: 3081.85 | J19: 20545.68 | K19: PO-00015 | M19: PAY-00015 | N19: 45738 | O19: Paid | P19: Utility service | Q19: USR_RE | R19: USR_RE | S19: Approved | T19: Partial | U19: =F19-E19 -> 2 | V19: =H19>High_Value_AP_Threshold -> FALSE | W19: =COUNTIFS($B$5:$B$304,B19,$D$5:$D$304,D19)>1 -> FALSE | X19: =AND(K19="",P19<>"Utility service",P19<>"Campaign services") -> FALSE | Y19: =AND(L19="",OR(P19="Merchandise replenishment",P19="Office supplies",P19="Transport and logistics")) -> FALSE | Z19: =OR(F19>Year_End_Window_End,AND(E19>=Year_End_Window_Start,F19>=Year_End_Window_Start)) -> FALSE
A20: INV-00016 | B20: V002 | C20: Red Sand Facilities LLC | D20: 002-2025-0016 | E20: 45979 | F20: 45982 | G20: 46012 | H20: 72049.13 | I20: 9397.71 | J20: 62651.42 | K20: PO-00016 | M20: PAY-00016 | N20: 46008 | O20: Paid | P20: Utility service | Q20: USR_FA | R20: USR_NA | S20: Approved | T20: Partial | U20: =F20-E20 -> 3 | V20: =H20>High_Value_AP_Threshold -> FALSE | W20: =COUNTIFS($B$5:$B$304,B20,$D$5:$D$304,D20)>1 -> FALSE | X20: =AND(K20="",P20<>"Utility service",P20<>"Campaign services") -> FALSE | Y20: =AND(L20="",OR(P20="Merchandise replenishment",P20="Office supplies",P20="Transport and logistics")) -> FALSE | Z20: =OR(F20>Year_End_Window_End,AND(E20>=Year_End_Window_Start,F20>=Year_End_Window_Start)) -> FALSE
A21: INV-00017 | B21: V003 | C21: Sahab IT Services | D21: 003-2025-0017 | E21: 46015 | F21: 46022 | G21: 46052 | H21: 47176.61 | I21: 6153.47 | J21: 41023.14 | K21: PO-00017 | L21: GR-00017 | O21: Pending | P21: Merchandise replenishment | Q21: USR_RE | R21: USR_FA | S21: Approved | T21: Complete | U21: =F21-E21 -> 7 | V21: =H21>High_Value_AP_Threshold -> FALSE | W21: =COUNTIFS($B$5:$B$304,B21,$D$5:$D$304,D21)>1 -> FALSE | X21: =AND(K21="",P21<>"Utility service",P21<>"Campaign services") -> FALSE | Y21: =AND(L21="",OR(P21="Merchandise replenishment",P21="Office supplies",P21="Transport and logistics")) -> FALSE | Z21: =OR(F21>Year_End_Window_End,AND(E21>=Year_End_Window_Start,F21>=Year_End_Window_Start)) -> TRUE
A22: INV-00018 | B22: V001 | C22: Najd Merchandising Co. | D22: 001-2025-0018 | E22: 45957 | F22: 45958 | G22: 45988 | H22: 60673.25 | I22: 7913.9 | J22: 52759.35 | K22: PO-00018 | O22: Pending | P22: Utility service | Q22: USR_NA | R22: USR_NA | S22: Approved | T22: Partial | U22: =F22-E22 -> 1 | V22: =H22>High_Value_AP_Threshold -> FALSE | W22: =COUNTIFS($B$5:$B$304,B22,$D$5:$D$304,D22)>1 -> FALSE | X22: =AND(K22="",P22<>"Utility service",P22<>"Campaign services") -> FALSE | Y22: =AND(L22="",OR(P22="Merchandise replenishment",P22="Office supplies",P22="Transport and logistics")) -> FALSE | Z22: =OR(F22>Year_End_Window_End,AND(E22>=Year_End_Window_Start,F22>=Year_End_Window_Start)) -> FALSE
A23: INV-00019 | B23: V010 | C23: Thuraya Packaging | D23: 010-2025-0019 | E23: 45795 | F23: 45798 | G23: 45828 | H23: 48155.48 | I23: 6281.15 | J23: 41874.33 | K23: PO-00019 | L23: GR-00019 | M23: PAY-00019 | N23: 45821 | O23: Paid | P23: Office supplies | Q23: USR_RE | R23: USR_OM | S23: Approved | T23: Complete | U23: =F23-E23 -> 3 | V23: =H23>High_Value_AP_Threshold -> FALSE | W23: =COUNTIFS($B$5:$B$304,B23,$D$5:$D$304,D23)>1 -> FALSE | X23: =AND(K23="",P23<>"Utility service",P23<>"Campaign services") -> FALSE | Y23: =AND(L23="",OR(P23="Merchandise replenishment",P23="Office supplies",P23="Transport and logistics")) -> FALSE | Z23: =OR(F23>Year_End_Window_End,AND(E23>=Year_End_Window_Start,F23>=Year_End_Window_Start)) -> FALSE
A24: INV-00020 | B24: V004 | C24: Wadi Marketing Studio | D24: 004-2025-0020 | E24: 45799 | F24: 45814 | G24: 45844 | H24: 47072.93 | I24: 6139.95 | J24: 40932.98 | K24: PO-00020 | L24: GR-00020 | M24: PAY-00020 | N24: 45841 | O24: Paid | P24: Office supplies | Q24: USR_AH | R24: USR_SA | S24: Approved | T24: Complete | U24: =F24-E24 -> 15 | V24: =H24>High_Value_AP_Threshold -> FALSE | W24: =COUNTIFS($B$5:$B$304,B24,$D$5:$D$304,D24)>1 -> FALSE | X24: =AND(K24="",P24<>"Utility service",P24<>"Campaign services") -> FALSE | Y24: =AND(L24="",OR(P24="Merchandise replenishment",P24="Office supplies",P24="Transport and logistics")) -> FALSE | Z24: =OR(F24>Year_End_Window_End,AND(E24>=Year_End_Window_Start,F24>=Year_End_Window_Start)) -> FALSE
A25: INV-00021 | B25: V010 | C25: Thuraya Packaging | D25: 010-2025-0021 | E25: 45896 | F25: 45926 | G25: 45956 | H25: 11940.06 | I25: 1557.4 | J25: 10382.66 | K25: PO-00021 | L25: GR-00021 | M25: PAY-00021 | N25: 45956 | O25: Paid | P25: Office supplies | Q25: USR_NA | R25: USR_RE | S25: Pending | T25: Complete | U25: =F25-E25 -> 30 | V25: =H25>High_Value_AP_Threshold -> FALSE | W25: =COUNTIFS($B$5:$B$304,B25,$D$5:$D$304,D25)>1 -> FALSE | X25: =AND(K25="",P25<>"Utility service",P25<>"Campaign services") -> FALSE | Y25: =AND(L25="",OR(P25="Merchandise replenishment",P25="Office supplies",P25="Transport and logistics")) -> FALSE | Z25: =OR(F25>Year_End_Window_End,AND(E25>=Year_End_Window_Start,F25>=Year_End_Window_Start)) -> FALSE
A26: INV-00022 | B26: V002 | C26: Red Sand Facilities LLC | D26: 002-2025-0022 | E26: 45805 | F26: 45806 | G26: 45836 | H26: 60806.54 | I26: 7931.29 | J26: 52875.25 | K26: PO-00022 | O26: Pending | P26: Utility service | Q26: USR_AH | R26: USR_OM | S26: Approved | T26: Partial | U26: =F26-E26 -> 1 | V26: =H26>High_Value_AP_Threshold -> FALSE | W26: =COUNTIFS($B$5:$B$304,B26,$D$5:$D$304,D26)>1 -> FALSE | X26: =AND(K26="",P26<>"Utility service",P26<>"Campaign services") -> FALSE | Y26: =AND(L26="",OR(P26="Merchandise replenishment",P26="Office supplies",P26="Transport and logistics")) -> FALSE | Z26: =OR(F26>Year_End_Window_End,AND(E26>=Year_End_Window_Start,F26>=Year_End_Window_Start)) -> FALSE
A27: INV-00023 | B27: V006 | C27: Palm Office Supplies | D27: 006-2025-0023 | E27: 45923 | F27: 45923 | G27: 45953 | H27: 61534.08 | I27: 8026.18 | J27: 53507.9 | K27: PO-00023 | M27: PAY-00023 | N27: 45947 | O27: Paid | P27: Store maintenance | Q27: USR_AH | R27: USR_OM | S27: Approved | T27: Partial | U27: =F27-E27 -> 0 | V27: =H27>High_Value_AP_Threshold -> FALSE | W27: =COUNTIFS($B$5:$B$304,B27,$D$5:$D$304,D27)>1 -> FALSE | X27: =AND(K27="",P27<>"Utility service",P27<>"Campaign services") -> FALSE | Y27: =AND(L27="",OR(P27="Merchandise replenishment",P27="Office supplies",P27="Transport and logistics")) -> FALSE | Z27: =OR(F27>Year_End_Window_End,AND(E27>=Year_End_Window_Start,F27>=Year_End_Window_Start)) -> FALSE
A28: INV-00024 | B28: V002 | C28: Red Sand Facilities LLC | D28: 002-2025-0024 | E28: 46003 | F28: 46018 | G28: 46048 | H28: 1005.5 | I28: 131.15 | J28: 874.35 | K28: PO-00024 | O28: Pending | P28: Utility service | Q28: USR_SA | R28: USR_OM | S28: Pending | T28: Partial | U28: =F28-E28 -> 15 | V28: =H28>High_Value_AP_Threshold -> FALSE | W28: =COUNTIFS($B$5:$B$304,B28,$D$5:$D$304,D28)>1 -> FALSE | X28: =AND(K28="",P28<>"Utility service",P28<>"Campaign services") -> FALSE | Y28: =AND(L28="",OR(P28="Merchandise replenishment",P28="Office supplies",P28="Transport and logistics")) -> FALSE | Z28: =OR(F28>Year_End_Window_End,AND(E28>=Year_End_Window_Start,F28>=Year_End_Window_Start)) -> FALSE
A29: INV-00025 | B29: V001 | C29: Najd Merchandising Co. | D29: 001-2025-0025 | E29: 45813 | F29: 45818 | G29: 45848 | H29: 49387.47 | I29: 6441.84 | J29: 42945.63 | K29: PO-00025 | L29: GR-00025 | O29: Pending | P29: Merchandise replenishment | Q29: USR_RE | R29: USR_OM | S29: Approved | T29: Complete | U29: =F29-E29 -> 5 | V29: =H29>High_Value_AP_Threshold -> FALSE | W29: =COUNTIFS($B$5:$B$304,B29,$D$5:$D$304,D29)>1 -> FALSE | X29: =AND(K29="",P29<>"Utility service",P29<>"Campaign services") -> FALSE | Y29: =AND(L29="",OR(P29="Merchandise replenishment",P29="Office supplies",P29="Transport and logistics")) -> FALSE | Z29: =OR(F29>Year_End_Window_End,AND(E29>=Year_End_Window_Start,F29>=Year_End_Window_Start)) -> FALSE
A30: INV-00026 | B30: V003 | C30: Sahab IT Services | D30: 003-2025-0026 | E30: 45727 | F30: 45729 | G30: 45759 | H30: 46141.32 | I30: 6018.43 | J30: 40122.89 | K30: PO-00026 | O30: Pending | P30: Store maintenance | Q30: USR_AH | R30: USR_RE | S30: Approved | T30: Partial | U30: =F30-E30 -> 2 | V30: =H30>High_Value_AP_Threshold -> FALSE | W30: =COUNTIFS($B$5:$B$304,B30,$D$5:$D$304,D30)>1 -> FALSE | X30: =AND(K30="",P30<>"Utility service",P30<>"Campaign services") -> FALSE | Y30: =AND(L30="",OR(P30="Merchandise replenishment",P30="Office supplies",P30="Transport and logistics")) -> FALSE | Z30: =OR(F30>Year_End_Window_End,AND(E30>=Year_End_Window_Start,F30>=Year_End_Window_Start)) -> FALSE
A31: INV-00027 | B31: V008 | C31: Desert Star Maintenance | D31: 008-2025-0027 | E31: 45752 | F31: 45755 | G31: 45785 | H31: 18408.71 | I31: 2401.14 | J31: 16007.57 | K31: PO-00027 | L31: GR-00027 | M31: PAY-00027 | N31: 45777 | O31: Paid | P31: Transport and logistics | Q31: USR_FA | R31: USR_FA | S31: Approved | T31: Complete | U31: =F31-E31 -> 3 | V31: =H31>High_Value_AP_Threshold -> FALSE | W31: =COUNTIFS($B$5:$B$304,B31,$D$5:$D$304,D31)>1 -> FALSE | X31: =AND(K31="",P31<>"Utility service",P31<>"Campaign services") -> FALSE | Y31: =AND(L31="",OR(P31="Merchandise replenishment",P31="Office supplies",P31="Transport and logistics")) -> FALSE | Z31: =OR(F31>Year_End_Window_End,AND(E31>=Year_End_Window_Start,F31>=Year_End_Window_Start)) -> FALSE
A32: INV-00028 | B32: V005 | C32: Rimal Utilities Provider | D32: 005-2025-0028 | E32: 45780 | F32: 45780 | G32: 45810 | H32: 31846.87 | I32: 4153.94 | J32: 27692.93 | K32: PO-00028 | M32: PAY-00028 | N32: 45825 | O32: Paid | P32: Utility service | Q32: USR_SA | R32: USR_NA | S32: Approved | T32: Partial | U32: =F32-E32 -> 0 | V32: =H32>High_Value_AP_Threshold -> FALSE | W32: =COUNTIFS($B$5:$B$304,B32,$D$5:$D$304,D32)>1 -> FALSE | X32: =AND(K32="",P32<>"Utility service",P32<>"Campaign services") -> FALSE | Y32: =AND(L32="",OR(P32="Merchandise replenishment",P32="Office supplies",P32="Transport and logistics")) -> FALSE | Z32: =OR(F32>Year_End_Window_End,AND(E32>=Year_End_Window_Start,F32>=Year_End_Window_Start)) -> FALSE
A33: INV-00029 | B33: V009 | C33: Afaq Professional Services | D33: 009-2025-0029 | E33: 45720 | F33: 45727 | G33: 45757 | H33: 65281.66 | I33: 8515 | J33: 56766.66 | K33: PO-00029 | M33: PAY-00029 | N33: 45732 | O33: Paid | P33: Cloud support services | Q33: USR_AH | R33: USR_OM | S33: Approved | T33: Partial | U33: =F33-E33 -> 7 | V33: =H33>High_Value_AP_Threshold -> FALSE | W33: =COUNTIFS($B$5:$B$304,B33,$D$5:$D$304,D33)>1 -> FALSE | X33: =AND(K33="",P33<>"Utility service",P33<>"Campaign services") -> FALSE | Y33: =AND(L33="",OR(P33="Merchandise replenishment",P33="Office supplies",P33="Transport and logistics")) -> FALSE | Z33: =OR(F33>Year_End_Window_End,AND(E33>=Year_End_Window_Start,F33>=Year_End_Window_Start)) -> FALSE
A34: INV-00030 | B34: V004 | C34: Wadi Marketing Studio | D34: 004-2025-0030 | E34: 45838 | F34: 45840 | G34: 45870 | H34: 20681.74 | I34: 2697.62 | J34: 17984.12 | K34: PO-00030 | L34: GR-00030 | M34: PAY-00030 | N34: 45853 | O34: Paid | P34: Transport and logistics | Q34: USR_AH | R34: USR_NA | S34: Approved | T34: Complete | U34: =F34-E34 -> 2 | V34: =H34>High_Value_AP_Threshold -> FALSE | W34: =COUNTIFS($B$5:$B$304,B34,$D$5:$D$304,D34)>1 -> FALSE | X34: =AND(K34="",P34<>"Utility service",P34<>"Campaign services") -> FALSE | Y34: =AND(L34="",OR(P34="Merchandise replenishment",P34="Office supplies",P34="Transport and logistics")) -> FALSE | Z34: =OR(F34>Year_End_Window_End,AND(E34>=Year_End_Window_Start,F34>=Year_End_Window_Start)) -> FALSE
A35: INV-00031 | B35: V003 | C35: Sahab IT Services | D35: 003-2025-0031 | E35: 45767 | F35: 45769 | G35: 45799 | H35: 36719.14 | I35: 4789.45 | J35: 31929.69 | K35: PO-00031 | M35: PAY-00031 | N35: 45780 | O35: Paid | P35: Utility service | Q35: USR_RE | R35: USR_FA | S35: Approved | T35: Partial | U35: =F35-E35 -> 2 | V35: =H35>High_Value_AP_Threshold -> FALSE | W35: =COUNTIFS($B$5:$B$304,B35,$D$5:$D$304,D35)>1 -> FALSE | X35: =AND(K35="",P35<>"Utility service",P35<>"Campaign services") -> FALSE | Y35: =AND(L35="",OR(P35="Merchandise replenishment",P35="Office supplies",P35="Transport and logistics")) -> FALSE | Z35: =OR(F35>Year_End_Window_End,AND(E35>=Year_End_Window_Start,F35>=Year_End_Window_Start)) -> FALSE
A36: INV-00032 | B36: V009 | C36: Afaq Professional Services | D36: 009-2025-0032 | E36: 45736 | F36: 45737 | G36: 45767 | H36: 5662.91 | I36: 738.64 | J36: 4924.27 | K36: PO-00032 | M36: PAY-00032 | N36: 45782 | O36: Paid | P36: Cloud support services | Q36: USR_NA | R36: USR_NA | S36: Approved | T36: Partial | U36: =F36-E36 -> 1 | V36: =H36>High_Value_AP_Threshold -> FALSE | W36: =COUNTIFS($B$5:$B$304,B36,$D$5:$D$304,D36)>1 -> FALSE | X36: =AND(K36="",P36<>"Utility service",P36<>"Campaign services") -> FALSE | Y36: =AND(L36="",OR(P36="Merchandise replenishment",P36="Office supplies",P36="Transport and logistics")) -> FALSE | Z36: =OR(F36>Year_End_Window_End,AND(E36>=Year_End_Window_Start,F36>=Year_End_Window_Start)) -> FALSE
A37: INV-00033 | B37: V007 | C37: Oasis Logistics | D37: 007-2025-0033 | E37: 45912 | F37: 45915 | G37: 45945 | H37: 13251.66 | I37: 1728.48 | J37: 11523.18 | K37: PO-00033 | L37: GR-00033 | M37: PAY-00033 | N37: 45939 | O37: Paid | P37: Transport and logistics | Q37: USR_RE | R37: USR_NA | S37: Approved | T37: Complete | U37: =F37-E37 -> 3 | V37: =H37>High_Value_AP_Threshold -> FALSE | W37: =COUNTIFS($B$5:$B$304,B37,$D$5:$D$304,D37)>1 -> FALSE | X37: =AND(K37="",P37<>"Utility service",P37<>"Campaign services") -> FALSE | Y37: =AND(L37="",OR(P37="Merchandise replenishment",P37="Office supplies",P37="Transport and logistics")) -> FALSE | Z37: =OR(F37>Year_End_Window_End,AND(E37>=Year_End_Window_Start,F37>=Year_End_Window_Start)) -> FALSE
A38: INV-00034 | B38: V003 | C38: Sahab IT Services | D38: 003-2025-0034 | E38: 45948 | F38: 45963 | G38: 45993 | H38: 71587.32 | I38: 9337.48 | J38: 62249.84 | K38: PO-00034 | M38: PAY-00034 | N38: 45976 | O38: Paid | P38: Campaign services | Q38: USR_AH | R38: USR_NA | S38: Approved | T38: Partial | U38: =F38-E38 -> 15 | V38: =H38>High_Value_AP_Threshold -> FALSE | W38: =COUNTIFS($B$5:$B$304,B38,$D$5:$D$304,D38)>1 -> FALSE | X38: =AND(K38="",P38<>"Utility service",P38<>"Campaign services") -> FALSE | Y38: =AND(L38="",OR(P38="Merchandise replenishment",P38="Office supplies",P38="Transport and logistics")) -> FALSE | Z38: =OR(F38>Year_End_Window_End,AND(E38>=Year_End_Window_Start,F38>=Year_End_Window_Start)) -> FALSE
A39: INV-00035 | B39: V001 | C39: Najd Merchandising Co. | D39: 001-2025-0035 | E39: 45830 | F39: 45835 | G39: 45865 | H39: 67597 | I39: 8817 | J39: 58780 | K39: PO-00035 | M39: PAY-00035 | N39: 45870 | O39: Paid | P39: Store maintenance | Q39: USR_RE | R39: USR_RE | S39: Approved | T39: Partial | U39: =F39-E39 -> 5 | V39: =H39>High_Value_AP_Threshold -> FALSE | W39: =COUNTIFS($B$5:$B$304,B39,$D$5:$D$304,D39)>1 -> FALSE | X39: =AND(K39="",P39<>"Utility service",P39<>"Campaign services") -> FALSE | Y39: =AND(L39="",OR(P39="Merchandise replenishment",P39="Office supplies",P39="Transport and logistics")) -> FALSE | Z39: =OR(F39>Year_End_Window_End,AND(E39>=Year_End_Window_Start,F39>=Year_End_Window_Start)) -> FALSE
A40: INV-00036 | B40: V010 | C40: Thuraya Packaging | D40: 010-2025-0036 | E40: 45982 | F40: 45983 | G40: 46013 | H40: 30189.22 | I40: 3937.72 | J40: 26251.5 | K40: PO-00036 | L40: GR-00036 | M40: PAY-00036 | N40: 45995 | O40: Paid | P40: Transport and logistics | Q40: USR_NA | R40: USR_NA | S40: Approved | T40: Complete | U40: =F40-E40 -> 1 | V40: =H40>High_Value_AP_Threshold -> FALSE | W40: =COUNTIFS($B$5:$B$304,B40,$D$5:$D$304,D40)>1 -> FALSE | X40: =AND(K40="",P40<>"Utility service",P40<>"Campaign services") -> FALSE | Y40: =AND(L40="",OR(P40="Merchandise replenishment",P40="Office supplies",P40="Transport and logistics")) -> FALSE | Z40: =OR(F40>Year_End_Window_End,AND(E40>=Year_End_Window_Start,F40>=Year_End_Window_Start)) -> FALSE
A41: INV-00037 | B41: V002 | C41: Red Sand Facilities LLC | D41: 002-2025-0037 | E41: 45979 | F41: 45986 | G41: 46016 | H41: 8573.34 | I41: 1118.26 | J41: 7455.08 | K41: PO-00037 | L41: GR-00037 | O41: Pending | P41: Merchandise replenishment | Q41: USR_AH | R41: USR_OM | S41: Approved | T41: Complete | U41: =F41-E41 -> 7 | V41: =H41>High_Value_AP_Threshold -> FALSE | W41: =COUNTIFS($B$5:$B$304,B41,$D$5:$D$304,D41)>1 -> FALSE | X41: =AND(K41="",P41<>"Utility service",P41<>"Campaign services") -> FALSE | Y41: =AND(L41="",OR(P41="Merchandise replenishment",P41="Office supplies",P41="Transport and logistics")) -> FALSE | Z41: =OR(F41>Year_End_Window_End,AND(E41>=Year_End_Window_Start,F41>=Year_End_Window_Start)) -> FALSE
A42: INV-00038 | B42: V005 | C42: Rimal Utilities Provider | D42: 005-2025-0038 | E42: 45820 | F42: 45822 | G42: 45852 | H42: 72361.44 | I42: 9438.45 | J42: 62922.99 | K42: PO-00038 | M42: PAY-00038 | N42: 45863 | O42: Paid | P42: Campaign services | Q42: USR_FA | R42: USR_SA | S42: Pending | T42: Partial | U42: =F42-E42 -> 2 | V42: =H42>High_Value_AP_Threshold -> FALSE | W42: =COUNTIFS($B$5:$B$304,B42,$D$5:$D$304,D42)>1 -> FALSE | X42: =AND(K42="",P42<>"Utility service",P42<>"Campaign services") -> FALSE | Y42: =AND(L42="",OR(P42="Merchandise replenishment",P42="Office supplies",P42="Transport and logistics")) -> FALSE | Z42: =OR(F42>Year_End_Window_End,AND(E42>=Year_End_Window_Start,F42>=Year_End_Window_Start)) -> FALSE
A43: INV-00039 | B43: V003 | C43: Sahab IT Services | D43: 003-2025-0039 | E43: 45930 | F43: 45960 | G43: 45990 | H43: 27029.25 | I43: 3525.55 | J43: 23503.7 | K43: PO-00039 | L43: GR-00039 | O43: Pending | P43: Office supplies | Q43: USR_RE | R43: USR_OM | S43: Approved | T43: Complete | U43: =F43-E43 -> 30 | V43: =H43>High_Value_AP_Threshold -> FALSE | W43: =COUNTIFS($B$5:$B$304,B43,$D$5:$D$304,D43)>1 -> FALSE | X43: =AND(K43="",P43<>"Utility service",P43<>"Campaign services") -> FALSE | Y43: =AND(L43="",OR(P43="Merchandise replenishment",P43="Office supplies",P43="Transport and logistics")) -> FALSE | Z43: =OR(F43>Year_End_Window_End,AND(E43>=Year_End_Window_Start,F43>=Year_End_Window_Start)) -> FALSE
A44: INV-00040 | B44: V002 | C44: Red Sand Facilities LLC | D44: 002-2025-0040 | E44: 45720 | F44: 45735 | G44: 45765 | H44: 53258.95 | I44: 6946.82 | J44: 46312.13 | O44: Pending | P44: Utility service | Q44: USR_SA | R44: USR_FA | S44: Approved | T44: Missing | U44: =F44-E44 -> 15 | V44: =H44>High_Value_AP_Threshold -> FALSE | W44: =COUNTIFS($B$5:$B$304,B44,$D$5:$D$304,D44)>1 -> FALSE | X44: =AND(K44="",P44<>"Utility service",P44<>"Campaign services") -> FALSE | Y44: =AND(L44="",OR(P44="Merchandise replenishment",P44="Office supplies",P44="Transport and logistics")) -> FALSE | Z44: =OR(F44>Year_End_Window_End,AND(E44>=Year_End_Window_Start,F44>=Year_End_Window_Start)) -> FALSE
A45: INV-00041 | B45: V004 | C45: Wadi Marketing Studio | D45: 004-2025-0041 | E45: 45821 | F45: 45823 | G45: 45853 | H45: 56210.46 | I45: 7331.8 | J45: 48878.66 | M45: PAY-00041 | N45: 45859 | O45: Paid | P45: Campaign services | Q45: USR_AH | R45: USR_OM | S45: Approved | T45: Missing | U45: =F45-E45 -> 2 | V45: =H45>High_Value_AP_Threshold -> FALSE | W45: =COUNTIFS($B$5:$B$304,B45,$D$5:$D$304,D45)>1 -> FALSE | X45: =AND(K45="",P45<>"Utility service",P45<>"Campaign services") -> FALSE | Y45: =AND(L45="",OR(P45="Merchandise replenishment",P45="Office supplies",P45="Transport and logistics")) -> FALSE | Z45: =OR(F45>Year_End_Window_End,AND(E45>=Year_End_Window_Start,F45>=Year_End_Window_Start)) -> FALSE
A46: INV-00042 | B46: V004 | C46: Wadi Marketing Studio | D46: 004-2025-0042 | E46: 45743 | F46: 45746 | G46: 45776 | H46: 44277.66 | I46: 5775.35 | J46: 38502.31 | K46: PO-00042 | L46: GR-00042 | M46: PAY-00042 | N46: 45753 | O46: Paid | P46: Office supplies | Q46: USR_SA | R46: USR_NA | S46: Approved | T46: Complete | U46: =F46-E46 -> 3 | V46: =H46>High_Value_AP_Threshold -> FALSE | W46: =COUNTIFS($B$5:$B$304,B46,$D$5:$D$304,D46)>1 -> FALSE | X46: =AND(K46="",P46<>"Utility service",P46<>"Campaign services") -> FALSE | Y46: =AND(L46="",OR(P46="Merchandise replenishment",P46="Office supplies",P46="Transport and logistics")) -> FALSE | Z46: =OR(F46>Year_End_Window_End,AND(E46>=Year_End_Window_Start,F46>=Year_End_Window_Start)) -> FALSE
A47: INV-00043 | B47: V003 | C47: Sahab IT Services | D47: 003-2025-0043 | E47: 45717 | F47: 45718 | G47: 45748 | H47: 31912.45 | I47: 4162.49 | J47: 27749.96 | K47: PO-00043 | M47: PAY-00043 | N47: 45755 | O47: Paid | P47: Campaign services | Q47: USR_FA | R47: USR_OM | S47: Approved | T47: Partial | U47: =F47-E47 -> 1 | V47: =H47>High_Value_AP_Threshold -> FALSE | W47: =COUNTIFS($B$5:$B$304,B47,$D$5:$D$304,D47)>1 -> FALSE | X47: =AND(K47="",P47<>"Utility service",P47<>"Campaign services") -> FALSE | Y47: =AND(L47="",OR(P47="Merchandise replenishment",P47="Office supplies",P47="Transport and logistics")) -> FALSE | Z47: =OR(F47>Year_End_Window_End,AND(E47>=Year_End_Window_Start,F47>=Year_End_Window_Start)) -> FALSE
A48: INV-00044 | B48: V006 | C48: Palm Office Supplies | D48: 006-2025-0044 | E48: 45795 | F48: 45795 | G48: 45825 | H48: 50955.38 | I48: 6646.35 | J48: 44309.03 | K48: PO-00044 | O48: Pending | P48: Utility service | Q48: USR_NA | R48: USR_NA | S48: Approved | T48: Partial | U48: =F48-E48 -> 0 | V48: =H48>High_Value_AP_Threshold -> FALSE | W48: =COUNTIFS($B$5:$B$304,B48,$D$5:$D$304,D48)>1 -> FALSE | X48: =AND(K48="",P48<>"Utility service",P48<>"Campaign services") -> FALSE | Y48: =AND(L48="",OR(P48="Merchandise replenishment",P48="Office supplies",P48="Transport and logistics")) -> FALSE | Z48: =OR(F48>Year_End_Window_End,AND(E48>=Year_End_Window_Start,F48>=Year_End_Window_Start)) -> FALSE
A49: INV-00045 | B49: V005 | C49: Rimal Utilities Provider | D49: 005-2025-0045 | E49: 45945 | F49: 45948 | G49: 45978 | H49: 66247.8 | I49: 8641.02 | J49: 57606.78 | K49: PO-00045 | L49: GR-00045 | M49: PAY-00045 | N49: 45965 | O49: Paid | P49: Transport and logistics | Q49: USR_SA | R49: USR_NA | S49: Approved | T49: Complete | U49: =F49-E49 -> 3 | V49: =H49>High_Value_AP_Threshold -> FALSE | W49: =COUNTIFS($B$5:$B$304,B49,$D$5:$D$304,D49)>1 -> FALSE | X49: =AND(K49="",P49<>"Utility service",P49<>"Campaign services") -> FALSE | Y49: =AND(L49="",OR(P49="Merchandise replenishment",P49="Office supplies",P49="Transport and logistics")) -> FALSE | Z49: =OR(F49>Year_End_Window_End,AND(E49>=Year_End_Window_Start,F49>=Year_End_Window_Start)) -> FALSE
A50: INV-00046 | B50: V001 | C50: Najd Merchandising Co. | D50: 001-2025-0046 | E50: 45796 | F50: 45801 | G50: 45831 | H50: 3825.56 | I50: 498.99 | J50: 3326.57 | K50: PO-00046 | L50: GR-00046 | M50: PAY-00046 | N50: 45814 | O50: Paid | P50: Office supplies | Q50: USR_AH | R50: USR_OM | S50: Approved | T50: Complete | U50: =F50-E50 -> 5 | V50: =H50>High_Value_AP_Threshold -> FALSE | W50: =COUNTIFS($B$5:$B$304,B50,$D$5:$D$304,D50)>1 -> FALSE | X50: =AND(K50="",P50<>"Utility service",P50<>"Campaign services") -> FALSE | Y50: =AND(L50="",OR(P50="Merchandise replenishment",P50="Office supplies",P50="Transport and logistics")) -> FALSE | Z50: =OR(F50>Year_End_Window_End,AND(E50>=Year_End_Window_Start,F50>=Year_End_Window_Start)) -> FALSE
A51: INV-00047 | B51: V005 | C51: Rimal Utilities Provider | D51: 005-2025-0047 | E51: 45981 | F51: 45988 | G51: 46018 | H51: 27042.71 | I51: 3527.31 | J51: 23515.4 | K51: PO-00047 | L51: GR-00047 | M51: PAY-00047 | N51: 46026 | O51: Paid | P51: Merchandise replenishment | Q51: USR_RE | R51: USR_NA | S51: Approved | T51: Complete | U51: =F51-E51 -> 7 | V51: =H51>High_Value_AP_Threshold -> FALSE | W51: =COUNTIFS($B$5:$B$304,B51,$D$5:$D$304,D51)>1 -> FALSE | X51: =AND(K51="",P51<>"Utility service",P51<>"Campaign services") -> FALSE | Y51: =AND(L51="",OR(P51="Merchandise replenishment",P51="Office supplies",P51="Transport and logistics")) -> FALSE | Z51: =OR(F51>Year_End_Window_End,AND(E51>=Year_End_Window_Start,F51>=Year_End_Window_Start)) -> FALSE
A52: INV-00048 | B52: V007 | C52: Oasis Logistics | D52: 007-2025-0048 | E52: 45703 | F52: 45705 | G52: 45735 | H52: 32294.59 | I52: 4212.34 | J52: 28082.25 | K52: PO-00048 | M52: PAY-00048 | N52: 45728 | O52: Paid | P52: Cloud support services | Q52: USR_OM | R52: USR_SA | S52: Approved | T52: Partial | U52: =F52-E52 -> 2 | V52: =H52>High_Value_AP_Threshold -> FALSE | W52: =COUNTIFS($B$5:$B$304,B52,$D$5:$D$304,D52)>1 -> FALSE | X52: =AND(K52="",P52<>"Utility service",P52<>"Campaign services") -> FALSE | Y52: =AND(L52="",OR(P52="Merchandise replenishment",P52="Office supplies",P52="Transport and logistics")) -> FALSE | Z52: =OR(F52>Year_End_Window_End,AND(E52>=Year_End_Window_Start,F52>=Year_End_Window_Start)) -> FALSE
A53: INV-00049 | B53: V003 | C53: Sahab IT Services | D53: 003-2025-0049 | E53: 45842 | F53: 45857 | G53: 45887 | H53: 17500.12 | I53: 2282.62 | J53: 15217.5 | K53: PO-00049 | M53: PAY-00049 | N53: 45894 | O53: Paid | P53: Cloud support services | Q53: USR_OM | R53: USR_FA | S53: Approved | T53: Partial | U53: =F53-E53 -> 15 | V53: =H53>High_Value_AP_Threshold -> FALSE | W53: =COUNTIFS($B$5:$B$304,B53,$D$5:$D$304,D53)>1 -> FALSE | X53: =AND(K53="",P53<>"Utility service",P53<>"Campaign services") -> FALSE | Y53: =AND(L53="",OR(P53="Merchandise replenishment",P53="Office supplies",P53="Transport and logistics")) -> FALSE | Z53: =OR(F53>Year_End_Window_End,AND(E53>=Year_End_Window_Start,F53>=Year_End_Window_Start)) -> FALSE
A54: INV-00050 | B54: V010 | C54: Thuraya Packaging | D54: 010-2025-0050 | E54: 45731 | F54: 45731 | G54: 45761 | H54: 29849.69 | I54: 3893.44 | J54: 25956.25 | K54: PO-00050 | M54: PAY-00050 | N54: 45763 | O54: Paid | P54: Cloud support services | Q54: USR_RE | R54: USR_RE | S54: Approved | T54: Partial | U54: =F54-E54 -> 0 | V54: =H54>High_Value_AP_Threshold -> FALSE | W54: =COUNTIFS($B$5:$B$304,B54,$D$5:$D$304,D54)>1 -> FALSE | X54: =AND(K54="",P54<>"Utility service",P54<>"Campaign services") -> FALSE | Y54: =AND(L54="",OR(P54="Merchandise replenishment",P54="Office supplies",P54="Transport and logistics")) -> FALSE | Z54: =OR(F54>Year_End_Window_End,AND(E54>=Year_End_Window_Start,F54>=Year_End_Window_Start)) -> FALSE
A55: INV-00051 | B55: V009 | C55: Afaq Professional Services | D55: 009-2025-0051 | E55: 45765 | F55: 45765 | G55: 45795 | H55: 41383.07 | I55: 5397.79 | J55: 35985.28 | K55: PO-00051 | M55: PAY-00051 | N55: 45773 | O55: Paid | P55: Store maintenance | Q55: USR_OM | R55: USR_SA | S55: Pending | T55: Partial | U55: =F55-E55 -> 0 | V55: =H55>High_Value_AP_Threshold -> FALSE | W55: =COUNTIFS($B$5:$B$304,B55,$D$5:$D$304,D55)>1 -> FALSE | X55: =AND(K55="",P55<>"Utility service",P55<>"Campaign services") -> FALSE | Y55: =AND(L55="",OR(P55="Merchandise replenishment",P55="Office supplies",P55="Transport and logistics")) -> FALSE | Z55: =OR(F55>Year_End_Window_End,AND(E55>=Year_End_Window_Start,F55>=Year_End_Window_Start)) -> FALSE
A56: INV-00052 | B56: V004 | C56: Wadi Marketing Studio | D56: 004-2025-0052 | E56: 45693 | F56: 45723 | G56: 45753 | H56: 20053.67 | I56: 2615.7 | J56: 17437.97 | K56: PO-00052 | O56: Pending | P56: Campaign services | Q56: USR_OM | R56: USR_NA | S56: Approved | T56: Partial | U56: =F56-E56 -> 30 | V56: =H56>High_Value_AP_Threshold -> FALSE | W56: =COUNTIFS($B$5:$B$304,B56,$D$5:$D$304,D56)>1 -> FALSE | X56: =AND(K56="",P56<>"Utility service",P56<>"Campaign services") -> FALSE | Y56: =AND(L56="",OR(P56="Merchandise replenishment",P56="Office supplies",P56="Transport and logistics")) -> FALSE | Z56: =OR(F56>Year_End_Window_End,AND(E56>=Year_End_Window_Start,F56>=Year_End_Window_Start)) -> FALSE
A57: INV-00053 | B57: V003 | C57: Sahab IT Services | D57: 003-2025-0053 | E57: 45864 | F57: 45869 | G57: 45899 | H57: 69149.14 | I57: 9019.45 | J57: 60129.69 | M57: PAY-00053 | N57: 45879 | O57: Paid | P57: Campaign services | Q57: USR_OM | R57: USR_SA | S57: Approved | T57: Missing | U57: =F57-E57 -> 5 | V57: =H57>High_Value_AP_Threshold -> FALSE | W57: =COUNTIFS($B$5:$B$304,B57,$D$5:$D$304,D57)>1 -> FALSE | X57: =AND(K57="",P57<>"Utility service",P57<>"Campaign services") -> FALSE | Y57: =AND(L57="",OR(P57="Merchandise replenishment",P57="Office supplies",P57="Transport and logistics")) -> FALSE | Z57: =OR(F57>Year_End_Window_End,AND(E57>=Year_End_Window_Start,F57>=Year_End_Window_Start)) -> FALSE
A58: INV-00054 | B58: V006 | C58: Palm Office Supplies | D58: 006-2025-0054 | E58: 45954 | F58: 45969 | G58: 45999 | H58: 31912.36 | I58: 4162.48 | J58: 27749.88 | M58: PAY-00054 | N58: 46009 | O58: Paid | P58: Utility service | Q58: USR_RE | R58: USR_NA | S58: Approved | T58: Missing | U58: =F58-E58 -> 15 | V58: =H58>High_Value_AP_Threshold -> FALSE | W58: =COUNTIFS($B$5:$B$304,B58,$D$5:$D$304,D58)>1 -> FALSE | X58: =AND(K58="",P58<>"Utility service",P58<>"Campaign services") -> FALSE | Y58: =AND(L58="",OR(P58="Merchandise replenishment",P58="Office supplies",P58="Transport and logistics")) -> FALSE | Z58: =OR(F58>Year_End_Window_End,AND(E58>=Year_End_Window_Start,F58>=Year_End_Window_Start)) -> FALSE
A59: INV-00055 | B59: V007 | C59: Oasis Logistics | D59: 007-2025-0055 | E59: 45759 | F59: 45769 | G59: 45799 | H59: 35748 | I59: 4662.78 | J59: 31085.22 | K59: PO-00055 | M59: PAY-00055 | N59: 45785 | O59: Paid | P59: Utility service | Q59: USR_AH | R59: USR_RE | S59: Approved | T59: Partial | U59: =F59-E59 -> 10 | V59: =H59>High_Value_AP_Threshold -> FALSE | W59: =COUNTIFS($B$5:$B$304,B59,$D$5:$D$304,D59)>1 -> FALSE | X59: =AND(K59="",P59<>"Utility service",P59<>"Campaign services") -> FALSE | Y59: =AND(L59="",OR(P59="Merchandise replenishment",P59="Office supplies",P59="Transport and logistics")) -> FALSE | Z59: =OR(F59>Year_End_Window_End,AND(E59>=Year_End_Window_Start,F59>=Year_End_Window_Start)) -> FALSE
A60: INV-00056 | B60: V007 | C60: Oasis Logistics | D60: 007-2025-0056 | E60: 45872 | F60: 45872 | G60: 45902 | H60: 14401 | I60: 1878.39 | J60: 12522.61 | K60: PO-00056 | L60: GR-00056 | M60: PAY-00056 | N60: 45880 | O60: Paid | P60: Merchandise replenishment | Q60: USR_NA | R60: USR_OM | S60: Pending | T60: Complete | U60: =F60-E60 -> 0 | V60: =H60>High_Value_AP_Threshold -> FALSE | W60: =COUNTIFS($B$5:$B$304,B60,$D$5:$D$304,D60)>1 -> FALSE | X60: =AND(K60="",P60<>"Utility service",P60<>"Campaign services") -> FALSE | Y60: =AND(L60="",OR(P60="Merchandise replenishment",P60="Office supplies",P60="Transport and logistics")) -> FALSE | Z60: =OR(F60>Year_End_Window_End,AND(E60>=Year_End_Window_Start,F60>=Year_End_Window_Start)) -> FALSE
A61: INV-00057 | B61: V010 | C61: Thuraya Packaging | D61: 010-2025-0057 | E61: 45814 | F61: 45844 | G61: 45874 | H61: 66880.75 | I61: 8723.58 | J61: 58157.17 | K61: PO-00057 | M61: PAY-00057 | N61: 45867 | O61: Paid | P61: Utility service | Q61: USR_RE | R61: USR_OM | S61: Approved | T61: Partial | U61: =F61-E61 -> 30 | V61: =H61>High_Value_AP_Threshold -> FALSE | W61: =COUNTIFS($B$5:$B$304,B61,$D$5:$D$304,D61)>1 -> FALSE | X61: =AND(K61="",P61<>"Utility service",P61<>"Campaign services") -> FALSE | Y61: =AND(L61="",OR(P61="Merchandise replenishment",P61="Office supplies",P61="Transport and logistics")) -> FALSE | Z61: =OR(F61>Year_End_Window_End,AND(E61>=Year_End_Window_Start,F61>=Year_End_Window_Start)) -> FALSE
A62: INV-00058 | B62: V004 | C62: Wadi Marketing Studio | D62: 004-2025-0013 | E62: 45945 | F62: 45950 | G62: 45980 | H62: 28727.46 | I62: 3747.06 | J62: 24980.4 | K62: PO-00058 | L62: GR-00058 | O62: Pending | P62: Office supplies | Q62: USR_RE | R62: USR_OM | S62: Approved | T62: Complete | U62: =F62-E62 -> 5 | V62: =H62>High_Value_AP_Threshold -> FALSE | W62: =COUNTIFS($B$5:$B$304,B62,$D$5:$D$304,D62)>1 -> TRUE | X62: =AND(K62="",P62<>"Utility service",P62<>"Campaign services") -> FALSE | Y62: =AND(L62="",OR(P62="Merchandise replenishment",P62="Office supplies",P62="Transport and logistics")) -> FALSE | Z62: =OR(F62>Year_End_Window_End,AND(E62>=Year_End_Window_Start,F62>=Year_End_Window_Start)) -> FALSE
A63: INV-00059 | B63: V007 | C63: Oasis Logistics | D63: 007-2025-0059 | E63: 45750 | F63: 45760 | G63: 45790 | H63: 23675.16 | I63: 3088.06 | J63: 20587.1 | K63: PO-00059 | O63: Pending | P63: Campaign services | Q63: USR_OM | R63: USR_SA | S63: Approved | T63: Partial | U63: =F63-E63 -> 10 | V63: =H63>High_Value_AP_Threshold -> FALSE | W63: =COUNTIFS($B$5:$B$304,B63,$D$5:$D$304,D63)>1 -> FALSE | X63: =AND(K63="",P63<>"Utility service",P63<>"Campaign services") -> FALSE | Y63: =AND(L63="",OR(P63="Merchandise replenishment",P63="Office supplies",P63="Transport and logistics")) -> FALSE | Z63: =OR(F63>Year_End_Window_End,AND(E63>=Year_End_Window_Start,F63>=Year_End_Window_Start)) -> FALSE
A64: INV-00060 | B64: V006 | C64: Palm Office Supplies | D64: 006-2025-0060 | E64: 45694 | F64: 45709 | G64: 45739 | H64: 60518.84 | I64: 7893.76 | J64: 52625.08 | K64: PO-00060 | M64: PAY-00060 | N64: 45736 | O64: Paid | P64: Store maintenance | Q64: USR_RE | R64: USR_FA | S64: Approved | T64: Partial | U64: =F64-E64 -> 15 | V64: =H64>High_Value_AP_Threshold -> FALSE | W64: =COUNTIFS($B$5:$B$304,B64,$D$5:$D$304,D64)>1 -> FALSE | X64: =AND(K64="",P64<>"Utility service",P64<>"Campaign services") -> FALSE | Y64: =AND(L64="",OR(P64="Merchandise replenishment",P64="Office supplies",P64="Transport and logistics")) -> FALSE | Z64: =OR(F64>Year_End_Window_End,AND(E64>=Year_End_Window_Start,F64>=Year_End_Window_Start)) -> FALSE
A65: INV-00061 | B65: V007 | C65: Oasis Logistics | D65: 007-2025-0061 | E65: 45968 | F65: 45971 | G65: 46001 | H65: 42319.45 | I65: 5519.93 | J65: 36799.52 | K65: PO-00061 | L65: GR-00061 | M65: PAY-00061 | N65: 46008 | O65: Paid | P65: Merchandise replenishment | Q65: USR_AH | R65: USR_FA | S65: Approved | T65: Complete | U65: =F65-E65 -> 3 | V65: =H65>High_Value_AP_Threshold -> FALSE | W65: =COUNTIFS($B$5:$B$304,B65,$D$5:$D$304,D65)>1 -> FALSE | X65: =AND(K65="",P65<>"Utility service",P65<>"Campaign services") -> FALSE | Y65: =AND(L65="",OR(P65="Merchandise replenishment",P65="Office supplies",P65="Transport and logistics")) -> FALSE | Z65: =OR(F65>Year_End_Window_End,AND(E65>=Year_End_Window_Start,F65>=Year_End_Window_Start)) -> FALSE
A66: INV-00062 | B66: V006 | C66: Palm Office Supplies | D66: 006-2025-0062 | E66: 45662 | F66: 45663 | G66: 45693 | H66: 1155.51 | I66: 150.72 | J66: 1004.79 | K66: PO-00062 | M66: PAY-00062 | N66: 45705 | O66: Paid | P66: Store maintenance | Q66: USR_FA | R66: USR_RE | S66: Approved | T66: Partial | U66: =F66-E66 -> 1 | V66: =H66>High_Value_AP_Threshold -> FALSE | W66: =COUNTIFS($B$5:$B$304,B66,$D$5:$D$304,D66)>1 -> FALSE | X66: =AND(K66="",P66<>"Utility service",P66<>"Campaign services") -> FALSE | Y66: =AND(L66="",OR(P66="Merchandise replenishment",P66="Office supplies",P66="Transport and logistics")) -> FALSE | Z66: =OR(F66>Year_End_Window_End,AND(E66>=Year_End_Window_Start,F66>=Year_End_Window_Start)) -> FALSE
A67: INV-00063 | B67: V003 | C67: Sahab IT Services | D67: 003-2025-0063 | E67: 45878 | F67: 45881 | G67: 45911 | H67: 4527.08 | I67: 590.49 | J67: 3936.59 | K67: PO-00063 | M67: PAY-00063 | N67: 45908 | O67: Paid | P67: Store maintenance | Q67: USR_NA | R67: USR_FA | S67: Approved | T67: Partial | U67: =F67-E67 -> 3 | V67: =H67>High_Value_AP_Threshold -> FALSE | W67: =COUNTIFS($B$5:$B$304,B67,$D$5:$D$304,D67)>1 -> FALSE | X67: =AND(K67="",P67<>"Utility service",P67<>"Campaign services") -> FALSE | Y67: =AND(L67="",OR(P67="Merchandise replenishment",P67="Office supplies",P67="Transport and logistics")) -> FALSE | Z67: =OR(F67>Year_End_Window_End,AND(E67>=Year_End_Window_Start,F67>=Year_End_Window_Start)) -> FALSE
A68: INV-00064 | B68: V006 | C68: Palm Office Supplies | D68: 006-2025-0064 | E68: 45660 | F68: 45663 | G68: 45693 | H68: 1825.35 | I68: 238.09 | J68: 1587.26 | K68: PO-00064 | L68: GR-00064 | O68: Pending | P68: Office supplies | Q68: USR_FA | R68: USR_SA | S68: Approved | T68: Complete | U68: =F68-E68 -> 3 | V68: =H68>High_Value_AP_Threshold -> FALSE | W68: =COUNTIFS($B$5:$B$304,B68,$D$5:$D$304,D68)>1 -> FALSE | X68: =AND(K68="",P68<>"Utility service",P68<>"Campaign services") -> FALSE | Y68: =AND(L68="",OR(P68="Merchandise replenishment",P68="Office supplies",P68="Transport and logistics")) -> FALSE | Z68: =OR(F68>Year_End_Window_End,AND(E68>=Year_End_Window_Start,F68>=Year_End_Window_Start)) -> FALSE
A69: INV-00065 | B69: V006 | C69: Palm Office Supplies | D69: 006-2025-0065 | E69: 45938 | F69: 45953 | G69: 45983 | H69: 69416.62 | I69: 9054.34 | J69: 60362.28 | K69: PO-00065 | O69: Pending | P69: Cloud support services | Q69: USR_AH | R69: USR_OM | S69: Approved | T69: Partial | U69: =F69-E69 -> 15 | V69: =H69>High_Value_AP_Threshold -> FALSE | W69: =COUNTIFS($B$5:$B$304,B69,$D$5:$D$304,D69)>1 -> FALSE | X69: =AND(K69="",P69<>"Utility service",P69<>"Campaign services") -> FALSE | Y69: =AND(L69="",OR(P69="Merchandise replenishment",P69="Office supplies",P69="Transport and logistics")) -> FALSE | Z69: =OR(F69>Year_End_Window_End,AND(E69>=Year_End_Window_Start,F69>=Year_End_Window_Start)) -> FALSE
A70: INV-00066 | B70: V010 | C70: Thuraya Packaging | D70: 010-2025-0066 | E70: 45861 | F70: 45866 | G70: 45896 | H70: 32062.4 | I70: 4182.05 | J70: 27880.35 | K70: PO-00066 | M70: PAY-00066 | N70: 45905 | O70: Paid | P70: Utility service | Q70: USR_SA | R70: USR_RE | S70: Approved | T70: Partial | U70: =F70-E70 -> 5 | V70: =H70>High_Value_AP_Threshold -> FALSE | W70: =COUNTIFS($B$5:$B$304,B70,$D$5:$D$304,D70)>1 -> FALSE | X70: =AND(K70="",P70<>"Utility service",P70<>"Campaign services") -> FALSE | Y70: =AND(L70="",OR(P70="Merchandise replenishment",P70="Office supplies",P70="Transport and logistics")) -> FALSE | Z70: =OR(F70>Year_End_Window_End,AND(E70>=Year_End_Window_Start,F70>=Year_End_Window_Start)) -> FALSE
A71: INV-00067 | B71: V006 | C71: Palm Office Supplies | D71: 006-2025-0067 | E71: 45725 | F71: 45735 | G71: 45765 | H71: 13318 | I71: 1737.13 | J71: 11580.87 | K71: PO-00067 | L71: GR-00067 | M71: PAY-00067 | N71: 45771 | O71: Paid | P71: Office supplies | Q71: USR_RE | R71: USR_FA | S71: Approved | T71: Complete | U71: =F71-E71 -> 10 | V71: =H71>High_Value_AP_Threshold -> FALSE | W71: =COUNTIFS($B$5:$B$304,B71,$D$5:$D$304,D71)>1 -> FALSE | X71: =AND(K71="",P71<>"Utility service",P71<>"Campaign services") -> FALSE | Y71: =AND(L71="",OR(P71="Merchandise replenishment",P71="Office supplies",P71="Transport and logistics")) -> FALSE | Z71: =OR(F71>Year_End_Window_End,AND(E71>=Year_End_Window_Start,F71>=Year_End_Window_Start)) -> FALSE
A72: INV-00068 | B72: V009 | C72: Afaq Professional Services | D72: 009-2025-0068 | E72: 45974 | F72: 45975 | G72: 46005 | H72: 11583.93 | I72: 1510.95 | J72: 10072.98 | K72: PO-00068 | M72: PAY-00068 | N72: 45999 | O72: Paid | P72: Cloud support services | Q72: USR_SA | R72: USR_OM | S72: Approved | T72: Partial | U72: =F72-E72 -> 1 | V72: =H72>High_Value_AP_Threshold -> FALSE | W72: =COUNTIFS($B$5:$B$304,B72,$D$5:$D$304,D72)>1 -> FALSE | X72: =AND(K72="",P72<>"Utility service",P72<>"Campaign services") -> FALSE | Y72: =AND(L72="",OR(P72="Merchandise replenishment",P72="Office supplies",P72="Transport and logistics")) -> FALSE | Z72: =OR(F72>Year_End_Window_End,AND(E72>=Year_End_Window_Start,F72>=Year_End_Window_Start)) -> FALSE
A73: INV-00069 | B73: V002 | C73: Red Sand Facilities LLC | D73: 002-2025-0069 | E73: 45722 | F73: 45752 | G73: 45782 | H73: 18859.03 | I73: 2459.87 | J73: 16399.16 | K73: PO-00069 | M73: PAY-00069 | N73: 45762 | O73: Paid | P73: Cloud support services | Q73: USR_SA | R73: USR_RE | S73: Approved | T73: Partial | U73: =F73-E73 -> 30 | V73: =H73>High_Value_AP_Threshold -> FALSE | W73: =COUNTIFS($B$5:$B$304,B73,$D$5:$D$304,D73)>1 -> FALSE | X73: =AND(K73="",P73<>"Utility service",P73<>"Campaign services") -> FALSE | Y73: =AND(L73="",OR(P73="Merchandise replenishment",P73="Office supplies",P73="Transport and logistics")) -> FALSE | Z73: =OR(F73>Year_End_Window_End,AND(E73>=Year_End_Window_Start,F73>=Year_End_Window_Start)) -> FALSE
A74: INV-00070 | B74: V007 | C74: Oasis Logistics | D74: 007-2025-0070 | E74: 45907 | F74: 45908 | G74: 45938 | H74: 1108.67 | I74: 144.61 | J74: 964.06 | K74: PO-00070 | L74: GR-00070 | M74: PAY-00070 | N74: 45927 | O74: Paid | P74: Merchandise replenishment | Q74: USR_AH | R74: USR_OM | S74: Approved | T74: Complete | U74: =F74-E74 -> 1 | V74: =H74>High_Value_AP_Threshold -> FALSE | W74: =COUNTIFS($B$5:$B$304,B74,$D$5:$D$304,D74)>1 -> FALSE | X74: =AND(K74="",P74<>"Utility service",P74<>"Campaign services") -> FALSE | Y74: =AND(L74="",OR(P74="Merchandise replenishment",P74="Office supplies",P74="Transport and logistics")) -> FALSE | Z74: =OR(F74>Year_End_Window_End,AND(E74>=Year_End_Window_Start,F74>=Year_End_Window_Start)) -> FALSE
A75: INV-00071 | B75: V005 | C75: Rimal Utilities Provider | D75: 005-2025-0071 | E75: 45998 | F75: 45998 | G75: 46028 | H75: 60247.99 | I75: 7858.43 | J75: 52389.56 | K75: PO-00071 | L75: GR-00071 | M75: PAY-00071 | N75: 46033 | O75: Paid | P75: Merchandise replenishment | Q75: USR_AH | R75: USR_RE | S75: Approved | T75: Complete | U75: =F75-E75 -> 0 | V75: =H75>High_Value_AP_Threshold -> FALSE | W75: =COUNTIFS($B$5:$B$304,B75,$D$5:$D$304,D75)>1 -> FALSE | X75: =AND(K75="",P75<>"Utility service",P75<>"Campaign services") -> FALSE | Y75: =AND(L75="",OR(P75="Merchandise replenishment",P75="Office supplies",P75="Transport and logistics")) -> FALSE | Z75: =OR(F75>Year_End_Window_End,AND(E75>=Year_End_Window_Start,F75>=Year_End_Window_Start)) -> FALSE
A76: INV-00072 | B76: V003 | C76: Sahab IT Services | D76: 003-2025-0072 | E76: 45663 | F76: 45666 | G76: 45696 | H76: 62846.12 | I76: 8197.32 | J76: 54648.8 | K76: PO-00072 | L76: GR-00072 | M76: PAY-00072 | N76: 45701 | O76: Paid | P76: Office supplies | Q76: USR_AH | R76: USR_FA | S76: Approved | T76: Complete | U76: =F76-E76 -> 3 | V76: =H76>High_Value_AP_Threshold -> FALSE | W76: =COUNTIFS($B$5:$B$304,B76,$D$5:$D$304,D76)>1 -> FALSE | X76: =AND(K76="",P76<>"Utility service",P76<>"Campaign services") -> FALSE | Y76: =AND(L76="",OR(P76="Merchandise replenishment",P76="Office supplies",P76="Transport and logistics")) -> FALSE | Z76: =OR(F76>Year_End_Window_End,AND(E76>=Year_End_Window_Start,F76>=Year_End_Window_Start)) -> FALSE
A77: INV-00073 | B77: V001 | C77: Najd Merchandising Co. | D77: 001-2025-0073 | E77: 45787 | F77: 45790 | G77: 45820 | H77: 32896.88 | I77: 4290.9 | J77: 28605.98 | M77: PAY-00073 | N77: 45819 | O77: Paid | P77: Campaign services | Q77: USR_AH | R77: USR_RE | S77: Approved | T77: Missing | U77: =F77-E77 -> 3 | V77: =H77>High_Value_AP_Threshold -> FALSE | W77: =COUNTIFS($B$5:$B$304,B77,$D$5:$D$304,D77)>1 -> FALSE | X77: =AND(K77="",P77<>"Utility service",P77<>"Campaign services") -> FALSE | Y77: =AND(L77="",OR(P77="Merchandise replenishment",P77="Office supplies",P77="Transport and logistics")) -> FALSE | Z77: =OR(F77>Year_End_Window_End,AND(E77>=Year_End_Window_Start,F77>=Year_End_Window_Start)) -> FALSE
A78: INV-00074 | B78: V010 | C78: Thuraya Packaging | D78: 010-2025-0074 | E78: 45944 | F78: 45974 | G78: 46004 | H78: 46661.48 | I78: 6086.28 | J78: 40575.2 | K78: PO-00074 | M78: PAY-00074 | N78: 46003 | O78: Paid | P78: Store maintenance | Q78: USR_AH | R78: USR_OM | S78: Approved | T78: Partial | U78: =F78-E78 -> 30 | V78: =H78>High_Value_AP_Threshold -> FALSE | W78: =COUNTIFS($B$5:$B$304,B78,$D$5:$D$304,D78)>1 -> FALSE | X78: =AND(K78="",P78<>"Utility service",P78<>"Campaign services") -> FALSE | Y78: =AND(L78="",OR(P78="Merchandise replenishment",P78="Office supplies",P78="Transport and logistics")) -> FALSE | Z78: =OR(F78>Year_End_Window_End,AND(E78>=Year_End_Window_Start,F78>=Year_End_Window_Start)) -> FALSE
A79: INV-00075 | B79: V010 | C79: Thuraya Packaging | D79: 010-2025-0075 | E79: 45713 | F79: 45716 | G79: 45746 | H79: 17695.94 | I79: 2308.17 | J79: 15387.77 | K79: PO-00075 | O79: Pending | P79: Campaign services | Q79: USR_FA | R79: USR_SA | S79: Approved | T79: Partial | U79: =F79-E79 -> 3 | V79: =H79>High_Value_AP_Threshold -> FALSE | W79: =COUNTIFS($B$5:$B$304,B79,$D$5:$D$304,D79)>1 -> FALSE | X79: =AND(K79="",P79<>"Utility service",P79<>"Campaign services") -> FALSE | Y79: =AND(L79="",OR(P79="Merchandise replenishment",P79="Office supplies",P79="Transport and logistics")) -> FALSE | Z79: =OR(F79>Year_End_Window_End,AND(E79>=Year_End_Window_Start,F79>=Year_End_Window_Start)) -> FALSE
A80: INV-00076 | B80: V010 | C80: Thuraya Packaging | D80: 010-2025-0076 | E80: 45962 | F80: 45967 | G80: 45997 | H80: 1717.81 | I80: 224.06 | J80: 1493.75 | K80: PO-00076 | L80: GR-00076 | O80: Pending | P80: Merchandise replenishment | Q80: USR_FA | R80: USR_NA | S80: Approved | T80: Complete | U80: =F80-E80 -> 5 | V80: =H80>High_Value_AP_Threshold -> FALSE | W80: =COUNTIFS($B$5:$B$304,B80,$D$5:$D$304,D80)>1 -> FALSE | X80: =AND(K80="",P80<>"Utility service",P80<>"Campaign services") -> FALSE | Y80: =AND(L80="",OR(P80="Merchandise replenishment",P80="Office supplies",P80="Transport and logistics")) -> FALSE | Z80: =OR(F80>Year_End_Window_End,AND(E80>=Year_End_Window_Start,F80>=Year_End_Window_Start)) -> FALSE
A81: INV-00077 | B81: V008 | C81: Desert Star Maintenance | D81: 008-2025-0077 | E81: 45894 | F81: 45909 | G81: 45939 | H81: 24839.1 | I81: 3239.88 | J81: 21599.22 | K81: PO-00077 | M81: PAY-00077 | N81: 45954 | O81: Paid | P81: Cloud support services | Q81: USR_OM | R81: USR_OM | S81: Approved | T81: Partial | U81: =F81-E81 -> 15 | V81: =H81>High_Value_AP_Threshold -> FALSE | W81: =COUNTIFS($B$5:$B$304,B81,$D$5:$D$304,D81)>1 -> FALSE | X81: =AND(K81="",P81<>"Utility service",P81<>"Campaign services") -> FALSE | Y81: =AND(L81="",OR(P81="Merchandise replenishment",P81="Office supplies",P81="Transport and logistics")) -> FALSE | Z81: =OR(F81>Year_End_Window_End,AND(E81>=Year_End_Window_Start,F81>=Year_End_Window_Start)) -> FALSE
A82: INV-00078 | B82: V005 | C82: Rimal Utilities Provider | D82: 005-2025-0078 | E82: 45699 | F82: 45704 | G82: 45734 | H82: 8546.16 | I82: 1114.72 | J82: 7431.44 | M82: PAY-00078 | N82: 45723 | O82: Paid | P82: Utility service | Q82: USR_RE | R82: USR_OM | S82: Pending | T82: Missing | U82: =F82-E82 -> 5 | V82: =H82>High_Value_AP_Threshold -> FALSE | W82: =COUNTIFS($B$5:$B$304,B82,$D$5:$D$304,D82)>1 -> FALSE | X82: =AND(K82="",P82<>"Utility service",P82<>"Campaign services") -> FALSE | Y82: =AND(L82="",OR(P82="Merchandise replenishment",P82="Office supplies",P82="Transport and logistics")) -> FALSE | Z82: =OR(F82>Year_End_Window_End,AND(E82>=Year_End_Window_Start,F82>=Year_End_Window_Start)) -> FALSE
A83: INV-00079 | B83: V003 | C83: Sahab IT Services | D83: 003-2025-0079 | E83: 45979 | F83: 46009 | G83: 46039 | H83: 67802.87 | I83: 8843.85 | J83: 58959.02 | K83: PO-00079 | O83: Pending | P83: Campaign services | Q83: USR_FA | R83: USR_SA | S83: Approved | T83: Partial | U83: =F83-E83 -> 30 | V83: =H83>High_Value_AP_Threshold -> FALSE | W83: =COUNTIFS($B$5:$B$304,B83,$D$5:$D$304,D83)>1 -> FALSE | X83: =AND(K83="",P83<>"Utility service",P83<>"Campaign services") -> FALSE | Y83: =AND(L83="",OR(P83="Merchandise replenishment",P83="Office supplies",P83="Transport and logistics")) -> FALSE | Z83: =OR(F83>Year_End_Window_End,AND(E83>=Year_End_Window_Start,F83>=Year_End_Window_Start)) -> FALSE
A84: INV-00080 | B84: V004 | C84: Wadi Marketing Studio | D84: 004-2025-0080 | E84: 46012 | F84: 46022 | G84: 46052 | H84: 54024.65 | I84: 7046.69 | J84: 46977.96 | K84: PO-00080 | M84: PAY-00080 | N84: 46037 | O84: Paid | P84: Store maintenance | Q84: USR_AH | R84: USR_FA | S84: Approved | T84: Partial | U84: =F84-E84 -> 10 | V84: =H84>High_Value_AP_Threshold -> FALSE | W84: =COUNTIFS($B$5:$B$304,B84,$D$5:$D$304,D84)>1 -> FALSE | X84: =AND(K84="",P84<>"Utility service",P84<>"Campaign services") -> FALSE | Y84: =AND(L84="",OR(P84="Merchandise replenishment",P84="Office supplies",P84="Transport and logistics")) -> FALSE | Z84: =OR(F84>Year_End_Window_End,AND(E84>=Year_End_Window_Start,F84>=Year_End_Window_Start)) -> TRUE
A85: INV-00081 | B85: V010 | C85: Thuraya Packaging | D85: 010-2025-0081 | E85: 45825 | F85: 45827 | G85: 45857 | H85: 30091.59 | I85: 3924.99 | J85: 26166.6 | K85: PO-00081 | M85: PAY-00081 | N85: 45832 | O85: Paid | P85: Store maintenance | Q85: USR_SA | R85: USR_FA | S85: Approved | T85: Partial | U85: =F85-E85 -> 2 | V85: =H85>High_Value_AP_Threshold -> FALSE | W85: =COUNTIFS($B$5:$B$304,B85,$D$5:$D$304,D85)>1 -> FALSE | X85: =AND(K85="",P85<>"Utility service",P85<>"Campaign services") -> FALSE | Y85: =AND(L85="",OR(P85="Merchandise replenishment",P85="Office supplies",P85="Transport and logistics")) -> FALSE | Z85: =OR(F85>Year_End_Window_End,AND(E85>=Year_End_Window_Start,F85>=Year_End_Window_Start)) -> FALSE
A86: INV-00082 | B86: V010 | C86: Thuraya Packaging | D86: 010-2025-0082 | E86: 45894 | F86: 45894 | G86: 45924 | H86: 18211.63 | I86: 2375.43 | J86: 15836.2 | K86: PO-00082 | M86: PAY-00082 | N86: 45911 | O86: Paid | P86: Cloud support services | Q86: USR_AH | R86: USR_SA | S86: Approved | T86: Partial | U86: =F86-E86 -> 0 | V86: =H86>High_Value_AP_Threshold -> FALSE | W86: =COUNTIFS($B$5:$B$304,B86,$D$5:$D$304,D86)>1 -> FALSE | X86: =AND(K86="",P86<>"Utility service",P86<>"Campaign services") -> FALSE | Y86: =AND(L86="",OR(P86="Merchandise replenishment",P86="Office supplies",P86="Transport and logistics")) -> FALSE | Z86: =OR(F86>Year_End_Window_End,AND(E86>=Year_End_Window_Start,F86>=Year_End_Window_Start)) -> FALSE
A87: INV-00083 | B87: V003 | C87: Sahab IT Services | D87: 003-2025-0083 | E87: 45896 | F87: 45911 | G87: 45941 | H87: 72485.56 | I87: 9454.64 | J87: 63030.92 | K87: PO-00083 | M87: PAY-00083 | N87: 45943 | O87: Paid | P87: Utility service | Q87: USR_FA | R87: USR_NA | S87: Approved | T87: Partial | U87: =F87-E87 -> 15 | V87: =H87>High_Value_AP_Threshold -> FALSE | W87: =COUNTIFS($B$5:$B$304,B87,$D$5:$D$304,D87)>1 -> FALSE | X87: =AND(K87="",P87<>"Utility service",P87<>"Campaign services") -> FALSE | Y87: =AND(L87="",OR(P87="Merchandise replenishment",P87="Office supplies",P87="Transport and logistics")) -> FALSE | Z87: =OR(F87>Year_End_Window_End,AND(E87>=Year_End_Window_Start,F87>=Year_End_Window_Start)) -> FALSE
A88: INV-00084 | B88: V003 | C88: Sahab IT Services | D88: 003-2025-0084 | E88: 45757 | F88: 45758 | G88: 45788 | H88: 60518.07 | I88: 7893.66 | J88: 52624.41 | K88: PO-00084 | L88: GR-00084 | M88: PAY-00084 | N88: 45764 | O88: Paid | P88: Transport and logistics | Q88: USR_NA | R88: USR_OM | S88: Approved | T88: Complete | U88: =F88-E88 -> 1 | V88: =H88>High_Value_AP_Threshold -> FALSE | W88: =COUNTIFS($B$5:$B$304,B88,$D$5:$D$304,D88)>1 -> FALSE | X88: =AND(K88="",P88<>"Utility service",P88<>"Campaign services") -> FALSE | Y88: =AND(L88="",OR(P88="Merchandise replenishment",P88="Office supplies",P88="Transport and logistics")) -> FALSE | Z88: =OR(F88>Year_End_Window_End,AND(E88>=Year_End_Window_Start,F88>=Year_End_Window_Start)) -> FALSE
A89: INV-00085 | B89: V006 | C89: Palm Office Supplies | D89: 006-2025-0085 | E89: 45940 | F89: 45950 | G89: 45980 | H89: 70165.66 | I89: 9152.04 | J89: 61013.62 | K89: PO-00085 | O89: Pending | P89: Cloud support services | Q89: USR_AH | R89: USR_NA | S89: Approved | T89: Partial | U89: =F89-E89 -> 10 | V89: =H89>High_Value_AP_Threshold -> FALSE | W89: =COUNTIFS($B$5:$B$304,B89,$D$5:$D$304,D89)>1 -> FALSE | X89: =AND(K89="",P89<>"Utility service",P89<>"Campaign services") -> FALSE | Y89: =AND(L89="",OR(P89="Merchandise replenishment",P89="Office supplies",P89="Transport and logistics")) -> FALSE | Z89: =OR(F89>Year_End_Window_End,AND(E89>=Year_End_Window_Start,F89>=Year_End_Window_Start)) -> FALSE
A90: INV-00086 | B90: V009 | C90: Afaq Professional Services | D90: 009-2025-0086 | E90: 45945 | F90: 45952 | G90: 45982 | H90: 10460.94 | I90: 1364.47 | J90: 9096.47 | K90: PO-00086 | M90: PAY-00086 | N90: 45962 | O90: Paid | P90: Store maintenance | Q90: USR_NA | R90: USR_NA | S90: Approved | T90: Partial | U90: =F90-E90 -> 7 | V90: =H90>High_Value_AP_Threshold -> FALSE | W90: =COUNTIFS($B$5:$B$304,B90,$D$5:$D$304,D90)>1 -> FALSE | X90: =AND(K90="",P90<>"Utility service",P90<>"Campaign services") -> FALSE | Y90: =AND(L90="",OR(P90="Merchandise replenishment",P90="Office supplies",P90="Transport and logistics")) -> FALSE | Z90: =OR(F90>Year_End_Window_End,AND(E90>=Year_End_Window_Start,F90>=Year_End_Window_Start)) -> FALSE
A91: INV-00087 | B91: V006 | C91: Palm Office Supplies | D91: 006-2025-0087 | E91: 45827 | F91: 45832 | G91: 45862 | H91: 58184.17 | I91: 7589.24 | J91: 50594.93 | K91: PO-00087 | O91: Pending | P91: Store maintenance | Q91: USR_FA | R91: USR_NA | S91: Approved | T91: Partial | U91: =F91-E91 -> 5 | V91: =H91>High_Value_AP_Threshold -> FALSE | W91: =COUNTIFS($B$5:$B$304,B91,$D$5:$D$304,D91)>1 -> FALSE | X91: =AND(K91="",P91<>"Utility service",P91<>"Campaign services") -> FALSE | Y91: =AND(L91="",OR(P91="Merchandise replenishment",P91="Office supplies",P91="Transport and logistics")) -> FALSE | Z91: =OR(F91>Year_End_Window_End,AND(E91>=Year_End_Window_Start,F91>=Year_End_Window_Start)) -> FALSE
A92: INV-00088 | B92: V007 | C92: Oasis Logistics | D92: 007-2025-0088 | E92: 45949 | F92: 45954 | G92: 45984 | H92: 60038.5 | I92: 7831.11 | J92: 52207.39 | K92: PO-00088 | M92: PAY-00088 | N92: 45983 | O92: Paid | P92: Cloud support services | Q92: USR_FA | R92: USR_SA | S92: Approved | T92: Partial | U92: =F92-E92 -> 5 | V92: =H92>High_Value_AP_Threshold -> FALSE | W92: =COUNTIFS($B$5:$B$304,B92,$D$5:$D$304,D92)>1 -> FALSE | X92: =AND(K92="",P92<>"Utility service",P92<>"Campaign services") -> FALSE | Y92: =AND(L92="",OR(P92="Merchandise replenishment",P92="Office supplies",P92="Transport and logistics")) -> FALSE | Z92: =OR(F92>Year_End_Window_End,AND(E92>=Year_End_Window_Start,F92>=Year_End_Window_Start)) -> FALSE
A93: INV-00089 | B93: V004 | C93: Wadi Marketing Studio | D93: 004-2025-0089 | E93: 45910 | F93: 45915 | G93: 45945 | H93: 10821.7 | I93: 1411.53 | J93: 9410.17 | K93: PO-00089 | M93: PAY-00089 | N93: 45941 | O93: Paid | P93: Store maintenance | Q93: USR_AH | R93: USR_FA | S93: Approved | T93: Partial | U93: =F93-E93 -> 5 | V93: =H93>High_Value_AP_Threshold -> FALSE | W93: =COUNTIFS($B$5:$B$304,B93,$D$5:$D$304,D93)>1 -> FALSE | X93: =AND(K93="",P93<>"Utility service",P93<>"Campaign services") -> FALSE | Y93: =AND(L93="",OR(P93="Merchandise replenishment",P93="Office supplies",P93="Transport and logistics")) -> FALSE | Z93: =OR(F93>Year_End_Window_End,AND(E93>=Year_End_Window_Start,F93>=Year_End_Window_Start)) -> FALSE
A94: INV-00090 | B94: V001 | C94: Najd Merchandising Co. | D94: 001-2025-0090 | E94: 45758 | F94: 45761 | G94: 45791 | H94: 70394.38 | I94: 9181.88 | J94: 61212.5 | K94: PO-00090 | L94: GR-00090 | M94: PAY-00090 | N94: 45767 | O94: Paid | P94: Merchandise replenishment | Q94: USR_OM | R94: USR_FA | S94: Approved | T94: Complete | U94: =F94-E94 -> 3 | V94: =H94>High_Value_AP_Threshold -> FALSE | W94: =COUNTIFS($B$5:$B$304,B94,$D$5:$D$304,D94)>1 -> FALSE | X94: =AND(K94="",P94<>"Utility service",P94<>"Campaign services") -> FALSE | Y94: =AND(L94="",OR(P94="Merchandise replenishment",P94="Office supplies",P94="Transport and logistics")) -> FALSE | Z94: =OR(F94>Year_End_Window_End,AND(E94>=Year_End_Window_Start,F94>=Year_End_Window_Start)) -> FALSE
A95: INV-00091 | B95: V004 | C95: Wadi Marketing Studio | D95: 004-2025-0091 | E95: 45823 | F95: 45823 | G95: 45853 | H95: 63218.67 | I95: 8245.91 | J95: 54972.76 | K95: PO-00091 | M95: PAY-00091 | N95: 45830 | O95: Paid | P95: Utility service | Q95: USR_NA | R95: USR_SA | S95: Approved | T95: Partial | U95: =F95-E95 -> 0 | V95: =H95>High_Value_AP_Threshold -> FALSE | W95: =COUNTIFS($B$5:$B$304,B95,$D$5:$D$304,D95)>1 -> FALSE | X95: =AND(K95="",P95<>"Utility service",P95<>"Campaign services") -> FALSE | Y95: =AND(L95="",OR(P95="Merchandise replenishment",P95="Office supplies",P95="Transport and logistics")) -> FALSE | Z95: =OR(F95>Year_End_Window_End,AND(E95>=Year_End_Window_Start,F95>=Year_End_Window_Start)) -> FALSE
A96: INV-00092 | B96: V008 | C96: Desert Star Maintenance | D96: 008-2025-0092 | E96: 45828 | F96: 45831 | G96: 45861 | H96: 43154.42 | I96: 5628.84 | J96: 37525.58 | K96: PO-00092 | L96: GR-00092 | O96: Pending | P96: Transport and logistics | Q96: USR_OM | R96: USR_SA | S96: Approved | T96: Complete | U96: =F96-E96 -> 3 | V96: =H96>High_Value_AP_Threshold -> FALSE | W96: =COUNTIFS($B$5:$B$304,B96,$D$5:$D$304,D96)>1 -> FALSE | X96: =AND(K96="",P96<>"Utility service",P96<>"Campaign services") -> FALSE | Y96: =AND(L96="",OR(P96="Merchandise replenishment",P96="Office supplies",P96="Transport and logistics")) -> FALSE | Z96: =OR(F96>Year_End_Window_End,AND(E96>=Year_End_Window_Start,F96>=Year_End_Window_Start)) -> FALSE
A97: INV-00093 | B97: V010 | C97: Thuraya Packaging | D97: 010-2025-0093 | E97: 45741 | F97: 45741 | G97: 45771 | H97: 4503.05 | I97: 587.35 | J97: 3915.7 | K97: PO-00093 | L97: GR-00093 | O97: Pending | P97: Merchandise replenishment | Q97: USR_RE | R97: USR_NA | S97: Approved | T97: Complete | U97: =F97-E97 -> 0 | V97: =H97>High_Value_AP_Threshold -> FALSE | W97: =COUNTIFS($B$5:$B$304,B97,$D$5:$D$304,D97)>1 -> FALSE | X97: =AND(K97="",P97<>"Utility service",P97<>"Campaign services") -> FALSE | Y97: =AND(L97="",OR(P97="Merchandise replenishment",P97="Office supplies",P97="Transport and logistics")) -> FALSE | Z97: =OR(F97>Year_End_Window_End,AND(E97>=Year_End_Window_Start,F97>=Year_End_Window_Start)) -> FALSE
A98: INV-00094 | B98: V004 | C98: Wadi Marketing Studio | D98: 004-2025-0094 | E98: 45660 | F98: 45675 | G98: 45705 | H98: 38531.29 | I98: 5025.82 | J98: 33505.47 | K98: PO-00094 | M98: PAY-00094 | N98: 45709 | O98: Paid | P98: Cloud support services | Q98: USR_RE | R98: USR_RE | S98: Approved | T98: Partial | U98: =F98-E98 -> 15 | V98: =H98>High_Value_AP_Threshold -> FALSE | W98: =COUNTIFS($B$5:$B$304,B98,$D$5:$D$304,D98)>1 -> FALSE | X98: =AND(K98="",P98<>"Utility service",P98<>"Campaign services") -> FALSE | Y98: =AND(L98="",OR(P98="Merchandise replenishment",P98="Office supplies",P98="Transport and logistics")) -> FALSE | Z98: =OR(F98>Year_End_Window_End,AND(E98>=Year_End_Window_Start,F98>=Year_End_Window_Start)) -> FALSE
A99: INV-00095 | B99: V008 | C99: Desert Star Maintenance | D99: 008-2025-0095 | E99: 45951 | F99: 45956 | G99: 45986 | H99: 44838.42 | I99: 5848.49 | J99: 38989.93 | K99: PO-00095 | M99: PAY-00095 | N99: 45971 | O99: Paid | P99: Utility service | Q99: USR_NA | R99: USR_SA | S99: Approved | T99: Partial | U99: =F99-E99 -> 5 | V99: =H99>High_Value_AP_Threshold -> FALSE | W99: =COUNTIFS($B$5:$B$304,B99,$D$5:$D$304,D99)>1 -> FALSE | X99: =AND(K99="",P99<>"Utility service",P99<>"Campaign services") -> FALSE | Y99: =AND(L99="",OR(P99="Merchandise replenishment",P99="Office supplies",P99="Transport and logistics")) -> FALSE | Z99: =OR(F99>Year_End_Window_End,AND(E99>=Year_End_Window_Start,F99>=Year_End_Window_Start)) -> FALSE
A100: INV-00096 | B100: V005 | C100: Rimal Utilities Provider | D100: 005-2025-0096 | E100: 45925 | F100: 45932 | G100: 45962 | H100: 66884.32 | I100: 8724.04 | J100: 58160.28 | K100: PO-00096 | L100: GR-00096 | M100: PAY-00096 | N100: 45975 | O100: Paid | P100: Merchandise replenishment | Q100: USR_RE | R100: USR_FA | S100: Approved | T100: Complete | U100: =F100-E100 -> 7 | V100: =H100>High_Value_AP_Threshold -> FALSE | W100: =COUNTIFS($B$5:$B$304,B100,$D$5:$D$304,D100)>1 -> FALSE | X100: =AND(K100="",P100<>"Utility service",P100<>"Campaign services") -> FALSE | Y100: =AND(L100="",OR(P100="Merchandise replenishment",P100="Office supplies",P100="Transport and logistics")) -> FALSE | Z100: =OR(F100>Year_End_Window_End,AND(E100>=Year_End_Window_Start,F100>=Year_End_Window_Start)) -> FALSE
A101: INV-00097 | B101: V001 | C101: Najd Merchandising Co. | D101: 001-2025-0097 | E101: 45793 | F101: 45796 | G101: 45826 | H101: 58794.15 | I101: 7668.8 | J101: 51125.35 | K101: PO-00097 | L101: GR-00097 | M101: PAY-00097 | N101: 45818 | O101: Paid | P101: Transport and logistics | Q101: USR_NA | R101: USR_FA | S101: Pending | T101: Complete | U101: =F101-E101 -> 3 | V101: =H101>High_Value_AP_Threshold -> FALSE | W101: =COUNTIFS($B$5:$B$304,B101,$D$5:$D$304,D101)>1 -> FALSE | X101: =AND(K101="",P101<>"Utility service",P101<>"Campaign services") -> FALSE | Y101: =AND(L101="",OR(P101="Merchandise replenishment",P101="Office supplies",P101="Transport and logistics")) -> FALSE | Z101: =OR(F101>Year_End_Window_End,AND(E101>=Year_End_Window_Start,F101>=Year_End_Window_Start)) -> FALSE
...

Sheet 04_Analytics_Tests
A1: 04_Analytics_Tests — Test Catalog & Results
A2: Counts are screening flags, not confirmed misstatements. A transaction may trigger more than one test.
A4: Test_ID | B4: Test_Name | C4: Risk_Addressed | D4: Relevant_Assertion | E4: Data_Source | F4: Test_Logic | G4: Threshold | H4: Formula_or_Method | I4: Flagged_Transaction_Count | J4: Potential_Amount | K4: Interpretation | L4: Recommended_Follow_Up | M4: Test_Status
A5: AP-01 | B5: Duplicate supplier invoice numbers | C5: Duplicate recording or payment | D5: Accuracy / Occurrence | E5: 03_AP_Data | F5: Repeated Vendor_ID + Vendor_Invoice_Number | G5: Exact match | H5: COUNTIFS Vendor_ID + Vendor_Invoice_Number | I5: =COUNTIF('03_AP_Data'!W:W,TRUE()) -> 2 | J5: =SUMIF('03_AP_Data'!W:W,TRUE(),'03_AP_Data'!H:H) -> 88129.78 | K5: Repeated values may be legitimate credit notes or split allocations. | L5: Inspect invoice image, PO, receipt, payment evidence and vendor statement. | M5: Completed
A6: AP-02 | B6: Potential duplicate amounts | C6: Duplicate or erroneous invoice entry | D6: Accuracy / Occurrence | E6: 03_AP_Data | F6: Same vendor, equal amount, close invoice dates | G6: 90 days / SAR 0.01 | H6: Vendor + amount + date-window screening | I6: =COUNTIF('03_AP_Data'!W:W,TRUE()) -> 2 | J6: =SUMIF('03_AP_Data'!W:W,TRUE(),'03_AP_Data'!H:H) -> 88129.78 | K6: Preliminary similarity screen; recurring monthly payments may be legitimate. | L6: Compare invoice references, services received and payment records. | M6: Completed
A7: GL-01 | B7: High-value transactions | C7: Large or unusual posting risk | D7: Accuracy / Valuation | E7: 02_GL_Data + 03_AP_Data | F7: Absolute signed amount exceeds configured screen | G7: GL SAR 100,000 / AP SAR 75,000 | H7: ABS(Signed_Amount)>threshold or Gross_Amount>threshold | I7: =COUNTIF('02_GL_Data'!Y:Y,TRUE())+COUNTIF('03_AP_Data'!V:V,TRUE()) -> 59 | J7: =SUMIF('02_GL_Data'!Y:Y,TRUE(),'02_GL_Data'!L:L)+SUMIF('03_AP_Data'!V:V,TRUE(),'03_AP_Data'!H:H) -> 103500 | K7: Screening threshold is not audit materiality. | L7: Vouch approval, contract, receipt, calculation and posting. | M7: Completed
A8: GL-02 | B8: Year-end journal entries | C8: Cut-off or management override risk | D8: Cut-off / Occurrence | E8: 02_GL_Data | F8: Posting date in 16–31 Dec 2025 | G8: 16-Dec to 31-Dec | H8: AND(Posting_Date>=start,<=end) | I8: =COUNTIF('02_GL_Data'!V:V,TRUE()) -> 52 | J8: =SUMIF('02_GL_Data'!V:V,TRUE(),'02_GL_Data'!L:L) -> 0 | K8: Year-end timing alone does not prove error. | L8: Inspect support and subsequent reversal / settlement. | M8: Completed
A9: GL-03 | B9: Weekend postings | C9: Unauthorized or unusual timing | D9: Occurrence / Authorization | E9: 02_GL_Data | F9: Posting on Friday or Saturday | G9: Friday–Saturday | H9: WEEKDAY(Posting_Date,2) in {5,6} | I9: =COUNTIF('02_GL_Data'!W:W,TRUE()) -> 282 | J9: =SUMIF('02_GL_Data'!W:W,TRUE(),'02_GL_Data'!L:L) -> 0 | K9: Legitimate postings can occur on weekends. | L9: Review workflow logs, business rationale and approvals. | M9: Completed
A10: GL-04 | B10: After-hours journal entries | C10: Access, authorization or override risk | D10: Occurrence / Authorization | E10: 02_GL_Data | F10: Created outside 08:00–18:00 | G10: 08:00–18:00 | H10: HOUR(Creation_Timestamp) outside window | I10: =COUNTIF('02_GL_Data'!X:X,TRUE()) -> 444 | J10: =SUMIF('02_GL_Data'!X:X,TRUE(),'02_GL_Data'!L:L) -> 0 | K10: Timestamp is a review indicator and may reflect batch processing. | L10: Inspect system logs, user activity and approval trail. | M10: Completed
A11: GL-05 | B11: Round-number transactions | C11: Estimate or unsupported posting risk | D11: Accuracy / Valuation | E11: 02_GL_Data | F11: Absolute amount is threshold multiple | G11: SAR 10,000 multiple | H11: MOD(ABS(Signed_Amount),threshold)=0 | I11: =COUNTIF('02_GL_Data'!Z:Z,TRUE()) -> 2 | J11: =SUMIF('02_GL_Data'!Z:Z,TRUE(),'02_GL_Data'!L:L) -> 0 | K11: Round values are common in legitimate entries. | L11: Trace to contract, calculation and evidence of review. | M11: Completed
A12: AP-03 | B12: Missing supporting documentation | C12: Unrecorded or unsupported purchases | D12: Occurrence / Completeness | E12: 03_AP_Data | F12: Missing required PO, receipt or support by transaction type | G12: Rule-based | H12: Missing PO / receipt / support indicators | I12: =COUNTIF('03_AP_Data'!X:X,TRUE())+COUNTIF('03_AP_Data'!Y:Y,TRUE())+COUNTIF('03_AP_Data'!T:T,"Missing") -> 27 | J12: =SUMIF('03_AP_Data'!X:X,TRUE(),'03_AP_Data'!H:H)+SUMIF('03_AP_Data'!Y:Y,TRUE(),'03_AP_Data'!H:H) -> 393208.99 | K12: Some service types legitimately lack a PO or receipt. | L12: Obtain invoice, PO, receipt, approval and service evidence. | M12: Completed
A13: AP-04 | B13: Invoice and posting-date differences | C13: Period or processing delay risk | D13: Cut-off / Accuracy | E13: 03_AP_Data | F13: Invoice-to-posting days outside review limit | G13: >30 days | H13: Posting_Date - Invoice_Date | I13: =COUNTIF('03_AP_Data'!U:U,">"&Invoice_Posting_Review_Limit) -> 1 | J13: =SUMIF('03_AP_Data'!U:U,">"&Invoice_Posting_Review_Limit,'03_AP_Data'!H:H) -> 61400.11 | K13: Date differences may have valid operational explanations. | L13: Inspect receipt/service period and posting rationale. | M13: Completed
A14: AP-05 | B14: Potential cut-off exceptions | C14: Liability / expense cut-off risk | D14: Completeness / Cut-off | E14: 03_AP_Data | F14: Invoices around reporting date or posted after year-end | G14: 16–31 Dec plus post-year-end | H14: Is_Potential_Cutoff | I14: =COUNTIF('03_AP_Data'!Z:Z,TRUE()) -> 17 | J14: =SUMIF('03_AP_Data'!Z:Z,TRUE(),'03_AP_Data'!H:H) -> 541309.12 | K14: Not a complete subsequent-period test because no full Jan-2026 register is provided. | L14: Inspect goods receipt, service period and subsequent posting. | M14: Completed
A15: GL-06 | B15: Unusual account combinations | C15: Posting to wrong or sensitive account | D15: Classification / Accuracy | E15: 02_GL_Data | F15: Selected manual revenue-to-equipment combination | G15: Rule matrix | H15: Manual JE with revenue and PPE combination | I15: =COUNTIFS('02_GL_Data'!O:O,"MANUAL_JE",'02_GL_Data'!M:M,"*revenue*") -> 4 | J15: =SUMIFS('02_GL_Data'!L:L,'02_GL_Data'!O:O,"MANUAL_JE",'02_GL_Data'!M:M,"*revenue*") -> 0 | K15: Uncommon combinations require context, not automatic error classification. | L15: Review business purpose, authorization and account mapping. | M15: Completed
A16: GL-07 | B16: Unbalanced journal entries | C16: Data integrity / posting completeness | D16: Accuracy / Completeness | E16: 02_GL_Data | F16: Debit total differs from credit total by tolerance | G16: SAR 0.01 | H16: Grouped journal balance validation | I16: =COUNTIF('99_Internal_QA'!B:B,"Unbalanced") -> 0 | J16: =SUM('99_Internal_QA'!C:C) -> 1316 | K16: Primary GL population is designed to be balanced. | L16: Investigate source export and posting completeness if any. | M16: Completed
A17: GL-08 | B17: Potential segregation-of-duties conflicts | C17: Inadequate review separation | D17: Authorization | E17: 02_GL_Data | F17: Creator equals approver | G17: Same user | H17: Created_By=Approved_By | I17: =COUNTIF('99_Internal_QA'!B:B,"Creator=Approver") -> 0 | J17: =SUMIF('99_Internal_QA'!B:B,"Creator=Approver",'99_Internal_QA'!C:C) -> 0 | K17: Control-review indicator; not proof of fraud. | L17: Inspect role design, compensating review and access logs. | M17: Completed
A18: GL-09 | B18: Large or unusual manual entries | C18: Management override / manual posting risk | D18: Occurrence / Authorization | E18: 02_GL_Data | F18: Manual + high value, year-end, after-hours or sensitive combination | G18: Combined indicators | H18: Filter MANUAL_JE and intersect indicators | I18: =COUNTIFS('02_GL_Data'!O:O,"MANUAL_JE",'02_GL_Data'!Y:Y,TRUE())+COUNTIFS('02_GL_Data'!O:O,"MANUAL_JE",'02_GL_Data'!V:V,TRUE()) -> 66 | J18: =SUMIFS('02_GL_Data'!L:L,'02_GL_Data'!O:O,"MANUAL_JE") -> 0 | K18: Combined indicators reduce noise but may overlap with other tests. | L18: Inspect journal support, approval and rationale. | M18: Completed
A19: AP-06 | B19: Potential duplicate payments | C19: Repeated settlement risk | D19: Occurrence / Accuracy | E19: 03_AP_Data | F19: Preliminary invoice/payment reference screen only | G19: No separate payment register | H19: Not performed as a full payment test | I19: ="Not performed" -> Not performed | J19: ="Not available" -> Not available | K19: No separate payment register is provided; invoice/payment references support only preliminary screening. | L19: Obtain payment register or bank export for a full duplicate-payment test. | M19: Limited

Sheet 05_Exception_Register
A1: 05_Exception_Register — Consolidated Screening Exceptions
A2: Each row is a traceable transaction-test instance. Overlapping flags are not summed as confirmed misstatement.
A4: Exception_ID | B4: Test_ID | C4: Source_Dataset | D4: Journal_ID | E4: Journal_Line_ID | F4: Invoice_ID | G4: Vendor_ID | H4: Transaction_Date | I4: Account_Code | J4: Account_Name | K4: Amount | L4: Threshold_or_Rule | M4: Exception_Reason | N4: Risk_Category | O4: Relevant_Assertion | P4: Priority | Q4: Evidence_Required | R4: Recommended_Procedure | S4: Investigation_Status | T4: Investigation_Outcome | U4: Potential_Misstatement_Amount | V4: Adjustment_Required | W4: Reviewer_Notes
A5: EXC-0001 | B5: AP-03 | C5: AP | F5: INV-00009 | G5: V010 | H5: 45964 | K5: 43093.15 | L5: Required documentation indicators | M5: Missing support | N5: Unsupported purchase | O5: Occurrence / Completeness | P5: Medium | Q5: PO; goods receipt; invoice; approval | R5: Obtain and inspect missing supporting evidence | S5: Not Reviewed | T5: Not Reviewed | U5: 0 | V5: No
A6: EXC-0002 | B6: AP-01 | C6: AP | F6: INV-00013 | G6: V004 | H6: 45982 | K6: 59402.32 | L6: Repeated Vendor_ID + Vendor_Invoice_Number | M6: Repeated supplier invoice number detected | N6: Duplicate recording | O6: Accuracy / Occurrence | P6: Medium | Q6: Invoice image; vendor statement; payment support | R6: Compare invoice number, date, amount and payment evidence | S6: Not Reviewed | T6: Not Reviewed | U6: 0 | V6: No
A7: EXC-0003 | B7: AP-03 | C7: AP | F7: INV-00040 | G7: V002 | H7: 45735 | K7: 53258.95 | L7: Required documentation indicators | M7: Missing support | N7: Unsupported purchase | O7: Occurrence / Completeness | P7: Medium | Q7: PO; goods receipt; invoice; approval | R7: Obtain and inspect missing supporting evidence | S7: Not Reviewed | T7: Not Reviewed | U7: 0 | V7: No
A8: EXC-0004 | B8: AP-03 | C8: AP | F8: INV-00041 | G8: V004 | H8: 45823 | K8: 56210.46 | L8: Required documentation indicators | M8: Missing support | N8: Unsupported purchase | O8: Occurrence / Completeness | P8: Medium | Q8: PO; goods receipt; invoice; approval | R8: Obtain and inspect missing supporting evidence | S8: Not Reviewed | T8: Not Reviewed | U8: 0 | V8: No
A9: EXC-0005 | B9: AP-03 | C9: AP | F9: INV-00053 | G9: V003 | H9: 45869 | K9: 69149.14 | L9: Required documentation indicators | M9: Missing support | N9: Unsupported purchase | O9: Occurrence / Completeness | P9: Medium | Q9: PO; goods receipt; invoice; approval | R9: Obtain and inspect missing supporting evidence | S9: Not Reviewed | T9: Not Reviewed | U9: 0 | V9: No
A10: EXC-0006 | B10: AP-03 | C10: AP | F10: INV-00054 | G10: V006 | H10: 45969 | K10: 31912.36 | L10: Required documentation indicators | M10: Missing support | N10: Unsupported purchase | O10: Occurrence / Completeness | P10: Medium | Q10: PO; goods receipt; invoice; approval | R10: Obtain and inspect missing supporting evidence | S10: Not Reviewed | T10: Not Reviewed | U10: 0 | V10: No
A11: EXC-0007 | B11: AP-01 | C11: AP | F11: INV-00058 | G11: V004 | H11: 45950 | K11: 28727.46 | L11: Repeated Vendor_ID + Vendor_Invoice_Number | M11: Repeated supplier invoice number detected | N11: Duplicate recording | O11: Accuracy / Occurrence | P11: Medium | Q11: Invoice image; vendor statement; payment support | R11: Compare invoice number, date, amount and payment evidence | S11: Not Reviewed | T11: Not Reviewed | U11: 0 | V11: No
A12: EXC-0008 | B12: AP-03 | C12: AP | F12: INV-00073 | G12: V001 | H12: 45790 | K12: 32896.88 | L12: Required documentation indicators | M12: Missing support | N12: Unsupported purchase | O12: Occurrence / Completeness | P12: Medium | Q12: PO; goods receipt; invoice; approval | R12: Obtain and inspect missing supporting evidence | S12: Not Reviewed | T12: Not Reviewed | U12: 0 | V12: No
A13: EXC-0009 | B13: AP-03 | C13: AP | F13: INV-00078 | G13: V005 | H13: 45704 | K13: 8546.16 | L13: Required documentation indicators | M13: Missing support | N13: Unsupported purchase | O13: Occurrence / Completeness | P13: Medium | Q13: PO; goods receipt; invoice; approval | R13: Obtain and inspect missing supporting evidence | S13: Not Reviewed | T13: Not Reviewed | U13: 0 | V13: No
A14: EXC-0010 | B14: AP-01 | C14: AP | F14: INV-00101 | G14: V008 | H14: 46010 | K14: 22248.6 | L14: Repeated Vendor_ID + Vendor_Invoice_Number | M14: Repeated supplier invoice number detected | N14: Duplicate recording | O14: Accuracy / Occurrence | P14: Medium | Q14: Invoice image; vendor statement; payment support | R14: Compare invoice number, date, amount and payment evidence | S14: Not Reviewed | T14: Not Reviewed | U14: 0 | V14: No
A15: EXC-0011 | B15: AP-01 | C15: AP | F15: INV-00102 | G15: V008 | H15: 45946 | K15: 22248.6 | L15: Repeated Vendor_ID + Vendor_Invoice_Number | M15: Repeated supplier invoice number detected | N15: Duplicate recording | O15: Accuracy / Occurrence | P15: Medium | Q15: Invoice image; vendor statement; payment support | R15: Compare invoice number, date, amount and payment evidence | S15: Not Reviewed | T15: Not Reviewed | U15: 0 | V15: No
A16: EXC-0012 | B16: AP-03 | C16: AP | F16: INV-00102 | G16: V008 | H16: 45946 | K16: 22248.6 | L16: Required documentation indicators | M16: Missing support | N16: Unsupported purchase | O16: Occurrence / Completeness | P16: Medium | Q16: PO; goods receipt; invoice; approval | R16: Obtain and inspect missing supporting evidence | S16: Not Reviewed | T16: Not Reviewed | U16: 0 | V16: No
... A38: EXC-0034 | B38: AP-03 | C38: AP | F38: INV-00292 | G38: V008 | H38: 45917 | K38: 33899.26 | L38: Required documentation indicators | M38: Missing support | N38: Unsupported purchase | O38: Occurrence / Completeness | P38: Medium | Q38: PO; goods receipt; invoice; approval | R38: Obtain and inspect missing supporting evidence | S38: Not Reviewed | T38: Not Reviewed | U38: 0 | V38: No
A39: EXC-0035 | B39: GL-03 | C39: GL | D39: JE-00012 | E39: JE-00012-01 | H39: 45737 | I39: 6000 | J39: Salaries Expense | K39: 74307.73 | L39: Configured screening rule | M39: Friday/Saturday posting | N39: Timing / authorization | O39: Occurrence / Authorization | P39: Medium | Q39: Workflow logs; approval; rationale | R39: Review supporting evidence and control context | S39: Not Reviewed | T39: Not Reviewed | U39: 0 | V39: No
A40: EXC-0036 | B40: GL-04 | C40: GL | D40: JE-00013 | E40: JE-00013-01 | H40: 46006 | I40: 1100 | J40: Trade Receivables | K40: 33640.64 | L40: Configured screening rule | M40: Created outside 08:00–18:00 | N40: Timing / authorization | O40: Occurrence / Authorization | P40: Medium | Q40: Workflow logs; approval; rationale | R40: Review supporting evidence and control context | S40: Not Reviewed | T40: Not Reviewed | U40: 0 | V40: No
A41: EXC-0037 | B41: GL-05 | C41: GL | D41: JE-00014 | E41: JE-00014-01 | H41: 45877 | I41: 6000 | J41: Salaries Expense | K41: 50000 | L41: Configured screening rule | M41: Exact round-number amount | N41: Timing / authorization | O41: Occurrence / Authorization | P41: Medium | Q41: Workflow logs; approval; rationale | R41: Review supporting evidence and control context | S41: Not Reviewed | T41: Not Reviewed | U41: 0 | V41: No
A42: EXC-0038 | B42: GL-08 | C42: GL | D42: JE-00015 | E42: JE-00015-01 | H42: 45935 | I42: 6600 | J42: Other Operating Expenses | K42: 51634.78 | L42: Configured screening rule | M42: Creator and approver are identical | N42: Timing / authorization | O42: Occurrence / Authorization | P42: Medium | Q42: Workflow logs; approval; rationale | R42: Review supporting evidence and control context | S42: Not Reviewed | T42: Not Reviewed | U42: 0 | V42: No
A43: EXC-0039 | B43: GL-06 | C43: GL | D43: JE-00016 | E43: JE-00016-01 | H43: 45753 | I43: 4000 | J43: Sales Revenue | K43: 81715.31 | L43: Configured screening rule | M43: Unusual manual account combination | N43: Timing / authorization | O43: Occurrence / Authorization | P43: Medium | Q43: Workflow logs; approval; rationale | R43: Review supporting evidence and control context | S43: Not Reviewed | T43: Not Reviewed | U43: 0 | V43: No
A44: EXC-0040 | B44: GL-01 | C44: GL | D44: JE-00045 | E44: JE-00045-01 | H44: 45876 | I44: 6300 | J44: Marketing Expense | K44: 145000 | L44: ABS(Signed_Amount) > SAR 100,000 | M44: High-value GL line | N44: Valuation / authorization | O44: Accuracy / Valuation | P44: High | Q44: Journal support; approval; contract | R44: Vouch the journal and assess authorization | S44: Not Reviewed | T44: Not Reviewed | U44: 0 | V44: No
A45: EXC-0041 | B45: GL-02 | C45: GL | D45: JE-00480 | E45: JE-00480-01 | H45: 46020 | I45: 6500 | J45: Depreciation Expense | K45: 62046.1 | L45: Posting date 16–31 Dec 2025 | M45: Manual year-end journal entry | N45: Cut-off / override | O45: Cut-off / Occurrence | P45: High | Q45: Support; reversal; approval | R45: Inspect support and subsequent reversal | S45: Not Reviewed | T45: Not Reviewed | U45: 0 | V45: No

Sheet 06_Dashboard
A1: 06_Dashboard — Executive Analytics Overview
A2: Namaa Retail Company (fictional) | Reporting period: 2025 | All values are screening indicators from synthetic data
A4: Total GL journal entries | D4: Total GL lines | G4: Total AP invoices | J4: Analytics tests completed | M4: Total exception instances
A5: =COUNTA('02_GL_Data'!A5:A1004)/2 -> 500 | D5: =COUNTA('02_GL_Data'!B5:B1004) -> 1000 | G5: =COUNTA('03_AP_Data'!A5:A304) -> 300 | J5: =COUNTIF('04_Analytics_Tests'!M5:M19,"Completed") -> 14 | M5: =COUNTA('05_Exception_Register'!A5:A200) -> 41
A7: Unique transactions flagged (QA key) | D7: High-priority exceptions | G7: Exceptions awaiting review | J7: Confirmed simulated errors | M7: Confirmed simulated misstatement amount
A8: =COUNTA('99_Internal_QA'!G5:G200) -> 38 | D8: =COUNTIF('05_Exception_Register'!P5:P200,"High") -> 5 | G8: =COUNTIF('05_Exception_Register'!S5:S200,"Not Reviewed") -> 41 | J8: =COUNTIF('05_Exception_Register'!T5:T200,"Confirmed Error") -> 0 | M8: =SUM('05_Exception_Register'!U5:U200) -> 0
A20: Chart 1 — Exceptions by Test
A21: Test_ID | B21: Flagged Count | D21: Priority | E21: Count | G21: Account Type | H21: Count | J21: Month | K21: Count
A22: AP-01 | B22: =COUNTIF('05_Exception_Register'!B:B,A22) -> 4 | D22: High | E22: =COUNTIF('05_Exception_Register'!P:P,D22) -> 5 | G22: Asset | H22: =COUNTIF('05_Exception_Register'!N:N,"*Asset*") -> 0 | J22: 45658 | K22: =COUNTIFS('05_Exception_Register'!H:H,">="&J22,'05_Exception_Register'!H:H,"<"&EDATE(J22,1)) -> 1
A23: AP-02 | B23: =COUNTIF('05_Exception_Register'!B:B,A23) -> 0 | D23: Medium | E23: =COUNTIF('05_Exception_Register'!P:P,D23) -> 36 | G23: Liability | H23: =COUNTIF('05_Exception_Register'!N:N,"*Liability*") -> 0 | J23: 45689 | K23: =COUNTIFS('05_Exception_Register'!H:H,">="&J23,'05_Exception_Register'!H:H,"<"&EDATE(J23,1)) -> 2
A24: GL-01 | B24: =COUNTIF('05_Exception_Register'!B:B,A24) -> 2 | D24: Low | E24: =COUNTIF('05_Exception_Register'!P:P,D24) -> 0 | G24: Expense | H24: =COUNTIF('05_Exception_Register'!N:N,"*Expense*") -> 0 | J24: 45717 | K24: =COUNTIFS('05_Exception_Register'!H:H,">="&J24,'05_Exception_Register'!H:H,"<"&EDATE(J24,1)) -> 4
A25: GL-02 | B25: =COUNTIF('05_Exception_Register'!B:B,A25) -> 1 | G25: Revenue | H25: =COUNTIF('05_Exception_Register'!N:N,"*Revenue*") -> 0 | J25: 45748 | K25: =COUNTIFS('05_Exception_Register'!H:H,">="&J25,'05_Exception_Register'!H:H,"<"&EDATE(J25,1)) -> 2
A26: GL-03 | B26: =COUNTIF('05_Exception_Register'!B:B,A26) -> 1 | G26: Other Income | H26: =COUNTIF('05_Exception_Register'!N:N,"*Other Income*") -> 0 | J26: 45778 | K26: =COUNTIFS('05_Exception_Register'!H:H,">="&J26,'05_Exception_Register'!H:H,"<"&EDATE(J26,1)) -> 4
A27: GL-04 | B27: =COUNTIF('05_Exception_Register'!B:B,A27) -> 1 | J27: 45809 | K27: =COUNTIFS('05_Exception_Register'!H:H,">="&J27,'05_Exception_Register'!H:H,"<"&EDATE(J27,1)) -> 2
A28: GL-05 | B28: =COUNTIF('05_Exception_Register'!B:B,A28) -> 1 | J28: 45839 | K28: =COUNTIFS('05_Exception_Register'!H:H,">="&J28,'05_Exception_Register'!H:H,"<"&EDATE(J28,1)) -> 2
A29: AP-03 | B29: =COUNTIF('05_Exception_Register'!B:B,A29) -> 25 | J29: 45870 | K29: =COUNTIFS('05_Exception_Register'!H:H,">="&J29,'05_Exception_Register'!H:H,"<"&EDATE(J29,1)) -> 2
A30: AP-04 | B30: =COUNTIF('05_Exception_Register'!B:B,A30) -> 1 | J30: 45901 | K30: =COUNTIFS('05_Exception_Register'!H:H,">="&J30,'05_Exception_Register'!H:H,"<"&EDATE(J30,1)) -> 3
A31: AP-05 | B31: =COUNTIF('05_Exception_Register'!B:B,A31) -> 3 | J31: 45931 | K31: =COUNTIFS('05_Exception_Register'!H:H,">="&J31,'05_Exception_Register'!H:H,"<"&EDATE(J31,1)) -> 6
A32: GL-06 | B32: =COUNTIF('05_Exception_Register'!B:B,A32) -> 1 | J32: 45962 | K32: =COUNTIFS('05_Exception_Register'!H:H,">="&J32,'05_Exception_Register'!H:H,"<"&EDATE(J32,1)) -> 3
A33: GL-07 | B33: =COUNTIF('05_Exception_Register'!B:B,A33) -> 0 | J33: 45992 | K33: =COUNTIFS('05_Exception_Register'!H:H,">="&J33,'05_Exception_Register'!H:H,"<"&EDATE(J33,1)) -> 7
A34: GL-08 | B34: =COUNTIF('05_Exception_Register'!B:B,A34) -> 1
A35: GL-09 | B35: =COUNTIF('05_Exception_Register'!B:B,A35) -> 0
A36: AP-06 | B36: =COUNTIF('05_Exception_Register'!B:B,A36) -> 0
A72: Interpretation note: exception instances may overlap across tests. They identify items for investigation and are not aggregated as total misstatement. Confirmed simulated errors are reported separately and may be zero.

Sheet 07_Audit_Memo
A1: 07_Audit_Memo — Audit Analytics Memorandum Summary
A2: This worksheet summarizes the accompanying PDF memorandum; it is not an audit opinion.
A4: To | B4: Portfolio reviewer / interview audience
A5: From | B5: Accounting Student — Educational Portfolio Project.
A6: Subject | B6: Audit data analytics simulation — GL and AP exception screening
A7: Executive Summary | B7: The analysis screened 1,000 synthetic GL lines and 300 synthetic AP invoices using 15 documented tests. The screening identified traceable anomalies involving duplicate invoice numbers, high-value items, timing, documentation, cut-off, manual journals and approval indicators. These are potential exceptions requiring evidence-based follow-up, not confirmed fraud or misstatement conclusions.
A8: Scope and Methodology | B8: The simulation covers 01-Jan-2025 to 31-Dec-2025. GL entries were generated as balanced two-line journal entries and AP records use Gross = Net + illustrative VAT. Formula-driven indicators reference centralized parameters. Exceptions are consolidated by transaction-test instance to preserve traceability and avoid presenting overlapping flags as one misstatement.
A9: Data Quality Results | B9: The internal QA build checks confirm unique journal and line identifiers, balanced GL entries, valid account mappings, AP amount reconciliation and consistent vendor references. The workbook includes a hidden internal QA key documenting designed scenarios and detection coverage.
A10: Key Limitations | B10: All records are synthetic and fictional. No real ledger, invoice, bank register, confirmation or external evidence was accessed. There is no complete subsequent-period AP population, so AP-05 is an illustrative cut-off screen rather than a complete subsequent-disbursements test. Analytics flags require investigation.
A11: Recommended Actions | B11: For the fictional scenario: strengthen duplicate invoice controls, retain supporting documentation, review manual journal approval and segregation-of-duties design, and formalize period-end cut-off procedures.
A12: Conclusion | B12: The tests demonstrate how full-population screening can prioritize audit follow-up. Appropriate next steps would be to obtain and inspect supporting evidence, evaluate explanations, determine whether any error exists, and document a conclusion for each exception. The work does not provide an audit opinion or assurance conclusion.

Sheet 99_Internal_QA
A1: Internal QA Validation Key
A2: Build log / validation support — not an audit working paper.
A4: Scenario | B4: QA_Status | C4: Amount_or_Count | D4: Intended_Detection | E4: Notes | G4: Unique_Transaction_Key
A5: GL journal balance | B5: Balanced | C5: 0 | D5: GL-07 | E5: All 500 journal IDs balance exactly. | G5: |INV-00009
A6: GL identifiers | B6: Pass | C6: 1000 | D6: Data validation | E6: Journal line IDs unique. | G6: |INV-00013
A7: AP amount reconciliation | B7: Pass | C7: 300 | D7: Data validation | E7: Gross = Net + VAT across all AP records. | G7: |INV-00040
A8: Duplicate invoice scenario | B8: Designed | C8: 2 | D8: AP-01 | E8: Two records share vendor invoice number. | G8: |INV-00041
A9: High-value GL scenario | B9: Designed | C9: 1 | D9: GL-01 | E9: JE-00045 contains SAR 145,000 line. | G9: |INV-00053
A10: Year-end manual scenario | B10: Designed | C10: 1 | D10: GL-02 | E10: JE-00480 posted 29-Dec-2025. | G10: |INV-00054
A11: Weekend scenario | B11: Designed | C11: 1 | D11: GL-03 | E11: JE-00012 posted Friday. | G11: |INV-00058
A12: After-hours scenario | B12: Designed | C12: 1 | D12: GL-04 | E12: JE-00013 created 23:30. | G12: |INV-00073
A13: Round-number scenario | B13: Designed | C13: 1 | D13: GL-05 | E13: JE-00014 contains SAR 50,000. | G13: |INV-00078
A14: SOD scenario | B14: Designed | C14: 1 | D14: GL-08 | E14: JE-00015 creator equals approver. | G14: |INV-00101
A15: Unusual combination scenario | B15: Designed | C15: 1 | D15: GL-06 | E15: JE-00016 manual revenue/equipment transfer. | G15: |INV-00102
A16: AP documentation scenarios | B16: Designed | C16: 3 | D16: AP-03 | E16: Missing PO/receipt/support examples. | G16: |INV-00131
... A18: AP cut-off scenarios | B18: Designed | C18: 3 | D18: AP-05 | E18: Records around and after 31-Dec-2025. | G18: |INV-00173
G19: |INV-00179
G20: |INV-00190
G21: |INV-00200
G22: |INV-00206
G23: |INV-00208
G24: |INV-00220
G25: |INV-00252
G26: |INV-00265
G27: |INV-00270
G28: |INV-00274
G29: |INV-00277
G30: |INV-00279
... G42: JE-00480|
